Workbook

Sheet Cover
A16: TIMES-Ireland Model
A19: Document type: | B19: New Technologies
A20: Sector(s): | B20: Power sector (PWR)
A21: Purpose: | B21: Specify techno-economic data for new generation technologies
A23: Original developer(s): | B23: Xiufeng Yue (UCC, xiufeng.yue@ucc.ie)
B24: James Glynn (UCC, james.glynn@ucc.ie)
A26: Current maintainer(s): | B26: Olexandr Balyk (UCC, olexandr.balyk@ucc.ie)
A29: Part of TIM version: | B29: 1
A30: Model repository: | B30: https://github.com/MaREI-EPMG/TIMES-Ireland-model
A31: Licence: | B31: CC BY-NC-SA 4.0 (unless specified otherwise)
B32: https://creativecommons.org/licenses/by-nc-sa/4.0/

Sheet ELC_EGP
A1: Electricity Generators Database
A2: Source: ETRI 2014 (https://setis.ec.europa.eu/publications/jrc-setis-reports/etri-2014 )
F3: ~FI_T: MEUR2015 | AL3: ~FI_Process
A4: TechName | B4: *Cost data Source | C4: *Effieiency Data source | D4: *TechDesc | E4: Comm-IN | F4: Comm-OUT | G4: EFF | H4: EFF~2020 | I4: EFF~2030 | J4: EFF~2040 | K4: EFF~2050 | L4: Start | M4: INVCOST~2015 | N4: INVCOST~2020 | O4: INVCOST~2030 | P4: INVCOST~2040 | Q4: INVCOST~2050 | R4: FIXOM | S4: FIXOM~2020 | T4: FIXOM~2030 | U4: FIXOM~2040 | V4: FIXOM~2050 | W4: VAROM | X4: VAROM~2020 | Y4: VAROM~2030 | Z4: VAROM~2040 | AA4: VAROM~2050 | AB4: LIFE | AC4: LIFE~2020 | AD4: LIFE~2030 | AE4: Cap2Act | AF4: AFA | AG4: AFA~2020 | AH4: AFA~2030 | AI4: AFA~2040 | AJ4: AFA~2050 | AL4: Sets | AM4: TechName | AN4: TechDesc | AO4: Tact | AP4: Tcap | AQ4: Tslvl | AR4: PrimaryCG | AS4: Vintage
A5: *Technology Name | D5: Technology Description | E5: Input Commodity | F5: Output Commodity | G5: Efficiency | M5: CAPEX REF (€2013/kW) | R5: FOM (€2013/kW) | W5: VOM (€2013/GJ) | AB5: Technical life | AF5: Max. capacity factor | AL5: *Process Set Membership | AM5: Technology Name | AN5: Technology Description | AO5: Activity Unit | AP5: Capacity Unit | AQ5: TimeSlice Level | AR5: Primary CommGrp | AS5: Vintage Tracking
A6: *P-RNW-WIN-OF02 | B6: ETRI2018 | D6: ="PWR "&AW6&" new" -> PWR Offshore wind new | E6: PWRWIN | F6: ELCC | G6: 1 | L6: 2019 | M6: =3118 -> 3118 | Q6: 2827 | R6: 128.39 | S6: 92.16 | T6: 77.4 | U6: 66.64 | V6: 52.44 | AB6: 20 | AC6: 25 | AD6: 30 | AE6: 31.536 | AL6: ELE | AM6: P-RNW-WIN-OF02 | AN6: =D6 -> PWR Offshore wind new | AO6: PJ | AP6: GW | AQ6: DAYNITE | AW6: Offshore wind
A7: P-RNW-SOL-PV01 | B7: ETRI2018 | D7: ="PWR "&AW7&" new" -> PWR Commercial solar PV system 0.1-2 MW new | E7: PWRSOL | F7: ELCC | G7: 1 | L7: 2019 | M7: 500 | Q7: 670 | R7: 27.5 | S7: 22.5 | T7: 20.25 | U7: 19 | V7: 18 | AB7: 25 | AE7: 31.536 | AL7: ELE | AM7: =A7 -> P-RNW-SOL-PV01 | AN7: =D7 -> PWR Commercial solar PV system 0.1-2 MW new | AO7: PJ | AP7: GW | AQ7: DAYNITE | AW7: Commercial solar PV system 0.1-2 MW
A8: P-RNW-SOL-PV02 | B8: ETRI2018 | D8: ="PWR "&AW8&" new" -> PWR Commercial solar PV >2 MW without tracking new | E8: PWRSOL | F8: ELCC | G8: 1 | L8: 2019 | M8: =+M7 -> 500 | Q8: =+Q7 -> 670 | R8: 16.66 | S8: 13.6 | T8: 10.88 | U8: 9.86 | V8: 8.84 | AB8: 25 | AE8: 31.536 | AL8: ELE | AM8: =A8 -> P-RNW-SOL-PV02 | AN8: =D8 -> PWR Commercial solar PV >2 MW without tracking new | AO8: PJ | AP8: GW | AQ8: DAYNITE | AW8: Commercial solar PV >2 MW without tracking
A9: P-RNW-SOL-PV03 | B9: ETRI2018 | D9: ="PWR "&AW9&" new" -> PWR Commercial solar PV >2 MW with tracking new | E9: PWRSOL | F9: ELCC | G9: 1 | L9: 2019 | M9: =+M8 -> 500 | Q9: =+Q8 -> 670 | R9: 21.75 | S9: 16.5 | T9: 13.35 | U9: 11.85 | V9: 10.65 | AB9: 25 | AE9: 31.536 | AL9: ELE | AM9: =A9 -> P-RNW-SOL-PV03 | AN9: =D9 -> PWR Commercial solar PV >2 MW with tracking new | AO9: PJ | AP9: GW | AQ9: DAYNITE | AW9: Commercial solar PV >2 MW with tracking
A10: P-RNW-SOL-CSP04 | B10: ETRI2014 | D10: ="PWR "&AW10&" new" -> PWR Solar thermal electricity power plants without thermal storage (power/heat=0.38) new | E10: PWRSOL | F10: ELCC | G10: 0.36 | L10: 2019 | M10: 5600 | N10: 4500 | O10: 3800 | P10: 3500 | Q10: 3400 | R10: 224 | S10: 180 | T10: 152 | U10: 140 | V10: 136 | W10: 0.448 | X10: 0.36 | Y10: 0.304 | Z10: 0.28 | AA10: 0.272 | AB10: 30 | AE10: 31.536 | AF10: 0.42 | AL10: ELE | AM10: =A10 -> P-RNW-SOL-CSP04 | AN10: =D10 -> PWR Solar thermal electricity power plants without thermal storage (power/heat=0.38) new | AO10: PJ | AP10: GW | AQ10: DAYNITE | AW10: Solar thermal electricity power plants without thermal storage (power/heat=0.38)
A11: P-RNW-HYD-DAM01 | B11: ETRI2018 | D11: ="PWR "&AW11&" new" -> PWR Hydropower dam and reservoir, >100 MW new | E11: PWRHYD | F11: ELCC | G11: 1 | L11: 2019 | M11: =VLOOKUP($A11,ETRI_Cost!$A:$I,5,FALSE) -> 3500 | N11: =VLOOKUP($A11,ETRI_Cost!$A:$I,6,FALSE) -> 3500 | O11: =VLOOKUP($A11,ETRI_Cost!$A:$I,7,FALSE) -> 3490 | P11: =VLOOKUP($A11,ETRI_Cost!$A:$I,8,FALSE) -> 3480 | Q11: =VLOOKUP($A11,ETRI_Cost!$A:$I,9,FALSE) -> 3470 | R11: 22 | S11: 22 | T11: 22 | U11: 22 | V11: 22 | W11: 0.066 | X11: 0.066 | Y11: 0.066 | Z11: 0.066 | AA11: 0.066 | AB11: 60 | AE11: 31.536 | AF11: 0.35 | AL11: ELE | AM11: =A11 -> P-RNW-HYD-DAM01 | AN11: =D11 -> PWR Hydropower dam and reservoir, >100 MW new | AO11: PJ | AP11: GW | AQ11: DAYNITE | AW11: Hydropower dam and reservoir, >100 MW
A12: P-RNW-HYD-DAM02 | B12: ETRI2018 | D12: ="PWR "&AW12&" new" -> PWR Hydropower dam and reservoir, 10-100 MW new | E12: PWRHYD | F12: ELCC | G12: 1 | L12: 2019 | M12: =VLOOKUP($A12,ETRI_Cost!$A:$I,5,FALSE) -> 4000 | N12: =VLOOKUP($A12,ETRI_Cost!$A:$I,6,FALSE) -> 4000 | O12: =VLOOKUP($A12,ETRI_Cost!$A:$I,7,FALSE) -> 3980 | P12: =VLOOKUP($A12,ETRI_Cost!$A:$I,8,FALSE) -> 3970 | Q12: =VLOOKUP($A12,ETRI_Cost!$A:$I,9,FALSE) -> 3970 | R12: 49.5 | S12: 50.4 | T12: 50.55 | U12: 50.55 | V12: 50.55 | W12: 0.165 | X12: 0.168 | Y12: 0.1685 | Z12: 0.1685 | AA12: 0.1685 | AB12: 60 | AE12: 31.536 | AF12: 0.4 | AL12: ELE | AM12: =A12 -> P-RNW-HYD-DAM02 | AN12: =D12 -> PWR Hydropower dam and reservoir, 10-100 MW new | AO12: PJ | AP12: GW | AQ12: DAYNITE | AW12: Hydropower dam and reservoir, 10-100 MW
A13: P-RNW-HYD-DAM03 | B13: ETRI2018 | D13: ="PWR "&AW13&" new" -> PWR Hydropower dam and reservoir, <10 MW new | E13: PWRHYD | F13: ELCC | G13: 1 | L13: 2019 | M13: =VLOOKUP($A13,ETRI_Cost!$A:$I,5,FALSE) -> 5000 | N13: =VLOOKUP($A13,ETRI_Cost!$A:$I,6,FALSE) -> 5000 | O13: =VLOOKUP($A13,ETRI_Cost!$A:$I,7,FALSE) -> 4980 | P13: =VLOOKUP($A13,ETRI_Cost!$A:$I,8,FALSE) -> 4970 | Q13: =VLOOKUP($A13,ETRI_Cost!$A:$I,9,FALSE) -> 4960 | R13: 66 | S13: 67.2 | T13: 67.5 | U13: 67.5 | V13: 67.5 | W13: 0.22 | X13: 0.224 | Y13: 0.225 | Z13: 0.225 | AA13: 0.225 | AB13: 60 | AE13: 31.536 | AF13: 0.37 | AL13: ELE | AM13: =A13 -> P-RNW-HYD-DAM03 | AN13: =D13 -> PWR Hydropower dam and reservoir, <10 MW new | AO13: PJ | AP13: GW | AQ13: DAYNITE | AW13: Hydropower dam and reservoir, <10 MW
A14: P-RNW-HYD-ROR04 | B14: ETRI2018 | D14: ="PWR "&AW14&" new" -> PWR Hydropower run-of-a-river new | E14: PWRHYD | F14: ELCC | G14: 1 | L14: 2019 | M14: =VLOOKUP($A14,ETRI_Cost!$A:$I,5,FALSE) -> 3000 | N14: =VLOOKUP($A14,ETRI_Cost!$A:$I,6,FALSE) -> 3000 | O14: =VLOOKUP($A14,ETRI_Cost!$A:$I,7,FALSE) -> 2990 | P14: =VLOOKUP($A14,ETRI_Cost!$A:$I,8,FALSE) -> 2980 | Q14: =VLOOKUP($A14,ETRI_Cost!$A:$I,9,FALSE) -> 2970 | R14: 82.5 | S14: 84 | T14: 84.3 | U14: 84.3 | V14: 84.3 | W14: 0.275 | X14: 0.28 | Y14: 0.281 | Z14: 0.281 | AA14: 0.281 | AB14: 60 | AE14: 31.536 | AF14: 0.37 | AL14: ELE | AM14: =A14 -> P-RNW-HYD-ROR04 | AN14: =D14 -> PWR Hydropower run-of-a-river new | AO14: PJ | AP14: GW | AQ14: DAYNITE | AW14: Hydropower run-of-a-river
A15: P-RNW-GEO01 | B15: ETRI2018 | C15: ETRI2014 | D15: ="PWR "&AW15&" new" -> PWR Flash power plant extracting fluid from hydrothermal system at 2.5 km depth new | E15: PWRGEO | F15: ELCC | G15: 0.1 | H15: 0.1 | I15: 0.1 | J15: 0.1 | K15: 0.1 | L15: 2019 | M15: =VLOOKUP($A15,ETRI_Cost!$A:$I,5,FALSE) -> 3540 | N15: =VLOOKUP($A15,ETRI_Cost!$A:$I,6,FALSE) -> 3350 | O15: =VLOOKUP($A15,ETRI_Cost!$A:$I,7,FALSE) -> 3150 | P15: =VLOOKUP($A15,ETRI_Cost!$A:$I,8,FALSE) -> 3020 | Q15: =VLOOKUP($A15,ETRI_Cost!$A:$I,9,FALSE) -> 2910 | R15: 77.42 | S15: 79.52 | T15: 80.46 | U15: 80.4 | V15: 79.42 | AB15: 30 | AE15: 31.536 | AF15: 0.95 | AL15: ELE | AM15: =A15 -> P-RNW-GEO01 | AN15: =D15 -> PWR Flash power plant extracting fluid from hydrothermal system at 2.5 km depth new | AO15: PJ | AP15: GW | AQ15: DAYNITE | AW15: Flash power plant extracting fluid from hydrothermal system at 2.5 km depth
A16: P-RNW-GEO02 | B16: ETRI2018 | C16: ETRI2014 | D16: ="PWR "&AW16&" new" -> PWR Organic Rankine Cycle hydrothermal system. new | E16: PWRGEO | F16: ELCC | G16: 0.1 | H16: 0.1 | I16: 0.1 | J16: 0.1 | K16: 0.1 | L16: 2019 | M16: =VLOOKUP($A16,ETRI_Cost!$A:$I,5,FALSE) -> 6970 | N16: =VLOOKUP($A16,ETRI_Cost!$A:$I,6,FALSE) -> 6600 | O16: =VLOOKUP($A16,ETRI_Cost!$A:$I,7,FALSE) -> 6190 | P16: =VLOOKUP($A16,ETRI_Cost!$A:$I,8,FALSE) -> 5950 | Q16: =VLOOKUP($A16,ETRI_Cost!$A:$I,9,FALSE) -> 5720 | R16: 146.37 | S16: 145.2 | T16: 143.52 | U16: 146.75 | V16: 148.77 | AB16: 30 | AE16: 31.536 | AF16: 0.95 | AL16: ELE | AM16: =A16 -> P-RNW-GEO02 | AN16: =D16 -> PWR Organic Rankine Cycle hydrothermal system. new | AO16: PJ | AP16: GW | AQ16: DAYNITE | AW16: Organic Rankine Cycle hydrothermal system.
A17: P-RNW-GEO03 | B17: ETRI2014 | C17: ETRI2014 | D17: ="PWR "&AW17&" new" -> PWR Organic Rankine Cycle Enhanced Geothermal System at 5.5 km depth new | E17: PWRGEO | F17: ELCC | G17: 0.1 | H17: 0.1 | I17: 0.1 | J17: 0.1 | K17: 0.1 | L17: 2019 | M17: 12600 | N17: 10300 | O17: 9000 | P17: 8600 | Q17: 8200 | R17: 226.8 | S17: 185.4 | T17: 171 | U17: 163.4 | V17: 155.8 | AB17: 30 | AE17: 31.536 | AF17: 0.95 | AL17: ELE | AM17: =A17 -> P-RNW-GEO03 | AN17: =D17 -> PWR Organic Rankine Cycle Enhanced Geothermal System at 5.5 km depth new | AO17: PJ | AP17: GW | AQ17: DAYNITE | AW17: Organic Rankine Cycle Enhanced Geothermal System at 5.5 km depth
A18: P-RNW-OCE-WAV01 | B18: ETRI2018 | D18: ="PWR "&AW18&" new" -> PWR Wave energy new | E18: PWROCE | F18: ELCC | G18: 1 | L18: 2019 | M18: =VLOOKUP($A18,ETRI_Cost!$A:$I,5,FALSE) -> 7910 | N18: =VLOOKUP($A18,ETRI_Cost!$A:$I,6,FALSE) -> 6310 | O18: =VLOOKUP($A18,ETRI_Cost!$A:$I,7,FALSE) -> 5320 | P18: =VLOOKUP($A18,ETRI_Cost!$A:$I,8,FALSE) -> 4040 | Q18: =VLOOKUP($A18,ETRI_Cost!$A:$I,9,FALSE) -> 3240 | R18: 326.88 | S18: 237.39 | T18: 210.56 | U18: 153.7 | V18: 133.4 | AB18: 20 | AE18: 31.536 | AF18: 0.36 | AL18: ELE | AM18: =A18 -> P-RNW-OCE-WAV01 | AN18: =D18 -> PWR Wave energy new | AO18: PJ | AP18: GW | AQ18: DAYNITE | AW18: Wave energy
A19: P-RNW-OCE-TID02 | B19: ETRI2018 | D19: ="PWR "&AW19&" new" -> PWR Tidal energy new | E19: PWROCE | F19: ELCC | G19: 1 | L19: 2019 | M19: =VLOOKUP($A19,ETRI_Cost!$A:$I,5,FALSE) -> 7840 | N19: =VLOOKUP($A19,ETRI_Cost!$A:$I,6,FALSE) -> 6260 | O19: =VLOOKUP($A19,ETRI_Cost!$A:$I,7,FALSE) -> 5270 | P19: =VLOOKUP($A19,ETRI_Cost!$A:$I,8,FALSE) -> 4000 | Q19: =VLOOKUP($A19,ETRI_Cost!$A:$I,9,FALSE) -> 3210 | R19: 363.8 | S19: 158.4 | T19: 117.8 | U19: 90.3 | V19: 93.1 | AB19: 20 | AE19: 31.536 | AF19: 0.36 | AL19: ELE | AM19: =A19 -> P-RNW-OCE-TID02 | AN19: =D19 -> PWR Tidal energy new | AO19: PJ | AP19: GW | AQ19: DAYNITE | AW19: Tidal energy
A20: P-TH-OCGT-GAS01 | B20: ETRI2014 | D20: ="PWR "&AW20&" new" -> PWR Open-Cycle Gas Turbine conventional new | E20: PWRGAS | F20: ELCC | G20: 0.38 | L20: 2019 | M20: 770 | R20: 7.7 | AB20: 30 | AE20: 31.536 | AF20: 0.95 | AL20: ELE | AM20: =A20 -> P-TH-OCGT-GAS01 | AN20: =D20 -> PWR Open-Cycle Gas Turbine conventional new | AO20: PJ | AP20: GW | AQ20: DAYNITE | AW20: Open-Cycle Gas Turbine conventional
A21: P-TH-OCGT-GAS02 | B21: ETRI2014 | D21: ="PWR "&AW21&" new" -> PWR Open Cycle Gas Turbine advanced new | E21: PWRGAS | F21: ELCC | G21: 0.4 | H21: 0.4 | I21: 0.43 | J21: 0.44 | K21: 0.45 | L21: 2019 | M21: 550 | N21: 550 | O21: 550 | P21: 550 | Q21: 550 | R21: 16.5 | S21: 16.5 | T21: 16.5 | U21: 16.5 | V21: 16.5 | W21: 0.0605 | X21: 0.0605 | Y21: 0.0605 | Z21: 0.0605 | AA21: 0.0605 | AB21: 30 | AE21: 31.536 | AF21: 0.95 | AL21: ELE | AM21: =A21 -> P-TH-OCGT-GAS02 | AN21: =D21 -> PWR Open Cycle Gas Turbine advanced new | AO21: PJ | AP21: GW | AQ21: DAYNITE | AW21: Open Cycle Gas Turbine advanced
A22: P-TH-CCGT-GAS03 | B22: ETRI2014 | C22: ETRI2014 | D22: ="PWR "&AW22&" new" -> PWR Combined Cycle Gas Turbine advanced new | E22: PWRGAS | F22: ELCC | G22: 0.58 | H22: 0.6 | I22: 0.62 | J22: 0.62 | K22: 0.63 | L22: 2019 | M22: 850 | N22: 850 | O22: 850 | P22: 850 | Q22: 850 | R22: 21.25 | S22: 21.25 | T22: 21.25 | U22: 21.25 | V22: 21.25 | W22: 0.017 | X22: 0.017 | Y22: 0.017 | Z22: 0.017 | AA22: 0.017 | AB22: 30 | AE22: 31.536 | AF22: 0.9 | AL22: ELE | AM22: =A22 -> P-TH-CCGT-GAS03 | AN22: =D22 -> PWR Combined Cycle Gas Turbine advanced new | AO22: PJ | AP22: GW | AQ22: DAYNITE | AW22: Combined Cycle Gas Turbine advanced
A23: P-TH-SC-COA01 | B23: ETRI2014 | C23: ETRI2014 | D23: ="PWR "&AW23&" new" -> PWR Pulverised coal supercritical new | E23: PWRCOA | F23: ELCC | G23: 0.45 | H23: 0.46 | I23: 0.48 | J23: 0.48 | K23: 0.48 | L23: 2019 | M23: 1600 | N23: 1600 | O23: 1600 | P23: 1600 | Q23: 1600 | R23: 40 | S23: 40 | T23: 40 | U23: 40 | V23: 40 | W23: 0.0576 | X23: 0.0576 | Y23: 0.0576 | Z23: 0.0576 | AA23: 0.0576 | AB23: 40 | AE23: 31.536 | AF23: 0.9 | AL23: ELE | AM23: =A23 -> P-TH-SC-COA01 | AN23: =D23 -> PWR Pulverised coal supercritical new | AO23: PJ | AP23: GW | AQ23: DAYNITE | AW23: Pulverised coal supercritical
A24: P-TH-FB-PEA01 | B24: ETRI2014 | C24: ETRI2014 | D24: ="PWR "&AW24&" new" -> PWR Pulverised peat supercritical new | E24: PWRPEA | F24: ELCC | G24: 0.42 | H24: 0.45 | I24: 0.47 | J24: 0.47 | K24: 0.47 | L24: 2019 | M24: 2000 | N24: 2000 | O24: 2000 | P24: 2000 | Q24: 2000 | R24: 50 | S24: 50 | T24: 50 | U24: 50 | V24: 50 | W24: 0.09 | X24: 0.09 | Y24: 0.09 | Z24: 0.09 | AA24: 0.09 | AB24: 40 | AE24: 31.536 | AF24: 0.9 | AL24: ELE | AM24: =A24 -> P-TH-FB-PEA01 | AN24: =D24 -> PWR Pulverised peat supercritical new | AO24: PJ | AP24: GW | AQ24: DAYNITE | AW24: Pulverised peat supercritical
A25: P-TH-SC-PEA02 | B25: ETRI2014 | C25: ETRI2014 | D25: ="PWR "&AW25&" new" -> PWR Supercritical fluidized bed peat new | E25: PWRPEA | F25: ELCC | G25: 0.42 | H25: 0.43 | I25: 0.45 | J25: 0.45 | K25: 0.45 | L25: 2019 | M25: 1900 | N25: 1900 | O25: 1900 | P25: 1900 | Q25: 1900 | R25: 38 | S25: 38 | T25: 38 | U25: 38 | V25: 38 | W25: 0.114 | X25: 0.114 | Y25: 0.114 | Z25: 0.114 | AA25: 0.114 | AB25: 40 | AE25: 31.536 | AF25: 0.85 | AL25: ELE | AM25: =A25 -> P-TH-SC-PEA02 | AN25: =D25 -> PWR Supercritical fluidized bed peat new | AO25: PJ | AP25: GW | AQ25: DAYNITE | AW25: Supercritical fluidized bed peat
A26: P-TH-IGCC-COA03 | B26: ETRI2014 | C26: ETRI2014 | D26: ="PWR "&AW26&" new" -> PWR Integrated Gasification Combined Cycle coal new | E26: PWRCOA | F26: ELCC | G26: 0.45 | H26: 0.46 | I26: 0.46 | J26: 0.47 | K26: 0.5 | L26: 2019 | M26: 2500 | N26: 2300 | O26: 2300 | P26: 2300 | Q26: 2200 | R26: 62.5 | S26: 57.5 | T26: 57.5 | U26: 57.5 | V26: 55 | W26: 0.125 | X26: 0.115 | Y26: 0.115 | Z26: 0.115 | AA26: 0.11 | AB26: 35 | AE26: 31.536 | AF26: 0.9 | AL26: ELE | AM26: =A26 -> P-TH-IGCC-COA03 | AN26: =D26 -> PWR Integrated Gasification Combined Cycle coal new | AO26: PJ | AP26: GW | AQ26: DAYNITE | AW26: Integrated Gasification Combined Cycle coal
A27: P-TH-IGCC-PEA03 | B27: ETRI2014 | C27: ETRI2014 | D27: ="PWR "&AW27&" new" -> PWR Integrated Gasification Combined Cycle peat new | E27: PWRPEA | F27: ELCC | G27: 0.43 | H27: 0.45 | I27: 0.46 | J27: 0.47 | K27: 0.47 | L27: 2019 | M27: 3100 | N27: 3000 | O27: 3000 | P27: 3000 | Q27: 3000 | R27: 93 | S27: 90 | T27: 90 | U27: 90 | V27: 90 | W27: 0.217 | X27: 0.21 | Y27: 0.21 | Z27: 0.21 | AA27: 0.21 | AB27: 35 | AE27: 31.536 | AF27: 0.9 | AL27: ELE | AM27: =A27 -> P-TH-IGCC-PEA03 | AN27: =D27 -> PWR Integrated Gasification Combined Cycle peat new | AO27: PJ | AP27: GW | AQ27: DAYNITE | AW27: Integrated Gasification Combined Cycle peat
A28: *P-TH-CCGT-GAS-CCS04 | B28: ETRI2018 | C28: ETRI2014 | D28: ="PWR "&AW28&" new" -> PWR CCGT advanced CCS post combustion new | E28: PWRGAS | F28: ELCC | G28: 0.5 | H28: 0.52 | I28: 0.55 | J28: 0.55 | K28: 0.55 | L28: 2030 | O28: =VLOOKUP($A28,ETRI_Cost!$A:$I,7,FALSE) -> 1390 | P28: =VLOOKUP($A28,ETRI_Cost!$A:$I,8,FALSE) -> 1310 | Q28: =VLOOKUP($A28,ETRI_Cost!$A:$I,9,FALSE) -> 1280 | R28: 37.5 | S28: 37.5 | T28: 37.5 | U28: 37.5 | V28: 37.5 | W28: 0.06 | X28: 0.06 | Y28: 0.06 | Z28: 0.06 | AA28: 0.06 | AB28: 30 | AE28: 31.536 | AF28: 0.9 | AL28: ELE | AM28: =A28 -> *P-TH-CCGT-GAS-CCS04 | AN28: =D28 -> PWR CCGT advanced CCS post combustion new | AO28: PJ | AP28: GW | AQ28: DAYNITE | AW28: CCGT advanced CCS post combustion
A29: *P-TH-SC-COA-CCS04 | B29: ETRI2018 | C29: ETRI2014 | D29: ="PWR "&AW29&" new" -> PWR Pulverised coal supercritical CCS post-combustion new | E29: PWRCOA | F29: ELCC | G29: 0.34 | H29: 0.35 | I29: 0.35 | J29: 0.38 | K29: 0.38 | L29: 2030 | O29: =VLOOKUP($A29,ETRI_Cost!$A:$I,7,FALSE) -> 2740 | P29: =VLOOKUP($A29,ETRI_Cost!$A:$I,8,FALSE) -> 2590 | Q29: =VLOOKUP($A29,ETRI_Cost!$A:$I,9,FALSE) -> 2570 | R29: 75 | S29: 67.5 | T29: 63.75 | U29: 63.75 | V29: 63.75 | W29: 0.165 | X29: 0.1485 | Y29: 0.14025 | Z29: 0.14025 | AA29: 0.14025 | AB29: 40 | AE29: 31.536 | AF29: 0.9 | AL29: ELE | AM29: =A29 -> *P-TH-SC-COA-CCS04 | AN29: =D29 -> PWR Pulverised coal supercritical CCS post-combustion new | AO29: PJ | AP29: GW | AQ29: DAYNITE | AW29: Pulverised coal supercritical CCS post-combustion
A30: *P-TH-FB-PEA-CCS04 | B30: ETRI2014 | C30: ETRI2014 | D30: ="PWR "&AW30&" new" -> PWR Fluidised bed peat CCS post combustion new | E30: PWRPEA | F30: ELCC | G30: 0.31 | H30: 0.32 | I30: 0.34 | J30: 0.34 | K30: 0.34 | L30: 2030 | M30: 3500 | N30: 3500 | O30: 3500 | P30: 3500 | Q30: 3500 | R30: 87.5 | S30: 87.5 | T30: 87.5 | U30: 87.5 | V30: 87.5 | W30: 0.35 | X30: 0.35 | Y30: 0.35 | Z30: 0.35 | AA30: 0.35 | AB30: 40 | AE30: 31.536 | AF30: 0.85 | AL30: ELE | AM30: =A30 -> *P-TH-FB-PEA-CCS04 | AN30: =D30 -> PWR Fluidised bed peat CCS post combustion new | AO30: PJ | AP30: GW | AQ30: DAYNITE | AW30: Fluidised bed peat CCS post combustion
A31: *P-TH-SC-COA-CCS05 | B31: ETRI2018 | C31: ETRI2014 | D31: ="PWR "&AW31&" new" -> PWR Pulverised coal supercritical CCS oxyfuel new | E31: PWRCOA | F31: ELCC | G31: 0.36 | H31: 0.37 | I31: 0.39 | J31: 0.4 | K31: 0.4 | L31: 2030 | O31: =VLOOKUP($A31,ETRI_Cost!$A:$I,7,FALSE) -> 2690 | P31: =VLOOKUP($A31,ETRI_Cost!$A:$I,8,FALSE) -> 2490 | Q31: =VLOOKUP($A31,ETRI_Cost!$A:$I,9,FALSE) -> 2470 | R31: 75 | S31: 67.5 | T31: 63.75 | U31: 63.75 | V31: 63.75 | W31: 0.09 | X31: 0.081 | Y31: 0.0765 | Z31: 0.0765 | AA31: 0.0765 | AB31: 40 | AE31: 31.536 | AF31: 0.9 | AL31: ELE | AM31: =A31 -> *P-TH-SC-COA-CCS05 | AN31: =D31 -> PWR Pulverised coal supercritical CCS oxyfuel new | AO31: PJ | AP31: GW | AQ31: DAYNITE | AW31: Pulverised coal supercritical CCS oxyfuel
A32: *P-TH-IGCC-COA-CCS06 | B32: ETRI2018 | C32: ETRI2014 | D32: ="PWR "&AW32&" new" -> PWR IGCC coal CCS pre-combustion new | E32: PWRCOA | F32: ELCC | G32: 0.35 | H32: 0.37 | I32: 0.4 | J32: 0.41 | K32: 0.44 | L32: 2030 | O32: =VLOOKUP($A32,ETRI_Cost!$A:$I,7,FALSE) -> 2540 | P32: =VLOOKUP($A32,ETRI_Cost!$A:$I,8,FALSE) -> 2220 | Q32: =VLOOKUP($A32,ETRI_Cost!$A:$I,9,FALSE) -> 2180 | R32: 93 | S32: 86.55 | T32: 84.75 | U32: 84.75 | V32: 84.75 | W32: 0.186 | X32: 0.1731 | Y32: 0.1695 | Z32: 0.1695 | AA32: 0.1695 | AB32: 35 | AE32: 31.536 | AF32: 0.9 | AL32: ELE | AM32: =A32 -> *P-TH-IGCC-COA-CCS06 | AN32: =D32 -> PWR IGCC coal CCS pre-combustion new | AO32: PJ | AP32: GW | AQ32: DAYNITE | AW32: IGCC coal CCS pre-combustion
A33: *P-TH-IGCC-PEA-CCS05 | B33: ETRI2018 | C33: ETRI2014 | D33: ="PWR "&AW33&" new" -> PWR IGCC peat CCS pre combustion new | E33: PWRPEA | F33: ELCC | G33: 0.35 | H33: 0.37 | I33: 0.4 | J33: 0.41 | K33: 0.41 | L33: 2030 | O33: =VLOOKUP($A33,ETRI_Cost!$A:$I,7,FALSE) -> 3870 | P33: =VLOOKUP($A33,ETRI_Cost!$A:$I,8,FALSE) -> 3380 | Q33: =VLOOKUP($A33,ETRI_Cost!$A:$I,9,FALSE) -> 3310 | R33: 103.5 | S33: 100.51 | T33: 100.51 | U33: 100.51 | V33: 100.51 | W33: 0.36 | X33: 0.3496 | Y33: 0.3496 | Z33: 0.3496 | AA33: 0.3496 | AB33: 35 | AE33: 31.536 | AF33: 0.9 | AL33: ELE | AM33: =A33 -> *P-TH-IGCC-PEA-CCS05 | AN33: =D33 -> PWR IGCC peat CCS pre combustion new | AO33: PJ | AP33: GW | AQ33: DAYNITE | AW33: IGCC peat CCS pre combustion
A34: P-RNW-FB-BIO01 | B34: ETRI2014 | C34: ETRI2014 | D34: ="PWR "&AW34&" new" -> PWR Biomass grate furnace steam turbine new | E34: PWRBIO | F34: ELCC | G34: 0.34 | H34: 0.35 | I34: 0.36 | J34: 0.38 | K34: 0.38 | L34: 2019 | M34: 2890 | N34: 2620 | O34: 2370 | P34: 2150 | Q34: 1950 | R34: 63.58 | S34: 57.64 | T34: 52.14 | U34: 47.3 | V34: 42.9 | W34: 0.10115 | X34: 0.0917 | Y34: 0.08295 | Z34: 0.07525 | AA34: 0.06825 | AB34: 25 | AE34: 31.536 | AF34: 0.9 | AL34: ELE | AM34: =A34 -> P-RNW-FB-BIO01 | AN34: New Power Plant - Biomass grate furnace steam turbine | AO34: PJ | AP34: GW | AQ34: DAYNITE | AW34: Biomass grate furnace steam turbine
A35: P-RNW-ST-BIO02 | B35: ETRI2014 | C35: ETRI2014 | D35: ="PWR "&AW35&" new" -> PWR Fluidised bed boiler (circulating or bubbling) plus steam turbine new | E35: PWRBIO | F35: ELCC | G35: 0.35 | H35: 0.36 | I35: 0.37 | J35: 0.38 | K35: 0.39 | L35: 2019 | M35: 2960 | N35: 2620 | O35: 2330 | P35: 2060 | Q35: 1830 | R35: 53.28 | S35: 47.16 | T35: 41.94 | U35: 37.08 | V35: 32.94 | W35: 0.11248 | X35: 0.09956 | Y35: 0.08854 | Z35: 0.07828 | AA35: 0.06954 | AB35: 25 | AE35: 31.536 | AF35: 0.9 | AL35: ELE | AM35: =A35 -> P-RNW-ST-BIO02 | AN35: New Power Plant - Fluidised bed boiler (circulating or bubbling) plus steam turbine | AO35: PJ | AP35: GW | AQ35: DAYNITE | AW35: Fluidised bed boiler (circulating or bubbling) plus steam turbine
A36: P-RNW-IGCC-BIO03 | B36: ETRI2014 | C36: ETRI2014 | D36: ="PWR "&AW36&" new" -> PWR Biomass IGCC new | E36: PWRBIO | F36: ELCC | G36: 0.35 | H36: 0.37 | I36: 0.43 | J36: 0.47 | K36: 0.48 | L36: 2019 | M36: 4810 | N36: 3810 | O36: 3140 | P36: 2840 | Q36: 2560 | R36: 105.82 | S36: 83.82 | T36: 69.08 | U36: 62.48 | V36: 56.32 | W36: 0.39442 | X36: 0.31242 | Y36: 0.25748 | Z36: 0.23288 | AA36: 0.20992 | AB36: 25 | AE36: 31.536 | AF36: 0.9 | AL36: ELE | AM36: =A36 -> P-RNW-IGCC-BIO03 | AN36: New Power Plant - Biomass IGCC | AO36: PJ | AP36: GW | AQ36: DAYNITE | AW36: Biomass IGCC
A37: P-RNW-AB-BIO04 | B37: ETRI2018 | C37: ETRI2014 | D37: ="PWR "&AW37&" new" -> PWR Anaerobic digestion new | E37: PWRBIO | F37: ELCC | G37: 0.36 | H37: 0.38 | I37: 0.4 | J37: 0.42 | K37: 0.45 | L37: 2019 | M37: =VLOOKUP($A37,ETRI_Cost!$A:$I,5,FALSE) -> 3100 | N37: =VLOOKUP($A37,ETRI_Cost!$A:$I,6,FALSE) -> 2860 | O37: =VLOOKUP($A37,ETRI_Cost!$A:$I,7,FALSE) -> 2740 | P37: =VLOOKUP($A37,ETRI_Cost!$A:$I,8,FALSE) -> 2630 | Q37: =VLOOKUP($A37,ETRI_Cost!$A:$I,9,FALSE) -> 2510 | R37: 159.08 | S37: 130.38 | T37: 113.16 | U37: 103.32 | V37: 94.3 | W37: 0.12028 | X37: 0.09858 | Y37: 0.08556 | Z37: 0.07812 | AA37: 0.0713 | AB37: 20 | AE37: 31.536 | AF37: 0.9 | AL37: ELE | AM37: =A37 -> P-RNW-AB-BIO04 | AN37: New Power Plant - Anaerobic digestion | AO37: PJ | AP37: GW | AQ37: DAYNITE | AW37: Anaerobic digestion
A38: P-RNW-ST-MSW04 | B38: ETRI2014 | C38: ETRI2014 | D38: ="PWR "&AW38&" new" -> PWR Municipal solid waste incinerator new | E38: PWRMSW | F38: ELCC | G38: 0.27 | H38: 0.31 | I38: 0.34 | J38: 0.37 | K38: 0.42 | L38: 2019 | M38: 6080 | N38: 5630 | O38: 5240 | P38: 4870 | Q38: 4540 | R38: 182.4 | S38: 168.9 | T38: 157.2 | U38: 146.1 | V38: 136.2 | W38: 0.41952 | X38: 0.38847 | Y38: 0.36156 | Z38: 0.33603 | AA38: 0.31326 | AB38: 25 | AE38: 31.536 | AF38: 0.9 | AL38: ELE | AM38: =A38 -> P-RNW-ST-MSW04 | AN38: New Power Plant - Municipal solid waste incinerator | AO38: PJ | AP38: GW | AQ38: DAYNITE | AW38: Municipal solid waste incinerator
A41: Source: UK TIMES (for H2)
D42: ~FI_T: MEUR2012 | AJ42: ~FI_Process
A43: TechName | B43: *TechDesc | C43: Comm-IN | D43: Comm-OUT | E43: EFF | F43: EFF~2020 | G43: EFF~2030 | H43: EFF~2040 | I43: EFF~2050 | J43: Start | K43: INVCOST | L43: INVCOST~2020 | M43: INVCOST~2030 | N43: INVCOST~2040 | O43: INVCOST~2050 | P43: FIXOM | Q43: FIXOM~2020 | R43: FIXOM~2030 | S43: FIXOM~2040 | T43: FIXOM~2050 | U43: VAROM | V43: VAROM~2020 | W43: VAROM~2030 | X43: VAROM~2040 | Y43: VAROM~2050 | Z43: LIFE | AA43: LIFE~2020 | AB43: LIFE~2030 | AC43: Cap2Act | AD43: AFA | AE43: AFA~2020 | AF43: AFA~2030 | AG43: AFA~2040 | AH43: AFA~2050 | AJ43: Sets | AK43: TechName | AL43: TechDesc | AM43: Tact | AN43: Tcap | AO43: Tslvl | AP43: PrimaryCG | AQ43: Vintage
A44: *Technology Name | B44: Technology Description | C44: Input Commodity | D44: Output Commodity | E44: Efficiency | K44: CAPEX REF (€2012/kW) | P44: FOM (€2013/kW) | U44: VOM (€2013/GJ) | Z44: Technical life | AD44: Max. capacity factor | AJ44: *Process Set Membership | AK44: Technology Name | AL44: Technology Description | AM44: Activity Unit | AN44: Capacity Unit | AO44: TimeSlice Level | AP44: Primary CommGrp | AQ44: Vintage Tracking
A45: P-TH-OCGT-H2-01 | B45: New Power Plant - Hydrogen Open Cycle Gas Turbine | C45: PWRH2G | D45: ELCC | F45: 0.42735 | J45: 2030 | K45: 520.8233 | L45: 515.50766 | M45: 509.75361 | N45: 504.71197 | Z45: 30 | AC45: 31.536 | AD45: 0.912 | AJ45: ELE | AK45: =A45 -> P-TH-OCGT-H2-01 | AL45: =B45 -> New Power Plant - Hydrogen Open Cycle Gas Turbine | AM45: PJ | AN45: GW | AO45: DAYNITE
A46: P-TH-CCGT-H2-02 | B46: New Power Plant - Hydrogen Combined Cycle Gas Turbine | C46: PWRH2G | D46: ELCC | F46: 0.59 | J46: 2030 | K46: 700.29672 | L46: 690.76687 | M46: 680.45105 | N46: 671.41243 | Z46: 35 | AC46: 31.536 | AD46: 0.912 | AK46: =A46 -> P-TH-CCGT-H2-02 | AL46: =B46 -> New Power Plant - Hydrogen Combined Cycle Gas Turbine | AM46: PJ | AN46: GW | AO46: DAYNITE

Sheet IMPEXP
A2: Electricity Interconnector | G2: ~FI_T: MEUR2014 | S2: ~FI_Process
A3: Region | B3: TechName | C3: *TechDesc | D3: Comm-IN | E3: Comm-OUT | F3: Year | G3: LimType | H3: NCAP_START | I3: NCAP_TLIFE | J3: PRC_CAPACT | K3: COST~2015 | L3: COST~2020 | M3: COST~2030 | N3: COST~2040 | O3: COST~2050 | P3: CAP_BND | Q3: CAP_BND~0 | S3: Sets | T3: Region | U3: TechName | V3: TechDesc | W3: Tact | X3: Tcap | Y3: Tslvl | Z3: PrimaryCG | AA3: Vintage
A4: *Region Name | B4: Technology Name | C4: Technology Description | K4: Euro/GJ | L4: Euro/GJ | M4: Euro/GJ | N4: Euro/GJ | O4: Euro/GJ | P4: GW | Q4: GW | S4: *Process Set Membership | T4: Region Name | U4: Technology Name | V4: Technology Description | W4: Activity Unit | X4: Capacity Unit | Y4: TimeSlice level of Process Activity | Z4: Primary Commodity Group | AA4: Vintage Tracking
A5: =T5 -> IE,National | B5: =U5 -> IMPELC_FR-CI | C5: =V5 -> Import of Electricity - France Celtic Interconnector | E5: ELCC | F5: 2026 | G5: FX | H5: 2026 | I5: 100 | J5: 31.536 | K5: 12.775231 | L5: 13.844655 | M5: 20.699647 | N5: 24.100187 | O5: 27.970361 | P5: 0.7 | Q5: 5 | S5: IMP | T5: IE,National | U5: IMPELC_FR-CI | V5: Import of Electricity - France Celtic Interconnector | W5: PJ | X5: GW | Y5: DAYNITE
A6: =T6 -> IE,National | B6: =U6 -> EXPELC_FR-CI | C6: =V6 -> Export of Electricity - France Celtic Interconnector | D6: ELCC | F6: 2026 | G6: FX | H6: 2026 | I6: 100 | J6: 31.536 | K6: 8.942662 | L6: 9.6912586 | M6: 14.489753 | N6: 16.870131 | O6: 19.579253 | P6: 0.7 | Q6: 5 | S6: EXP | T6: IE,National | U6: EXPELC_FR-CI | V6: Export of Electricity - France Celtic Interconnector | W6: PJ | X6: GW | Y6: DAYNITE
A7: =T7 -> IE,National | B7: =U7 -> IMPELC_UK-GL | C7: =V7 -> Import of Electricity - UK Greenlink | E7: ELCC | F7: 2024 | G7: FX | H7: 2024 | I7: 100 | J7: 31.536 | K7: 12.775231 | L7: 13.844655 | M7: 20.699647 | N7: 24.100187 | O7: 27.970361 | P7: 0.5 | Q7: 5 | S7: IMP | T7: IE,National | U7: IMPELC_UK-GL | V7: Import of Electricity - UK Greenlink | W7: PJ | X7: GW | Y7: DAYNITE
A8: =T8 -> IE,National | B8: =U8 -> EXPELC_UK-GL | C8: =V8 -> Export of Electricity - UK Greenlink | D8: ELCC | F8: 2024 | G8: FX | H8: 2024 | I8: 100 | J8: 31.536 | K8: 8.942662 | L8: 9.6912586 | M8: 14.489753 | N8: 16.870131 | O8: 19.579253 | P8: 0.5 | Q8: 5 | S8: EXP | T8: IE,National | U8: EXPELC_UK-GL | V8: Export of Electricity - UK Greenlink | W8: PJ | X8: GW | Y8: DAYNITE

Sheet ELC_WIN
D1: ~FI_T: MEUR2024 | AJ1: ~FI_Process
A2: TechName | B2: *TechDesc | C2: Comm-IN | D2: Comm-OUT | E2: EFF | F2: EFF~2020 | G2: EFF~2030 | H2: EFF~2040 | I2: EFF~2050 | J2: Start | K2: INVCOST | L2: INVCOST~2025 | M2: INVCOST~2030 | N2: INVCOST~2040 | O2: INVCOST~2050 | P2: FIXOM~2025 | Q2: FIXOM~2020 | R2: FIXOM~2030 | S2: FIXOM~2040 | T2: FIXOM~2050 | U2: VAROM | V2: VAROM~2020 | W2: VAROM~2030 | X2: VAROM~2040 | Y2: VAROM~2050 | Z2: LIFE | AA2: LIFE~2020 | AB2: LIFE~2030 | AC2: Cap2Act | AD2: AFA | AE2: AFA~2020 | AF2: AFA~2030 | AG2: AFA~2040 | AH2: AFA~2050 | AJ2: Sets | AK2: TechName | AL2: TechDesc | AM2: Tact | AN2: Tcap | AO2: Tslvl | AP2: PrimaryCG | AQ2: Vintage
A3: *Technology Name | B3: Technology Description | C3: Input Commodity | D3: Output Commodity | E3: Efficiency | K3: CAPEX REF (€2013/kW) | P3: FOM (€2013/kW) | U3: VOM (€2013/GJ) | Z3: Technical life | AD3: Max. capacity factor | AJ3: *Process Set Membership | AK3: Technology Name | AL3: Technology Description | AM3: Activity Unit | AN3: Capacity Unit | AO3: TimeSlice Level | AP3: Primary CommGrp | AQ3: Vintage Tracking
A4: P-RNW-WIN-ON01 | B4: New Power Plant - Onshore Wind - Connection Cost Level 01 | C4: PWRWIN | D4: ELCC | E4: 1 | J4: 2019 | L4: 1526 | O4: 1317 | P4: 37.8 | T4: =P4*O4/L4 -> 32.622936 | Z4: 20 | AA4: 22 | AB4: 25 | AC4: 31.536 | AJ4: ELE | AK4: P-RNW-WIN-ON01 | AL4: New Power Plant - Onshore Wind - Connection Cost Level 01 | AM4: PJ | AN4: GW | AO4: DAYNITE
A5: P-RNW-WIN-ON02 | B5: New Power Plant - Onshore Wind - Connection Cost Level 02 | C5: PWRWIN | D5: ELCC | E5: 1 | J5: 2019 | L5: 1575 | O5: 1366 | P5: 37.8 | T5: =P5*O5/L5 -> 32.784 | Z5: 20 | AA5: 22 | AB5: 25 | AC5: 31.536 | AJ5: ELE | AK5: P-RNW-WIN-ON02 | AL5: New Power Plant - Onshore Wind - Connection Cost Level 02 | AM5: PJ | AN5: GW | AO5: DAYNITE
A6: P-RNW-WIN-ON03 | B6: New Power Plant - Onshore Wind - Connection Cost Level 03 | C6: PWRWIN | D6: ELCC | E6: 1 | J6: 2019 | L6: 1662 | O6: 1451 | P6: 37.8 | T6: =P6*O6/L6 -> 33.001083 | Z6: 20 | AA6: 22 | AB6: 25 | AC6: 31.536 | AJ6: ELE | AK6: P-RNW-WIN-ON03 | AL6: New Power Plant - Onshore Wind - Connection Cost Level 03 | AM6: PJ | AN6: GW | AO6: DAYNITE
A7: P-RNW-WIN-ON04 | B7: New Power Plant - Onshore Wind - Connection Cost Level 04 | C7: PWRWIN | D7: ELCC | E7: 1 | J7: 2019 | L7: 1853 | O7: 1641 | P7: 37.8 | T7: =P7*O7/L7 -> 33.475337 | Z7: 20 | AA7: 22 | AB7: 25 | AC7: 31.536 | AJ7: ELE | AK7: P-RNW-WIN-ON04 | AL7: New Power Plant - Onshore Wind - Connection Cost Level 04 | AM7: PJ | AN7: GW | AO7: DAYNITE
A8: P-RNW-WIN-ON05 | B8: New Power Plant - Onshore Wind - Connection Cost Level 05 | C8: PWRWIN | D8: ELCC | E8: 1 | J8: 2019 | L8: 2303 | O8: 2088 | P8: 37.8 | T8: =P8*O8/L8 -> 34.271125 | Z8: 20 | AA8: 22 | AB8: 25 | AC8: 31.536 | AJ8: ELE | AK8: P-RNW-WIN-ON05 | AL8: New Power Plant - Onshore Wind - Connection Cost Level 05 | AM8: PJ | AN8: GW | AO8: DAYNITE
A9: P-RNW-WIN-OF02 | B9: PWR Offshore wind new | C9: PWRWIN | D9: ELCC | E9: 1 | J9: 2019 | L9: =3118 -> 3118 | O9: 2827 | P9: 128.39 | Q9: =+P9 -> 128.39 | T9: =+Q9*O9/L9 -> 116.40748 | Z9: 20 | AA9: 25 | AB9: 30 | AC9: 31.536

Sheet WIN_ON_COST
A1: fid | B1: Merged_ID | C1: Parcel | D1: COUNTY - 1 | E1: COUNTY - 2 | F1: Station ID | G1: name | H1: operator | I1: voltage | J1: voltage_pr | K1: voltage_te | L1: Distance | M1: Round Up Distance | N1: Area_km_2_ | O1: Class | P1: Area With Packing Density Applied(km2) | Q1: Rationalised Output Per Parcel (MW) | R1: Rationalised Output Per Parcel (MW) | S1: Cost (€) | T1: PS | U1: Cost Per MW | V1: Watt per Euro | AG1: Investment Cost
A2: 1 | B2: 1 | C2: CL1-001 | D2: KERRY | E2: KERRY | F2: SS-636 | G2: Garranebane 38kV Substation | H2: ESB Networks | I2: 38000 | J2: 38000 | K2: 20000 | L2: 15.861 | M2: 16 | N2: 0.122 | O2: 1 | P2: 0.122 | Q2: 3.45 | R2: 3.45 | S2: 1703340 | T2: 1 | U2: 493721.74 | V2: 2.0254324 | X2: Rationalised Output Per Parcel (MW) | Y2: Connection Cost Million E/Kw | AG2: 2015 | AH2: 2020 | AI2: 2030 | AJ2: 2040 | AK2: 2050
A3: 2 | B3: 2 | C3: CL1-002 | D3: KERRY | E3: KERRY | F3: SS-636 | G3: Garranebane 38kV Substation | H3: ESB Networks | I3: 38000 | J3: 38000 | K3: 20000 | L3: 5.42 | M3: 6 | N3: 0.263 | O3: 1 | P3: 0.263 | Q3: 3.45 | R3: 3.45 | S3: 769410 | T3: 4 | U3: 223017.39 | V3: 4.4839552 | X3: 3.45 | Y3: 493.72174 | AA3: Capacity | AB3: Total Connection Cost | AC3: Cost Range | AE3: Connection Cost (Euro/kW) | AG3: =ETRI_Cost!E43 -> 1350 | AH3: =ETRI_Cost!F45 -> 1290 | AI3: =ETRI_Cost!G45 -> 1190 | AJ3: =ETRI_Cost!H45 -> 1140 | AK3: =ETRI_Cost!I45 -> 1110
A4: 3 | B4: 3 | C4: CL1-003 | D4: GALWAY | E4: GALWAY | F4: SS-106 | G4: Clifden 38kV Substation | H4: ESB Networks | I4: 38000 | J4: 38000 | K4: low | L4: 11.691 | M4: 12 | N4: 0.133 | O4: 1 | P4: 0.133 | Q4: 3.45 | R4: 3.45 | S4: 1492540 | T4: 1 | U4: 432620.29 | V4: 2.3114958 | X4: 3.45 | Y4: 223.01739 | AA4: =SUMIFS(X:X,Y:Y,">"&AC4,Y:Y,"<"&AD4)/1000 -> 8.1111 | AB4: {=SUMPRODUCT(X:X,Y:Y,--(Y:Y>AC4),--(Y:Y<AD4))} -> 199028.83 | AC4: 0 | AD4: 30 | AE4: {=SUMPRODUCT(X:X,Y:Y,--(Y:Y>AC4),--(Y:Y<AD4))/SUMIFS(X:X,Y:Y,">"&AC4,Y:Y,"<"&AD4)} -> 24.537835 | AG4: =AG3+$AE4 -> 1374.5378 | AH4: =AH3+$AE4 -> 1314.5378 | AI4: =AI3+$AE4 -> 1214.5378 | AJ4: =AJ3+$AE4 -> 1164.5378 | AK4: =AK3+$AE4 -> 1134.5378
A5: 4 | B5: 4 | C5: CL1-004 | D5: DONEGAL | E5: DONEGAL | F5: SS-250 | G5: Kilcar 38kV Substation | H5: ESB Networks | I5: 38000 | J5: 38000 | K5: 10000 | L5: 13.24 | M5: 14 | N5: 0.133 | O5: 1 | P5: 0.133 | Q5: 3.45 | R5: 3.45 | S5: 1597940 | T5: 1 | U5: 463171.01 | V5: 2.1590298 | X5: 3.45 | Y5: 432.62029 | AA5: =SUMIFS(X:X,Y:Y,">"&AC5,Y:Y,"<"&AD5)/1000 -> 8.73225 | AB5: {=SUMPRODUCT(X:X,Y:Y,--(Y:Y>AC5),--(Y:Y<AD5))} -> 338735.64 | AC5: 30 | AD5: 50 | AE5: {=SUMPRODUCT(X:X,Y:Y,--(Y:Y>AC5),--(Y:Y<AD5))/SUMIFS(X:X,Y:Y,">"&AC5,Y:Y,"<"&AD5)} -> 38.791336 | AG5: =AG4+$AE5 -> 1413.3292 | AH5: =AH4+$AE5 -> 1353.3292 | AI5: =AI4+$AE5 -> 1253.3292 | AJ5: =AJ4+$AE5 -> 1203.3292 | AK5: =AK4+$AE5 -> 1173.3292
A6: 5 | B6: 5 | C6: CL1-005 | D6: DONEGAL | E6: DONEGAL | F6: SS-138 | G6: Creeslough 38kV Substation | H6: ESB Networks | I6: 38000 | J6: 38000 | K6: low | L6: 9.962 | M6: 10 | N6: 0.157 | O6: 1 | P6: 0.157 | Q6: 3.45 | R6: 3.45 | S6: 1387140 | T6: 1 | U6: 402069.57 | V6: 2.4871318 | X6: 3.45 | Y6: 463.17101 | AA6: =SUMIFS(X:X,Y:Y,">"&AC6,Y:Y,"<"&AD6)/1000 -> 5.7897 | AB6: {=SUMPRODUCT(X:X,Y:Y,--(Y:Y>AC6),--(Y:Y<AD6))} -> 399230.19 | AC6: 50 | AD6: 100 | AE6: {=SUMPRODUCT(X:X,Y:Y,--(Y:Y>AC6),--(Y:Y<AD6))/SUMIFS(X:X,Y:Y,">"&AC6,Y:Y,"<"&AD6)} -> 68.955246 | AG6: =AG5+$AE6 -> 1482.2844 | AH6: =AH5+$AE6 -> 1422.2844 | AI6: =AI5+$AE6 -> 1322.2844 | AJ6: =AJ5+$AE6 -> 1272.2844 | AK6: =AK5+$AE6 -> 1242.2844
A7: 6 | B7: 6 | C7: CL1-006 | D7: DONEGAL | E7: DONEGAL | F7: SS-119 | G7: Drumlough Hill (1) 38kV Substation | H7: ESB Networks | I7: 38000 | J7: low | K7: 38000 | L7: 10.639 | M7: 11 | N7: 0.093 | O7: 1 | P7: 0.093 | Q7: 3.45 | R7: 3.45 | S7: 1439840 | T7: 1 | U7: 417344.93 | V7: 2.3960996 | X7: 3.45 | Y7: 402.06957 | AA7: =SUMIFS(X:X,Y:Y,">"&AC7,Y:Y,"<"&AD7)/1000 -> 3.9777 | AB7: {=SUMPRODUCT(X:X,Y:Y,--(Y:Y>AC7),--(Y:Y<AD7))} -> 606529.79 | AC7: 100 | AD7: 200 | AE7: {=SUMPRODUCT(X:X,Y:Y,--(Y:Y>AC7),--(Y:Y<AD7))/SUMIFS(X:X,Y:Y,">"&AC7,Y:Y,"<"&AD7)} -> 152.48254 | AG7: =AG6+$AE7 -> 1634.767 | AH7: =AH6+$AE7 -> 1574.767 | AI7: =AI6+$AE7 -> 1474.767 | AJ7: =AJ6+$AE7 -> 1424.767 | AK7: =AK6+$AE7 -> 1394.767
A8: 7 | B8: 7 | C8: CL1-007 | D8: CLARE | E8: CLARE | F8: SS-708 | H8: EirGrid | I8: 110000 | J8: medium | K8: 110000 | L8: 1.526 | M8: 2 | N8: 0.126 | O8: 1 | P8: 0.126 | Q8: 3.45 | R8: 3.45 | S8: 1340080 | T8: 11 | U8: 388428.99 | V8: 2.5744732 | X8: 3.45 | Y8: 417.34493 | AA8: =SUMIFS(X:X,Y:Y,">"&AC8,Y:Y,"<"&AD8)/1000 -> 3.99075 | AB8: {=SUMPRODUCT(X:X,Y:Y,--(Y:Y>AC8),--(Y:Y<AD8))} -> 1427308.2 | AC8: 200 | AD8: 1000 | AE8: {=SUMPRODUCT(X:X,Y:Y,--(Y:Y>AC8),--(Y:Y<AD8))/SUMIFS(X:X,Y:Y,">"&AC8,Y:Y,"<"&AD8)} -> 357.65413 | AG8: =AG7+$AE8 -> 1992.4211 | AH8: =AH7+$AE8 -> 1932.4211 | AI8: =AI7+$AE8 -> 1832.4211 | AJ8: =AJ7+$AE8 -> 1782.4211 | AK8: =AK7+$AE8 -> 1752.4211
A9: 8 | B9: 8 | C9: CL1-008 | D9: DUBLIN | E9: DUBLIN | F9: SS-014 | G9: Ballyboden 38kV Substation | H9: ESB Networks | I9: 38000 | J9: 38000 | K9: 10000 | L9: 6.009 | M9: 7 | N9: 0.28 | O9: 1 | P9: 0.28 | Q9: 3.45 | R9: 3.45 | S9: 839680 | T9: 4 | U9: 243385.51 | V9: 4.1087081 | X9: 3.45 | Y9: 388.42899
A10: 9 | B10: 9 | C10: CL1-009 | D10: DUBLIN | E10: DUBLIN | F10: SS-014 | G10: Ballyboden 38kV Substation | H10: ESB Networks | I10: 38000 | J10: 38000 | K10: 10000 | L10: 5.282 | M10: 6 | N10: 0.178 | O10: 1 | P10: 0.178 | Q10: 3.45 | R10: 3.45 | S10: 769410 | T10: 4 | U10: 223017.39 | V10: 4.4839552 | X10: 3.45 | Y10: 243.38551
A11: 10 | B11: 10 | C11: CL1-010 | D11: WICKLOW | E11: WICKLOW | F11: SS-010 | G11: Fassaroe 110kV Substation | H11: EirGrid | I11: 110000 | J11: 110000 | K11: 38000 | L11: 4.695 | M11: 5 | N11: 0.2 | O11: 1 | P11: 0.2 | Q11: 3.45 | R11: 3.45 | S11: 1679970 | T11: 7 | U11: 486947.83 | V11: 2.0536081 | X11: 3.45 | Y11: 223.01739
A12: 11 | B12: 11 | C12: CL1-011 | D12: WICKLOW | E12: WICKLOW | F12: SS-010 | G12: Fassaroe 110kV Substation | H12: EirGrid | I12: 110000 | J12: 110000 | K12: 38000 | L12: 5.608 | M12: 6 | N12: 0.116 | O12: 1 | P12: 0.116 | Q12: 3.45 | R12: 3.45 | S12: 1732670 | T12: 7 | U12: 502223.19 | V12: 1.9911466 | X12: 3.45 | Y12: 486.94783
A13: 12 | B13: 12 | C13: CL1-012 | D13: WICKLOW | E13: WICKLOW | F13: SS-597 | G13: Kilmartin 38kV Substation | H13: ESB Networks | I13: 38000 | J13: 38000 | K13: low | L13: 5.924 | M13: 6 | N13: 0.134 | O13: 1 | P13: 0.134 | Q13: 3.45 | R13: 3.45 | S13: 769410 | T13: 4 | U13: 223017.39 | V13: 4.4839552 | X13: 3.45 | Y13: 502.22319
A14: 13 | B14: 13 | C14: CL1-013 | D14: CORK | E14: CORK | F14: SS-253 | G14: Ballydehob 38kV Substation | H14: ESB Networks | I14: 38000 | J14: 38000 | K14: low | L14: 8.843 | M14: 9 | N14: 0.139 | O14: 1 | P14: 0.139 | Q14: 3.45 | R14: 3.45 | S14: 1334440 | T14: 1 | U14: 386794.2 | V14: 2.5853542 | X14: 3.45 | Y14: 223.01739
A15: 14 | B15: 14 | C15: CL1-014 | D15: WICKLOW | E15: WICKLOW | F15: SS-037 | G15: Ballybeg 110kV Substation | H15: EirGrid | I15: 110000 | J15: 110000 | K15: 38000 | L15: 4.542 | M15: 5 | N15: 0.154 | O15: 1 | P15: 0.154 | Q15: 3.45 | R15: 3.45 | S15: 1679970 | T15: 7 | U15: 486947.83 | V15: 2.0536081 | X15: 3.45 | Y15: 386.7942
A16: 15 | B16: 15 | C16: CL1-015 | D16: KERRY | E16: KERRY | F16: SS-635 | G16: Dingle 38kV Substation | H16: ESB Networks | I16: 38000 | J16: 38000 | K16: 20000 | L16: 11.995 | M16: 12 | N16: 0.155 | O16: 1 | P16: 0.155 | Q16: 3.45 | R16: 3.45 | S16: 1492540 | T16: 1 | U16: 432620.29 | V16: 2.3114958 | X16: 3.45 | Y16: 486.94783
A17: 16 | B17: 16 | C17: CL1-016 | D17: CORK | E17: CORK | F17: SS-273 | G17: Castletownbere 38kV Substation | H17: ESB Networks | I17: 38000 | J17: 38000 | K17: 20000 | L17: 11.179 | M17: 12 | N17: 0.101 | O17: 1 | P17: 0.101 | Q17: 3.45 | R17: 3.45 | S17: 1492540 | T17: 1 | U17: 432620.29 | V17: 2.3114958 | X17: 3.45 | Y17: 432.62029
A18: 17 | B18: 17 | C18: CL1-017 | D18: DONEGAL | E18: DONEGAL | F18: SS-610 | G18: Milford (North) 38kV Substation | H18: ESB Networks | I18: 38000 | J18: 38000 | K18: low | L18: 14.864 | M18: 15 | N18: 0.149 | O18: 1 | P18: 0.149 | Q18: 3.45 | R18: 3.45 | S18: 1650640 | T18: 1 | U18: 478446.38 | V18: 2.0900984 | X18: 3.45 | Y18: 432.62029
A19: 18 | B19: 18 | C19: CL1-018 | D19: DONEGAL | E19: DONEGAL | F19: SS-117 | G19: Crockahenny 38kV Substation | H19: ESB Networks | I19: 38000 | J19: low | K19: 38000 | L19: 2.217 | M19: 3 | N19: 0.259 | O19: 1 | P19: 0.259 | Q19: 3.45 | R19: 3.45 | S19: 558600 | T19: 4 | U19: 161913.04 | V19: 6.1761547 | X19: 3.45 | Y19: 478.44638
A20: 19 | B20: 19 | C20: CL1-019 | D20: MAYO | E20: MAYO | F20: SS-642 | G20: Achill 38kV Substation | H20: ESB Networks | I20: 38000 | J20: 38000 | K20: 20000 | L20: 7.887 | M20: 8 | N20: 0.337 | O20: 1 | P20: 0.337 | Q20: 3.45 | R20: 3.45 | S20: 909950 | T20: 4 | U20: 263753.62 | V20: 3.7914171 | X20: 3.45 | Y20: 161.91304
A21: 20 | B21: 20 | C21: CL1-020 | D21: DONEGAL | E21: DONEGAL | F21: SS-123 | G21: Derrybeg 38kV Substation | H21: ESB Networks | I21: 38000 | J21: 38000 | K21: 10000 | L21: 8.548 | M21: 9 | N21: 0.523 | O21: 1 | P21: 0.523 | Q21: 3.45 | R21: 3.45 | S21: 1334440 | T21: 1 | U21: 386794.2 | V21: 2.5853542 | X21: 3.45 | Y21: 263.75362
A22: 21 | B22: 21 | C22: CL1-021 | D22: KERRY | E22: KERRY | F22: SS-636 | G22: Garranebane 38kV Substation | H22: ESB Networks | I22: 38000 | J22: 38000 | K22: 20000 | L22: 13.635 | M22: 14 | N22: 0.289 | O22: 1 | P22: 0.289 | Q22: 3.45 | R22: 3.45 | S22: 1597940 | T22: 1 | U22: 463171.01 | V22: 2.1590298 | X22: 3.45 | Y22: 386.7942
A23: 22 | B23: 22 | C23: CL1-022 | D23: WICKLOW | E23: WICKLOW | F23: SS-209 | G23: Blessington 38kV Substation | H23: ESB Networks | I23: 38000 | J23: 38000 | K23: 20000 | L23: 7.06 | M23: 8 | N23: 0.325 | O23: 1 | P23: 0.325 | Q23: 3.45 | R23: 3.45 | S23: 909950 | T23: 4 | U23: 263753.62 | V23: 3.7914171 | X23: 3.45 | Y23: 463.17101
A24: 23 | B24: 23 | C24: CL1-023 | D24: DONEGAL | E24: DONEGAL | F24: SS-117 | G24: Crockahenny 38kV Substation | H24: ESB Networks | I24: 38000 | J24: low | K24: 38000 | L24: 4.876 | M24: 5 | N24: 0.614 | O24: 1 | P24: 0.4605 | Q24: 3.45 | R24: 3.45 | S24: 699140 | T24: 4 | U24: 202649.28 | V24: 4.934634 | X24: 3.45 | Y24: 263.75362
A25: 24 | B25: 24 | C25: CL1-024 | D25: DONEGAL | E25: DONEGAL | F25: SS-617 | G25: Mulreavy 110kV Substation | H25: EirGrid | I25: 110000 | J25: 33000 | K25: 110000 | L25: 12.664 | M25: 13 | N25: 0.209 | O25: 1 | P25: 0.209 | Q25: 3.45 | R25: 3.45 | S25: 2101570 | T25: 7 | U25: 609150.72 | V25: 1.6416298 | X25: 3.45 | Y25: 202.64928
A26: 25 | B26: 25 | C26: CL1-025 | D26: CAVAN | E26: CAVAN | F26: SS-110 | G26: Corraclassy 110kV Substation | H26: EirGrid | I26: 110000 | L26: 10.905 | M26: 11 | N26: 0.786 | O26: 1 | P26: 0.5895 | Q26: 3.45 | R26: 3.45 | S26: 1996170 | T26: 7 | U26: 578600 | V26: 1.7283097 | X26: 3.45 | Y26: 609.15072
A27: 26 | B27: 26 | C27: CL1-026 | D27: LOUTH | E27: LOUTH | F27: SS-650 | G27: Ballymascanlan 38kV Substation | H27: ESB Networks | I27: 38000 | J27: 38000 | K27: low | L27: 4.994 | M27: 5 | N27: 0.211 | O27: 1 | P27: 0.211 | Q27: 3.45 | R27: 3.45 | S27: 699140 | T27: 4 | U27: 202649.28 | V27: 4.934634 | X27: 3.45 | Y27: 578.6
A28: 27 | B28: 27 | C28: CL1-027 | D28: CORK | E28: CORK | F28: SS-362 | G28: Glengarriff 38kV Substation | H28: ESB Networks | I28: 38000 | J28: 38000 | K28: 20000 | L28: 12.641 | M28: 13 | N28: 0.281 | O28: 1 | P28: 0.281 | Q28: 3.45 | R28: 3.45 | S28: 1545240 | T28: 1 | U28: 447895.65 | V28: 2.2326629 | X28: 3.45 | Y28: 202.64928
A29: 28 | B29: 28 | C29: CL1-028 | D29: KERRY | E29: KERRY | F29: SS-362 | G29: Glengarriff 38kV Substation | H29: ESB Networks | I29: 38000 | J29: 38000 | K29: 20000 | L29: 12.848 | M29: 13 | N29: 0.134 | O29: 1 | P29: 0.134 | Q29: 3.45 | R29: 3.45 | S29: 1545240 | T29: 1 | U29: 447895.65 | V29: 2.2326629 | X29: 3.45 | Y29: 447.89565
A30: 29 | B30: 29 | C30: CL1-029 | D30: CORK | E30: CORK | F30: SS-273 | G30: Castletownbere 38kV Substation | H30: ESB Networks | I30: 38000 | J30: 38000 | K30: 20000 | L30: 12.044 | M30: 13 | N30: 0.17 | O30: 1 | P30: 0.17 | Q30: 3.45 | R30: 3.45 | S30: 1545240 | T30: 1 | U30: 447895.65 | V30: 2.2326629 | X30: 3.45 | Y30: 447.89565
A31: 30 | B31: 30 | C31: CL1-030 | D31: KERRY | E31: KERRY | F31: SS-337 | G31: Knockaneden 38kV Substation | H31: ESB Networks | I31: 38000 | J31: low | K31: 38000 | L31: 13.637 | M31: 14 | N31: 0.496 | O31: 1 | P31: 0.496 | Q31: 3.45 | R31: 3.45 | S31: 1597940 | T31: 1 | U31: 463171.01 | V31: 2.1590298 | X31: 3.45 | Y31: 447.89565
A32: 31 | B32: 31 | C32: CL1-031 | D32: KERRY | E32: KERRY | F32: SS-151 | G32: Kenmare 38kV Substation | H32: ESB Networks | I32: 38000 | J32: 38000 | K32: low | L32: 12.786 | M32: 13 | N32: 0.351 | O32: 1 | P32: 0.351 | Q32: 3.45 | R32: 3.45 | S32: 1545240 | T32: 1 | U32: 447895.65 | V32: 2.2326629 | X32: 3.45 | Y32: 463.17101
A33: 32 | B33: 32 | C33: CL1-032 | D33: KERRY | E33: KERRY | F33: SS-151 | G33: Kenmare 38kV Substation | H33: ESB Networks | I33: 38000 | J33: 38000 | K33: low | L33: 14.48 | M33: 15 | N33: 0.438 | O33: 1 | P33: 0.438 | Q33: 3.45 | R33: 3.45 | S33: 1650640 | T33: 1 | U33: 478446.38 | V33: 2.0900984 | X33: 3.45 | Y33: 447.89565
A34: 33 | B34: 33 | C34: CL1-033 | D34: KERRY | E34: KERRY | F34: SS-321 | G34: Milltown 38kV Substation | H34: ESB Networks | I34: 38000 | J34: 38000 | K34: 20000 | L34: 11.713 | M34: 12 | N34: 0.121 | O34: 1 | P34: 0.121 | Q34: 3.45 | R34: 3.45 | S34: 1492540 | T34: 1 | U34: 432620.29 | V34: 2.3114958 | X34: 3.45 | Y34: 478.44638
A35: 34 | B35: 34 | C35: CL1-034 | D35: KERRY | E35: KERRY | F35: SS-387 | G35: Coolcorcoran 38kV Substation | H35: ESB Networks | I35: 38000 | J35: 38000 | K35: low | L35: 11.301 | M35: 12 | N35: 0.237 | O35: 1 | P35: 0.237 | Q35: 3.45 | R35: 3.45 | S35: 1492540 | T35: 1 | U35: 432620.29 | V35: 2.3114958 | X35: 3.45 | Y35: 432.62029
A36: 35 | B36: 35 | C36: CL1-035 | D36: KERRY | E36: KERRY | F36: SS-151 | G36: Kenmare 38kV Substation | H36: ESB Networks | I36: 38000 | J36: 38000 | K36: low | L36: 15.65 | M36: 16 | N36: 0.262 | O36: 1 | P36: 0.262 | Q36: 3.45 | R36: 3.45 | S36: 1703340 | T36: 1 | U36: 493721.74 | V36: 2.0254324 | X36: 3.45 | Y36: 432.62029
A37: 36 | B37: 36 | C37: CL1-036 | D37: KERRY | E37: KERRY | F37: SS-636 | G37: Garranebane 38kV Substation | H37: ESB Networks | I37: 38000 | J37: 38000 | K37: 20000 | L37: 4.091 | M37: 5 | N37: 0.567 | O37: 1 | P37: 0.567 | Q37: 3.45 | R37: 3.45 | S37: 699140 | T37: 4 | U37: 202649.28 | V37: 4.934634 | X37: 3.45 | Y37: 493.72174
A38: 37 | B38: 37 | C38: CL1-037 | D38: KERRY | E38: KERRY | F38: SS-337 | G38: Knockaneden 38kV Substation | H38: ESB Networks | I38: 38000 | J38: low | K38: 38000 | L38: 2.79 | M38: 3 | N38: 0.399 | O38: 1 | P38: 0.399 | Q38: 3.45 | R38: 3.45 | S38: 558600 | T38: 4 | U38: 161913.04 | V38: 6.1761547 | X38: 3.45 | Y38: 202.64928
A39: 38 | B39: 38 | C39: CL1-038 | D39: KERRY | E39: KERRY | F39: SS-337 | G39: Knockaneden 38kV Substation | H39: ESB Networks | I39: 38000 | J39: low | K39: 38000 | L39: 14.268 | M39: 15 | N39: 0.109 | O39: 1 | P39: 0.109 | Q39: 3.45 | R39: 3.45 | S39: 1650640 | T39: 1 | U39: 478446.38 | V39: 2.0900984 | X39: 3.45 | Y39: 161.91304
A40: 39 | B40: 39 | C40: CL1-039 | D40: KERRY | E40: KERRY | F40: SS-337 | G40: Knockaneden 38kV Substation | H40: ESB Networks | I40: 38000 | J40: low | K40: 38000 | L40: 9.745 | M40: 10 | N40: 0.123 | O40: 1 | P40: 0.123 | Q40: 3.45 | R40: 3.45 | S40: 1387140 | T40: 1 | U40: 402069.57 | V40: 2.4871318 | X40: 3.45 | Y40: 478.44638
A41: 40 | B41: 40 | C41: CL1-040 | D41: KERRY | E41: KERRY | F41: SS-337 | G41: Knockaneden 38kV Substation | H41: ESB Networks | I41: 38000 | J41: low | K41: 38000 | L41: 9.612 | M41: 10 | N41: 0.099 | O41: 1 | P41: 0.099 | Q41: 3.45 | R41: 3.45 | S41: 1387140 | T41: 1 | U41: 402069.57 | V41: 2.4871318 | X41: 3.45 | Y41: 402.06957
A42: 41 | B42: 41 | C42: CL1-041 | D42: KERRY | E42: KERRY | F42: SS-337 | G42: Knockaneden 38kV Substation | H42: ESB Networks | I42: 38000 | J42: low | K42: 38000 | L42: 15.118 | M42: 16 | N42: 0.109 | O42: 1 | P42: 0.109 | Q42: 3.45 | R42: 3.45 | S42: 1703340 | T42: 1 | U42: 493721.74 | V42: 2.0254324 | X42: 3.45 | Y42: 402.06957
A43: 42 | B43: 42 | C43: CL1-042 | D43: CORK | E43: CORK | F43: SS-362 | G43: Glengarriff 38kV Substation | H43: ESB Networks | I43: 38000 | J43: 38000 | K43: 20000 | L43: 1.996 | M43: 2 | N43: 0.14 | O43: 1 | P43: 0.14 | Q43: 3.45 | R43: 3.45 | S43: 488330 | T43: 4 | U43: 141544.93 | V43: 7.0648946 | X43: 3.45 | Y43: 493.72174
A44: 43 | B44: 43 | C44: CL1-043 | D44: CORK | E44: CORK | F44: SS-362 | G44: Glengarriff 38kV Substation | H44: ESB Networks | I44: 38000 | J44: 38000 | K44: 20000 | L44: 2.393 | M44: 3 | N44: 0.093 | O44: 1 | P44: 0.093 | Q44: 3.45 | R44: 3.45 | S44: 558600 | T44: 4 | U44: 161913.04 | V44: 6.1761547 | X44: 3.45 | Y44: 141.54493
A45: 44 | B45: 44 | C45: CL1-044 | D45: CORK | E45: KERRY | F45: SS-362 | G45: Glengarriff 38kV Substation | H45: ESB Networks | I45: 38000 | J45: 38000 | K45: 20000 | L45: 4.316 | M45: 5 | N45: 0.219 | O45: 1 | P45: 0.219 | Q45: 3.45 | R45: 3.45 | S45: 699140 | T45: 4 | U45: 202649.28 | V45: 4.934634 | X45: 3.45 | Y45: 161.91304
A46: 45 | B46: 45 | C46: CL1-045 | D46: KERRY | E46: KERRY | F46: SS-637 | G46: Kilgarvan 38kV Substation | H46: ESB Networks | I46: 38000 | J46: 38000 | K46: 20000 | L46: 4.375 | M46: 5 | N46: 0.163 | O46: 1 | P46: 0.163 | Q46: 3.45 | R46: 3.45 | S46: 699140 | T46: 4 | U46: 202649.28 | V46: 4.934634 | X46: 3.45 | Y46: 202.64928
A47: 46 | B47: 46 | C47: CL1-046 | D47: KERRY | E47: KERRY | F47: SS-637 | G47: Kilgarvan 38kV Substation | H47: ESB Networks | I47: 38000 | J47: 38000 | K47: 20000 | L47: 5.589 | M47: 6 | N47: 0.256 | O47: 1 | P47: 0.256 | Q47: 3.45 | R47: 3.45 | S47: 769410 | T47: 4 | U47: 223017.39 | V47: 4.4839552 | X47: 3.45 | Y47: 202.64928
A48: 47 | B48: 47 | C48: CL1-047 | D48: KERRY | E48: KERRY | F48: SS-635 | G48: Dingle 38kV Substation | H48: ESB Networks | I48: 38000 | J48: 38000 | K48: 20000 | L48: 10.077 | M48: 11 | N48: 0.349 | O48: 1 | P48: 0.349 | Q48: 3.45 | R48: 3.45 | S48: 1439840 | T48: 1 | U48: 417344.93 | V48: 2.3960996 | X48: 3.45 | Y48: 223.01739
A49: 48 | B49: 48 | C49: CL1-048 | D49: KERRY | E49: KERRY | F49: SS-634 | G49: Inch 38kV Substation | H49: ESB Networks | I49: 38000 | J49: 38000 | K49: 20000 | L49: 7.851 | M49: 8 | N49: 0.591 | O49: 1 | P49: 0.591 | Q49: 3.45 | R49: 3.45 | S49: 909950 | T49: 4 | U49: 263753.62 | V49: 3.7914171 | X49: 3.45 | Y49: 417.34493
A50: 49 | B50: 49 | C50: CL1-049 | D50: KERRY | E50: KERRY | F50: SS-140 | G50: Ballyard 38kV Substation | H50: ESB Networks | I50: 38000 | J50: 38000 | K50: 10000 | L50: 4.771 | M50: 5 | N50: 0.381 | O50: 1 | P50: 0.381 | Q50: 3.45 | R50: 3.45 | S50: 699140 | T50: 4 | U50: 202649.28 | V50: 4.934634 | X50: 3.45 | Y50: 263.75362
A51: 50 | B51: 50 | C51: CL1-050 | D51: CLARE | E51: CLARE | F51: SS-595 | G51: Kilkee 38kV Substation | H51: ESB Networks | I51: 38000 | J51: 38000 | K51: low | L51: 23.476 | M51: 24 | N51: 0.195 | O51: 1 | P51: 0.195 | Q51: 3.45 | R51: 3.45 | S51: 2124940 | T51: 1 | U51: 615924.64 | V51: 1.6235753 | X51: 3.45 | Y51: 202.64928
A52: 51 | B52: 51 | C52: CL1-051 | D52: CLARE | E52: CLARE | F52: SS-134 | G52: Ennistymon 38kV Substation | H52: ESB Networks | I52: 38000 | J52: 38000 | K52: low | L52: 15.891 | M52: 16 | N52: 0.111 | O52: 1 | P52: 0.111 | Q52: 3.45 | R52: 3.45 | S52: 1703340 | T52: 1 | U52: 493721.74 | V52: 2.0254324 | X52: 3.45 | Y52: 615.92464
A53: 52 | B53: 52 | C53: CL1-052 | D53: GALWAY | E53: GALWAY | F53: SS-105 | G53: Garroman 38kV Substation | H53: ESB Networks | I53: 38000 | J53: 38000 | K53: low | L53: 15.806 | M53: 16 | N53: 0.437 | O53: 1 | P53: 0.437 | Q53: 3.45 | R53: 3.45 | S53: 1703340 | T53: 1 | U53: 493721.74 | V53: 2.0254324 | X53: 3.45 | Y53: 493.72174
A54: 53 | B54: 53 | C54: CL1-053 | D54: GALWAY | E54: GALWAY | F54: SS-106 | G54: Clifden 38kV Substation | H54: ESB Networks | I54: 38000 | J54: 38000 | K54: low | L54: 11.451 | M54: 12 | N54: 0.189 | O54: 1 | P54: 0.189 | Q54: 3.45 | R54: 3.45 | S54: 1492540 | T54: 1 | U54: 432620.29 | V54: 2.3114958 | X54: 3.45 | Y54: 493.72174
A55: 54 | B55: 54 | C55: CL1-054 | D55: GALWAY | E55: GALWAY | F55: SS-106 | G55: Clifden 38kV Substation | H55: ESB Networks | I55: 38000 | J55: 38000 | K55: low | L55: 5.715 | M55: 6 | N55: 0.331 | O55: 1 | P55: 0.331 | Q55: 3.45 | R55: 3.45 | S55: 769410 | T55: 4 | U55: 223017.39 | V55: 4.4839552 | X55: 3.45 | Y55: 432.62029
A56: 55 | B56: 55 | C56: CL1-055 | D56: GALWAY | E56: GALWAY | F56: SS-105 | G56: Garroman 38kV Substation | H56: ESB Networks | I56: 38000 | J56: 38000 | K56: low | L56: 4.746 | M56: 5 | N56: 0.316 | O56: 1 | P56: 0.316 | Q56: 3.45 | R56: 3.45 | S56: 699140 | T56: 4 | U56: 202649.28 | V56: 4.934634 | X56: 3.45 | Y56: 223.01739
A57: 56 | B57: 56 | C57: CL1-056 | D57: GALWAY | E57: GALWAY | F57: SS-105 | G57: Garroman 38kV Substation | H57: ESB Networks | I57: 38000 | J57: 38000 | K57: low | L57: 14.998 | M57: 15 | N57: 0.394 | O57: 1 | P57: 0.394 | Q57: 3.45 | R57: 3.45 | S57: 1650640 | T57: 1 | U57: 478446.38 | V57: 2.0900984 | X57: 3.45 | Y57: 202.64928
A58: 57 | B58: 57 | C58: CL1-057 | D58: MAYO | E58: MAYO | F58: SS-461 | G58: Westport 38kV Substation | H58: ESB Networks | I58: 38000 | J58: 38000 | K58: 20000 | L58: 15.493 | M58: 16 | N58: 0.104 | O58: 1 | P58: 0.104 | Q58: 3.45 | R58: 3.45 | S58: 1703340 | T58: 1 | U58: 493721.74 | V58: 2.0254324 | X58: 3.45 | Y58: 478.44638
A59: 58 | B59: 58 | C59: CL1-058 | D59: GALWAY | E59: GALWAY | F59: SS-638 | G59: Oughterard 38kV Substation | H59: ESB Networks | I59: 38000 | J59: 38000 | K59: 10000 | L59: 12.648 | M59: 13 | N59: 0.377 | O59: 1 | P59: 0.377 | Q59: 3.45 | R59: 3.45 | S59: 1545240 | T59: 1 | U59: 447895.65 | V59: 2.2326629 | X59: 3.45 | Y59: 493.72174
A60: 59 | B60: 59 | C60: CL1-059 | D60: GALWAY | E60: GALWAY | F60: SS-638 | G60: Oughterard 38kV Substation | H60: ESB Networks | I60: 38000 | J60: 38000 | K60: 10000 | L60: 8.696 | M60: 9 | N60: 0.246 | O60: 1 | P60: 0.246 | Q60: 3.45 | R60: 3.45 | S60: 1334440 | T60: 1 | U60: 386794.2 | V60: 2.5853542 | X60: 3.45 | Y60: 447.89565
A61: 60 | B61: 60 | C61: CL1-060 | D61: MAYO | E61: MAYO | F61: SS-073 | G61: Carrowbeg 110kV Substation | H61: EirGrid | I61: 110000 | J61: 110000 | K61: 38000 | L61: 23.516 | M61: 24 | N61: 0.218 | O61: 1 | P61: 0.218 | Q61: 3.45 | R61: 3.45 | S61: 2681270 | T61: 7 | U61: 777179.71 | V61: 1.2867037 | X61: 3.45 | Y61: 386.7942
A62: 61 | B62: 61 | C62: CL1-061 | D62: MAYO | E62: MAYO | F62: SS-073 | G62: Carrowbeg 110kV Substation | H62: EirGrid | I62: 110000 | J62: 110000 | K62: 38000 | L62: 23.133 | M62: 24 | N62: 0.191 | O62: 1 | P62: 0.191 | Q62: 3.45 | R62: 3.45 | S62: 2681270 | T62: 7 | U62: 777179.71 | V62: 1.2867037 | X62: 3.45 | Y62: 777.17971
A63: 62 | B63: 62 | C63: CL1-062 | D63: MAYO | E63: MAYO | F63: SS-073 | G63: Carrowbeg 110kV Substation | H63: EirGrid | I63: 110000 | J63: 110000 | K63: 38000 | L63: 20.874 | M63: 21 | N63: 0.106 | O63: 1 | P63: 0.106 | Q63: 3.45 | R63: 3.45 | S63: 2523170 | T63: 7 | U63: 731353.62 | V63: 1.3673276 | X63: 3.45 | Y63: 777.17971
A64: 63 | B64: 63 | C64: CL1-063 | D64: GALWAY | E64: GALWAY | F64: SS-105 | G64: Garroman 38kV Substation | H64: ESB Networks | I64: 38000 | J64: 38000 | K64: low | L64: 3.98 | M64: 4 | N64: 0.279 | O64: 1 | P64: 0.279 | Q64: 3.45 | R64: 3.45 | S64: 628870 | T64: 4 | U64: 182281.16 | V64: 5.4860305 | X64: 3.45 | Y64: 731.35362
A65: 64 | B65: 64 | C65: CL1-064 | D65: GALWAY | E65: GALWAY | F65: SS-105 | G65: Garroman 38kV Substation | H65: ESB Networks | I65: 38000 | J65: 38000 | K65: low | L65: 11.894 | M65: 12 | N65: 0.276 | O65: 1 | P65: 0.276 | Q65: 3.45 | R65: 3.45 | S65: 1492540 | T65: 1 | U65: 432620.29 | V65: 2.3114958 | X65: 3.45 | Y65: 182.28116
A66: 65 | B66: 65 | C66: CL1-065 | D66: MAYO | E66: MAYO | F66: SS-317 | G66: Newport 38kV Substation | H66: ESB Networks | I66: 38000 | J66: 38000 | K66: 20000 | L66: 11.804 | M66: 12 | N66: 0.167 | O66: 1 | P66: 0.167 | Q66: 3.45 | R66: 3.45 | S66: 1492540 | T66: 1 | U66: 432620.29 | V66: 2.3114958 | X66: 3.45 | Y66: 432.62029
A67: 66 | B67: 66 | C67: CL1-066 | D67: MAYO | E67: MAYO | F67: SS-133 | G67: Bellacorrick 110kV Substation | H67: EirGrid | I67: 110000 | J67: 110000 | K67: 38000 | L67: 10.284 | M67: 11 | N67: 0.094 | O67: 1 | P67: 0.094 | Q67: 3.45 | R67: 3.45 | S67: 1996170 | T67: 7 | U67: 578600 | V67: 1.7283097 | X67: 3.45 | Y67: 432.62029
A68: 67 | B68: 67 | C68: CL1-067 | D68: MAYO | E68: MAYO | F68: SS-419 | G68: Bangor 38kV Substation | H68: ESB Networks | I68: 38000 | J68: 38000 | K68: low | L68: 5.543 | M68: 6 | N68: 0.698 | O68: 1 | P68: 0.5235 | Q68: 3.45 | R68: 3.45 | S68: 769410 | T68: 4 | U68: 223017.39 | V68: 4.4839552 | X68: 3.45 | Y68: 578.6
A69: 68 | B69: 68 | C69: CL1-068 | D69: MAYO | E69: MAYO | F69: SS-419 | G69: Bangor 38kV Substation | H69: ESB Networks | I69: 38000 | J69: 38000 | K69: low | L69: 14.459 | M69: 15 | N69: 0.288 | O69: 1 | P69: 0.288 | Q69: 3.45 | R69: 3.45 | S69: 1650640 | T69: 1 | U69: 478446.38 | V69: 2.0900984 | X69: 3.45 | Y69: 223.01739
A70: 69 | B70: 69 | C70: CL1-069 | D70: MAYO | E70: MAYO | F70: SS-419 | G70: Bangor 38kV Substation | H70: ESB Networks | I70: 38000 | J70: 38000 | K70: low | L70: 15.611 | M70: 16 | N70: 0.148 | O70: 1 | P70: 0.148 | Q70: 3.45 | R70: 3.45 | S70: 1703340 | T70: 1 | U70: 493721.74 | V70: 2.0254324 | X70: 3.45 | Y70: 478.44638
A71: 70 | B71: 70 | C71: CL1-070 | D71: MAYO | E71: MAYO | F71: SS-419 | G71: Bangor 38kV Substation | H71: ESB Networks | I71: 38000 | J71: 38000 | K71: low | L71: 15.467 | M71: 16 | N71: 0.187 | O71: 1 | P71: 0.187 | Q71: 3.45 | R71: 3.45 | S71: 1703340 | T71: 1 | U71: 493721.74 | V71: 2.0254324 | X71: 3.45 | Y71: 493.72174
A72: 71 | B72: 71 | C72: CL1-071 | D72: MAYO | E72: MAYO | F72: SS-419 | G72: Bangor 38kV Substation | H72: ESB Networks | I72: 38000 | J72: 38000 | K72: low | L72: 16.38 | M72: 17 | N72: 0.131 | O72: 1 | P72: 0.131 | Q72: 3.45 | R72: 3.45 | S72: 1756040 | T72: 1 | U72: 508997.1 | V72: 1.9646477 | X72: 3.45 | Y72: 493.72174
A73: 72 | B73: 72 | C73: CL1-072 | D73: MAYO | E73: MAYO | F73: SS-419 | G73: Bangor 38kV Substation | H73: ESB Networks | I73: 38000 | J73: 38000 | K73: low | L73: 1.724 | M73: 2 | N73: 0.688 | O73: 1 | P73: 0.516 | Q73: 3.45 | R73: 3.45 | S73: 488330 | T73: 4 | U73: 141544.93 | V73: 7.0648946 | X73: 3.45 | Y73: 508.9971
A74: 73 | B74: 73 | C74: CL1-073 | D74: MAYO | E74: MAYO | F74: SS-234 | G74: Crossmolina 38kV Substation | H74: ESB Networks | I74: 38000 | J74: 38000 | K74: low | L74: 13.238 | M74: 14 | N74: 0.596 | O74: 1 | P74: 0.447 | Q74: 3.45 | R74: 3.45 | S74: 1597940 | T74: 1 | U74: 463171.01 | V74: 2.1590298 | X74: 3.45 | Y74: 141.54493
A75: 74 | B75: 74 | C75: CL1-074 | D75: MAYO | E75: MAYO | F75: SS-133 | G75: Bellacorrick 110kV Substation | H75: EirGrid | I75: 110000 | J75: 110000 | K75: 38000 | L75: 13.919 | M75: 14 | N75: 0.619 | O75: 1 | P75: 0.46425 | Q75: 3.45 | R75: 3.45 | S75: 2154270 | T75: 7 | U75: 624426.09 | V75: 1.6014706 | X75: 3.45 | Y75: 463.17101
A76: 75 | B76: 75 | C76: CL1-075 | D76: MAYO | E76: MAYO | F76: SS-710 | G76: Tawnaghmore 110kV Substation | H76: EirGrid | I76: 110000 | J76: low | K76: 110000 | L76: 14.333 | M76: 15 | N76: 0.103 | O76: 1 | P76: 0.103 | Q76: 3.45 | R76: 3.45 | S76: 2206970 | T76: 7 | U76: 639701.45 | V76: 1.5632292 | X76: 3.45 | Y76: 624.42609
A77: 76 | B77: 76 | C77: CL1-076 | D77: MAYO | E77: MAYO | F77: SS-710 | G77: Tawnaghmore 110kV Substation | H77: EirGrid | I77: 110000 | J77: low | K77: 110000 | L77: 16.962 | M77: 17 | N77: 0.325 | O77: 1 | P77: 0.325 | Q77: 3.45 | R77: 3.45 | S77: 2312370 | T77: 7 | U77: 670252.17 | V77: 1.4919758 | X77: 3.45 | Y77: 639.70145
A78: 77 | B78: 77 | C78: CL1-077 | D78: MAYO | E78: MAYO | F78: SS-419 | G78: Bangor 38kV Substation | H78: ESB Networks | I78: 38000 | J78: 38000 | K78: low | L78: 7.99 | M78: 8 | N78: 0.129 | O78: 1 | P78: 0.129 | Q78: 3.45 | R78: 3.45 | S78: 909950 | T78: 4 | U78: 263753.62 | V78: 3.7914171 | X78: 3.45 | Y78: 670.25217
A79: 78 | B79: 78 | C79: CL1-078 | D79: SLIGO | E79: SLIGO | F79: SS-075 | G79: Cunghill 110kV Substation | H79: EirGrid | I79: 110000 | J79: 110000 | K79: medium | L79: 11.375 | M79: 12 | N79: 0.246 | O79: 1 | P79: 0.246 | Q79: 3.45 | R79: 3.45 | S79: 2048870 | T79: 7 | U79: 593875.36 | V79: 1.683855 | X79: 3.45 | Y79: 263.75362
A80: 79 | B80: 79 | C80: CL1-079 | D80: SLIGO | E80: SLIGO | F80: SS-075 | G80: Cunghill 110kV Substation | H80: EirGrid | I80: 110000 | J80: 110000 | K80: medium | L80: 11.206 | M80: 12 | N80: 0.242 | O80: 1 | P80: 0.242 | Q80: 3.45 | R80: 3.45 | S80: 2048870 | T80: 7 | U80: 593875.36 | V80: 1.683855 | X80: 3.45 | Y80: 593.87536
A81: 80 | B81: 80 | C81: CL1-080 | D81: SLIGO | E81: LEITRIM | F81: SS-042 | G81: Ballytivnan 38kV Substation | H81: ESB Networks | I81: 38000 | J81: 38000 | K81: 10000 | L81: 10.22 | M81: 11 | N81: 0.206 | O81: 1 | P81: 0.206 | Q81: 3.45 | R81: 3.45 | S81: 1439840 | T81: 1 | U81: 417344.93 | V81: 2.3960996 | X81: 3.45 | Y81: 593.87536
A82: 81 | B82: 81 | C82: CL1-081 | D82: SLIGO | E82: SLIGO | F82: SS-042 | G82: Ballytivnan 38kV Substation | H82: ESB Networks | I82: 38000 | J82: 38000 | K82: 10000 | L82: 8.688 | M82: 9 | N82: 0.249 | O82: 1 | P82: 0.249 | Q82: 3.45 | R82: 3.45 | S82: 1334440 | T82: 1 | U82: 386794.2 | V82: 2.5853542 | X82: 3.45 | Y82: 417.34493
A83: 82 | B83: 82 | C83: CL1-082 | D83: SLIGO | E83: SLIGO | F83: SS-042 | G83: Ballytivnan 38kV Substation | H83: ESB Networks | I83: 38000 | J83: 38000 | K83: 10000 | L83: 8.236 | M83: 9 | N83: 0.132 | O83: 1 | P83: 0.132 | Q83: 3.45 | R83: 3.45 | S83: 1334440 | T83: 1 | U83: 386794.2 | V83: 2.5853542 | X83: 3.45 | Y83: 386.7942
A84: 83 | B84: 83 | C84: CL1-083 | D84: DONEGAL | E84: DONEGAL | F84: SS-250 | G84: Kilcar 38kV Substation | H84: ESB Networks | I84: 38000 | J84: 38000 | K84: 10000 | L84: 4.929 | M84: 5 | N84: 0.527 | O84: 1 | P84: 0.527 | Q84: 3.45 | R84: 3.45 | S84: 699140 | T84: 4 | U84: 202649.28 | V84: 4.934634 | X84: 3.45 | Y84: 386.7942
A85: 84 | B85: 84 | C85: CL1-084 | D85: DONEGAL | E85: DONEGAL | F85: SS-250 | G85: Kilcar 38kV Substation | H85: ESB Networks | I85: 38000 | J85: 38000 | K85: 10000 | L85: 13.065 | M85: 14 | N85: 0.101 | O85: 1 | P85: 0.101 | Q85: 3.45 | R85: 3.45 | S85: 1597940 | T85: 1 | U85: 463171.01 | V85: 2.1590298 | X85: 3.45 | Y85: 202.64928
A86: 85 | B86: 85 | C86: CL1-085 | D86: DONEGAL | E86: DONEGAL | F86: SS-090 | G86: Corkermore 38kV Substation | H86: ESB Networks | I86: 38000 | J86: low | K86: 38000 | L86: 9.143 | M86: 10 | N86: 0.599 | O86: 1 | P86: 0.44925 | Q86: 3.45 | R86: 3.45 | S86: 1387140 | T86: 1 | U86: 402069.57 | V86: 2.4871318 | X86: 3.45 | Y86: 463.17101
A87: 86 | B87: 86 | C87: CL1-086 | D87: DONEGAL | E87: DONEGAL | F87: SS-250 | G87: Kilcar 38kV Substation | H87: ESB Networks | I87: 38000 | J87: 38000 | K87: 10000 | L87: 11.022 | M87: 12 | N87: 0.205 | O87: 1 | P87: 0.205 | Q87: 3.45 | R87: 3.45 | S87: 1492540 | T87: 1 | U87: 432620.29 | V87: 2.3114958 | X87: 3.45 | Y87: 402.06957
A88: 87 | B88: 87 | C88: CL1-087 | D88: DONEGAL | E88: DONEGAL | F88: SS-250 | G88: Kilcar 38kV Substation | H88: ESB Networks | I88: 38000 | J88: 38000 | K88: 10000 | L88: 3.316 | M88: 4 | N88: 0.442 | O88: 1 | P88: 0.442 | Q88: 3.45 | R88: 3.45 | S88: 628870 | T88: 4 | U88: 182281.16 | V88: 5.4860305 | X88: 3.45 | Y88: 432.62029
A89: 88 | B89: 88 | C89: CL1-088 | D89: DONEGAL | E89: DONEGAL | F89: SS-250 | G89: Kilcar 38kV Substation | H89: ESB Networks | I89: 38000 | J89: 38000 | K89: 10000 | L89: 2.243 | M89: 3 | N89: 0.097 | O89: 1 | P89: 0.097 | Q89: 3.45 | R89: 3.45 | S89: 558600 | T89: 4 | U89: 161913.04 | V89: 6.1761547 | X89: 3.45 | Y89: 182.28116
A90: 89 | B90: 89 | C90: CL1-089 | D90: DONEGAL | E90: DONEGAL | F90: SS-252 | G90: Killybegs 38kV Substation | H90: ESB Networks | I90: 38000 | J90: 38000 | K90: 10000 | L90: 4.306 | M90: 5 | N90: 0.197 | O90: 1 | P90: 0.197 | Q90: 3.45 | R90: 3.45 | S90: 699140 | T90: 4 | U90: 202649.28 | V90: 4.934634 | X90: 3.45 | Y90: 161.91304
A91: 90 | B91: 90 | C91: CL1-090 | D91: DONEGAL | E91: DONEGAL | F91: SS-684 | G91: Tievebrack 110kV Substation | H91: EirGrid | I91: 110000 | J91: 110000 | K91: 38000 | L91: 3.787 | M91: 4 | N91: 0.318 | O91: 1 | P91: 0.318 | Q91: 3.45 | R91: 3.45 | S91: 1627270 | T91: 7 | U91: 471672.46 | V91: 2.1201153 | X91: 3.45 | Y91: 202.64928
A92: 91 | B92: 91 | C92: CL1-091 | D92: DONEGAL | E92: DONEGAL | F92: SS-684 | G92: Tievebrack 110kV Substation | H92: EirGrid | I92: 110000 | J92: 110000 | K92: 38000 | L92: 3.504 | M92: 4 | N92: 0.395 | O92: 1 | P92: 0.395 | Q92: 3.45 | R92: 3.45 | S92: 1627270 | T92: 7 | U92: 471672.46 | V92: 2.1201153 | X92: 3.45 | Y92: 471.67246
A93: 92 | B93: 92 | C93: CL1-092 | D93: DONEGAL | E93: DONEGAL | F93: SS-123 | G93: Derrybeg 38kV Substation | H93: ESB Networks | I93: 38000 | J93: 38000 | K93: 10000 | L93: 10.189 | M93: 11 | N93: 0.286 | O93: 1 | P93: 0.286 | Q93: 3.45 | R93: 3.45 | S93: 1439840 | T93: 1 | U93: 417344.93 | V93: 2.3960996 | X93: 3.45 | Y93: 471.67246
A94: 93 | B94: 93 | C94: CL1-093 | D94: DONEGAL | E94: DONEGAL | F94: SS-119 | G94: Drumlough Hill (1) 38kV Substation | H94: ESB Networks | I94: 38000 | J94: low | K94: 38000 | L94: 1.583 | M94: 2 | N94: 0.166 | O94: 1 | P94: 0.166 | Q94: 3.45 | R94: 3.45 | S94: 488330 | T94: 4 | U94: 141544.93 | V94: 7.0648946 | X94: 3.45 | Y94: 417.34493
A95: 94 | B95: 94 | C95: CL1-094 | D95: DONEGAL | E95: DONEGAL | F95: SS-239 | G95: Moville 38kV Substation | H95: ESB Networks | I95: 38000 | J95: 38000 | K95: 20000 | L95: 3.296 | M95: 4 | N95: 0.115 | O95: 1 | P95: 0.115 | Q95: 3.45 | R95: 3.45 | S95: 628870 | T95: 4 | U95: 182281.16 | V95: 5.4860305 | X95: 3.45 | Y95: 141.54493
A96: 95 | B96: 95 | C96: CL1-095 | D96: DONEGAL | E96: DONEGAL | F96: SS-689 | H96: ESB Networks | I96: 38000 | L96: 5.174 | M96: 6 | N96: 0.108 | O96: 1 | P96: 0.108 | Q96: 3.45 | R96: 3.45 | S96: 769410 | T96: 4 | U96: 223017.39 | V96: 4.4839552 | X96: 3.45 | Y96: 182.28116
A97: 96 | B97: 96 | C97: CL1-096 | D97: MAYO | E97: MAYO | F97: SS-642 | G97: Achill 38kV Substation | H97: ESB Networks | I97: 38000 | J97: 38000 | K97: 20000 | L97: 10.713 | M97: 11 | N97: 0.108 | O97: 1 | P97: 0.108 | Q97: 3.45 | R97: 3.45 | S97: 1439840 | T97: 1 | U97: 417344.93 | V97: 2.3960996 | X97: 3.45 | Y97: 223.01739
A98: 97 | B98: 97 | C98: CL1-097 | D98: CARLOW | E98: CARLOW | F98: SS-481 | G98: Castledockrell 110kV Substation | H98: EirGrid | I98: 110000 | J98: 20000 | K98: 110000 | L98: 10.637 | M98: 11 | N98: 0.364 | O98: 1 | P98: 0.364 | Q98: 3.45 | R98: 3.45 | S98: 1996170 | T98: 7 | U98: 578600 | V98: 1.7283097 | X98: 3.45 | Y98: 417.34493
A99: 98 | B99: 98 | C99: CL1-098 | D99: CARLOW | E99: WEXFORD | F99: SS-481 | G99: Castledockrell 110kV Substation | H99: EirGrid | I99: 110000 | J99: 20000 | K99: 110000 | L99: 9.874 | M99: 10 | N99: 0.328 | O99: 1 | P99: 0.328 | Q99: 3.45 | R99: 3.45 | S99: 1943470 | T99: 7 | U99: 563324.64 | V99: 1.7751753 | X99: 3.45 | Y99: 578.6
A100: 99 | B100: 99 | C100: CL1-099 | D100: CARLOW | E100: CARLOW | F100: SS-494 | G100: Bunclody 38kV Substation | H100: ESB Networks | I100: 38000 | J100: 38000 | K100: 20000 | L100: 9.975 | M100: 10 | N100: 0.438 | O100: 1 | P100: 0.438 | Q100: 3.45 | R100: 3.45 | S100: 1387140 | T100: 1 | U100: 402069.57 | V100: 2.4871318 | X100: 3.45 | Y100: 563.32464
...

Sheet ELC_CCS
B1: Electricity Generators Database - CCS options
B2: Sources:
B3: Techno-economic data: ETRI 2014 (https://setis.ec.europa.eu/publications/jrc-setis-reports/etri-2014 )
B4: Process options: Irish TIMES v1.0 (using Fionn's analysis)
E6: ~FI_T: MEUR2015 | AO6: ~FI_Process | AX6: ~FI_Comm
B7: TechName | C7: *TechDesc | D7: Comm-IN | E7: Comm-OUT | F7: EFF | G7: EFF~2020 | H7: EFF~2030 | I7: EFF~2040 | J7: EFF~2050 | K7: Start | L7: INVCOST | M7: INVCOST~2020 | N7: INVCOST~2030 | O7: INVCOST~2040 | P7: INVCOST~2050 | Q7: FIXOM | R7: FIXOM~2020 | S7: FIXOM~2030 | T7: FIXOM~2040 | U7: FIXOM~2050 | V7: VAROM | W7: VAROM~2020 | X7: VAROM~2030 | Y7: VAROM~2040 | Z7: VAROM~2050 | AA7: *INVCOST | AB7: *INVCOST | AC7: *VAROM | AD7: *VAROM | AE7: LIFE | AF7: Cap2Act | AG7: AFA | AH7: AFA~2020 | AI7: AFA~2030 | AJ7: AFA~2040 | AK7: AFA~2050 | AO7: Sets | AP7: TechName | AQ7: TechDesc | AR7: Tact | AS7: Tcap | AT7: Tslvl | AU7: PrimaryCG | AV7: Vintage | AX7: Csets | AY7: CommName | AZ7: CommDesc | BA7: Unit | BB7: LimType | BC7: CTSLvl | BD7: PeakTS | BE7: Ctype
B8: *Technology Name | C8: Technology Description | D8: Input Commodity | E8: Output Commodity | F8: Efficiency | L8: Overall CAPEX (€2013/kW) | Q8: FOM (€2013/kW) | V8: Overall VOM (€2013/GJ) | AA8: Pipeline | AB8: Storage | AC8: Pipeline | AD8: Storage | AE8: Technical life | AG8: Max. capacity factor | AO8: \I: Process Set Membership | AP8: Technology Name | AQ8: Technology Description | AR8: Activity Unit | AS8: Capacity Unit | AT8: Timeslice Operational Level | AU8: Operational Commodity Group | AV8: Vintage Tracking | AX8: *Commodity Set Membership | AY8: Commodity Name | AZ8: Commodity Description | BA8: Unit | BB8: Balance Equ Type Override | BC8: Timeslice Tracking Level | BD8: Peak Monitoring | BE8: Electricity Indicator
B9: P-TH-SC-COA-CCS04-MP1 | C9: ="New Power Plant - "&BG9 -> New Power Plant - Pulverised coal supercritical CCS post-combustion_Moneypoint Kinsale | D9: PWRCOA | E9: ="ELCC, "&$AY$9 -> ELCC, PWRCO2S | F9: =IF(ELC_EGP!G$29="","",ELC_EGP!G$29) -> 0.34 | G9: =IF(ELC_EGP!H$29="","",ELC_EGP!H$29) -> 0.35 | H9: =IF(ELC_EGP!I$29="","",ELC_EGP!I$29) -> 0.35 | I9: =IF(ELC_EGP!J$29="","",ELC_EGP!J$29) -> 0.38 | J9: =IF(ELC_EGP!K$29="","",ELC_EGP!K$29) -> 0.38 | K9: =IF(ELC_EGP!L$29="","",ELC_EGP!L$29) -> 2030 | N9: =IF(ELC_EGP!O$29="","",ELC_EGP!O$29)+SUM($AA9:$AB9) -> 3102.3219 | O9: =IF(ELC_EGP!P$29="","",ELC_EGP!P$29)+SUM($AA9:$AB9) -> 2952.3219 | P9: =IF(ELC_EGP!Q$29="","",ELC_EGP!Q$29)+SUM($AA9:$AB9) -> 2932.3219 | Q9: =IF(ELC_EGP!R$29="","",ELC_EGP!R$29) -> 75 | R9: =IF(ELC_EGP!S$29="","",ELC_EGP!S$29) -> 67.5 | S9: =IF(ELC_EGP!T$29="","",ELC_EGP!T$29) -> 63.75 | T9: =IF(ELC_EGP!U$29="","",ELC_EGP!U$29) -> 63.75 | U9: =IF(ELC_EGP!V$29="","",ELC_EGP!V$29) -> 63.75 | V9: =IF(ELC_EGP!W$29="","",ELC_EGP!W$29)+SUM($AC9:$AD9) -> 0.87577648 | W9: =IF(ELC_EGP!X$29="","",ELC_EGP!X$29)+SUM($AC9:$AD9) -> 0.85927648 | X9: =IF(ELC_EGP!Y$29="","",ELC_EGP!Y$29)+SUM($AC9:$AD9) -> 0.85102648 | Y9: =IF(ELC_EGP!Z$29="","",ELC_EGP!Z$29)+SUM($AC9:$AD9) -> 0.85102648 | Z9: =IF(ELC_EGP!AA$29="","",ELC_EGP!AA$29)+SUM($AC9:$AD9) -> 0.85102648 | AA9: =231.039345996009*(131.215852099895/100) -> 303.16025 | AB9: =45.0872552876596*(131.215852099895/100) -> 59.161626 | AC9: =0.45069361273084*(131.215852099895/100) -> 0.59138146 | AD9: =0.0909913043412747*(131.215852099895/100) -> 0.11939502 | AE9: =IF(ELC_EGP!AB$29="","",ELC_EGP!AB$29) -> 40 | AF9: =IF(ELC_EGP!AE$29="","",ELC_EGP!AE$29) -> 31.536 | AG9: =IF(ELC_EGP!AF$29="","",ELC_EGP!AF$29) -> 0.9 | AH9: =IF(ELC_EGP!AG$29="","",ELC_EGP!AG$29) | AI9: =IF(ELC_EGP!AH$29="","",ELC_EGP!AH$29) | AJ9: =IF(ELC_EGP!AI$29="","",ELC_EGP!AI$29) | AK9: =IF(ELC_EGP!AJ$29="","",ELC_EGP!AJ$29) | AO9: ELE | AP9: =B9 -> P-TH-SC-COA-CCS04-MP1 | AQ9: =C9 -> New Power Plant - Pulverised coal supercritical CCS post-combustion_Moneypoint Kinsale | AR9: PJ | AS9: GW | AT9: DAYNITE | AX9: ENV | AY9: PWRCO2S | AZ9: Sequestered CO2 (PWR) | BA9: kt | BG9: Pulverised coal supercritical CCS post-combustion_Moneypoint Kinsale
B10: P-TH-IGCC-COA-CCS06-MP1 | C10: ="New Power Plant - "&BG10 -> New Power Plant - IGCC coal CCS pre-combustion_Moneypoint Kinsale | D10: PWRCOA | E10: ="ELCC, "&$AY$9 -> ELCC, PWRCO2S | F10: =IF(ELC_EGP!G$32="","",ELC_EGP!G$32) -> 0.35 | G10: =IF(ELC_EGP!H$32="","",ELC_EGP!H$32) -> 0.37 | H10: =IF(ELC_EGP!I$32="","",ELC_EGP!I$32) -> 0.4 | I10: =IF(ELC_EGP!J$32="","",ELC_EGP!J$32) -> 0.41 | J10: =IF(ELC_EGP!K$32="","",ELC_EGP!K$32) -> 0.44 | K10: =IF(ELC_EGP!L$32="","",ELC_EGP!L$32) -> 2030 | N10: =IF(ELC_EGP!O$32="","",ELC_EGP!O$32)+SUM($AA10:$AB10) -> 2902.3219 | O10: =IF(ELC_EGP!P$32="","",ELC_EGP!P$32)+SUM($AA10:$AB10) -> 2582.3219 | P10: =IF(ELC_EGP!Q$32="","",ELC_EGP!Q$32)+SUM($AA10:$AB10) -> 2542.3219 | Q10: =IF(ELC_EGP!R$32="","",ELC_EGP!R$32) -> 93 | R10: =IF(ELC_EGP!S$32="","",ELC_EGP!S$32) -> 86.55 | S10: =IF(ELC_EGP!T$32="","",ELC_EGP!T$32) -> 84.75 | T10: =IF(ELC_EGP!U$32="","",ELC_EGP!U$32) -> 84.75 | U10: =IF(ELC_EGP!V$32="","",ELC_EGP!V$32) -> 84.75 | V10: =IF(ELC_EGP!W$32="","",ELC_EGP!W$32)+SUM($AC10:$AD10) -> 0.89677648 | W10: =IF(ELC_EGP!X$32="","",ELC_EGP!X$32)+SUM($AC10:$AD10) -> 0.88387648 | X10: =IF(ELC_EGP!Y$32="","",ELC_EGP!Y$32)+SUM($AC10:$AD10) -> 0.88027648 | Y10: =IF(ELC_EGP!Z$32="","",ELC_EGP!Z$32)+SUM($AC10:$AD10) -> 0.88027648 | Z10: =IF(ELC_EGP!AA$32="","",ELC_EGP!AA$32)+SUM($AC10:$AD10) -> 0.88027648 | AA10: =231.039345996009*(131.215852099895/100) -> 303.16025 | AB10: =45.0872552876596*(131.215852099895/100) -> 59.161626 | AC10: =0.45069361273084*(131.215852099895/100) -> 0.59138146 | AD10: =0.0909913043412747*(131.215852099895/100) -> 0.11939502 | AE10: =IF(ELC_EGP!AB$32="","",ELC_EGP!AB$32) -> 35 | AF10: =IF(ELC_EGP!AE$32="","",ELC_EGP!AE$32) -> 31.536 | AG10: =IF(ELC_EGP!AF$32="","",ELC_EGP!AF$32) -> 0.9 | AH10: =IF(ELC_EGP!AG$32="","",ELC_EGP!AG$32) | AI10: =IF(ELC_EGP!AH$32="","",ELC_EGP!AH$32) | AJ10: =IF(ELC_EGP!AI$32="","",ELC_EGP!AI$32) | AK10: =IF(ELC_EGP!AJ$32="","",ELC_EGP!AJ$32) | AO10: ELE | AP10: =B10 -> P-TH-IGCC-COA-CCS06-MP1 | AQ10: =C10 -> New Power Plant - IGCC coal CCS pre-combustion_Moneypoint Kinsale | AR10: PJ | AS10: GW | AT10: DAYNITE | BG10: IGCC coal CCS pre-combustion_Moneypoint Kinsale
B11: P-TH-SC-COA-CCS04-MP2 | C11: ="New Power Plant - "&BG11 -> New Power Plant - Pulverised coal supercritical CCS post-combustion_Moneypoint Spanish Point | D11: PWRCOA | E11: ="ELCC, "&$AY$9 -> ELCC, PWRCO2S | F11: =IF(ELC_EGP!G$29="","",ELC_EGP!G$29) -> 0.34 | G11: =IF(ELC_EGP!H$29="","",ELC_EGP!H$29) -> 0.35 | H11: =IF(ELC_EGP!I$29="","",ELC_EGP!I$29) -> 0.35 | I11: =IF(ELC_EGP!J$29="","",ELC_EGP!J$29) -> 0.38 | J11: =IF(ELC_EGP!K$29="","",ELC_EGP!K$29) -> 0.38 | K11: =IF(ELC_EGP!L$29="","",ELC_EGP!L$29) -> 2030 | N11: =IF(ELC_EGP!O$29="","",ELC_EGP!O$29)+SUM($AA11:$AB11) -> 3451.1153 | O11: =IF(ELC_EGP!P$29="","",ELC_EGP!P$29)+SUM($AA11:$AB11) -> 3301.1153 | P11: =IF(ELC_EGP!Q$29="","",ELC_EGP!Q$29)+SUM($AA11:$AB11) -> 3281.1153 | Q11: =IF(ELC_EGP!R$29="","",ELC_EGP!R$29) -> 75 | R11: =IF(ELC_EGP!S$29="","",ELC_EGP!S$29) -> 67.5 | S11: =IF(ELC_EGP!T$29="","",ELC_EGP!T$29) -> 63.75 | T11: =IF(ELC_EGP!U$29="","",ELC_EGP!U$29) -> 63.75 | U11: =IF(ELC_EGP!V$29="","",ELC_EGP!V$29) -> 63.75 | V11: =IF(ELC_EGP!W$29="","",ELC_EGP!W$29)+SUM($AC11:$AD11) -> 0.83067111 | W11: =IF(ELC_EGP!X$29="","",ELC_EGP!X$29)+SUM($AC11:$AD11) -> 0.81417111 | X11: =IF(ELC_EGP!Y$29="","",ELC_EGP!Y$29)+SUM($AC11:$AD11) -> 0.80592111 | Y11: =IF(ELC_EGP!Z$29="","",ELC_EGP!Z$29)+SUM($AC11:$AD11) -> 0.80592111 | Z11: =IF(ELC_EGP!AA$29="","",ELC_EGP!AA$29)+SUM($AC11:$AD11) -> 0.80592111 | AA11: =496.855906144888*(131.215852099895/100) -> 651.95371 | AB11: =45.0872552876596*(131.215852099895/100) -> 59.161626 | AC11: =0.416318676166623*(131.215852099895/100) -> 0.5462761 | AD11: =0.0909913043412747*(131.215852099895/100) -> 0.11939502 | AE11: =IF(ELC_EGP!AB$29="","",ELC_EGP!AB$29) -> 40 | AF11: =IF(ELC_EGP!AE$29="","",ELC_EGP!AE$29) -> 31.536 | AG11: =IF(ELC_EGP!AF$29="","",ELC_EGP!AF$29) -> 0.9 | AH11: =IF(ELC_EGP!AG$29="","",ELC_EGP!AG$29) | AI11: =IF(ELC_EGP!AH$29="","",ELC_EGP!AH$29) | AJ11: =IF(ELC_EGP!AI$29="","",ELC_EGP!AI$29) | AK11: =IF(ELC_EGP!AJ$29="","",ELC_EGP!AJ$29) | AO11: ELE | AP11: =B11 -> P-TH-SC-COA-CCS04-MP2 | AQ11: =C11 -> New Power Plant - Pulverised coal supercritical CCS post-combustion_Moneypoint Spanish Point | AR11: PJ | AS11: GW | AT11: DAYNITE | BG11: Pulverised coal supercritical CCS post-combustion_Moneypoint Spanish Point
B12: P-TH-IGCC-COA-CCS06-MP2 | C12: ="New Power Plant - "&BG12 -> New Power Plant - IGCC coal CCS pre-combustion_Moneypoint Spanish Point | D12: PWRCOA | E12: ="ELCC, "&$AY$9 -> ELCC, PWRCO2S | F12: =IF(ELC_EGP!G$32="","",ELC_EGP!G$32) -> 0.35 | G12: =IF(ELC_EGP!H$32="","",ELC_EGP!H$32) -> 0.37 | H12: =IF(ELC_EGP!I$32="","",ELC_EGP!I$32) -> 0.4 | I12: =IF(ELC_EGP!J$32="","",ELC_EGP!J$32) -> 0.41 | J12: =IF(ELC_EGP!K$32="","",ELC_EGP!K$32) -> 0.44 | K12: =IF(ELC_EGP!L$32="","",ELC_EGP!L$32) -> 2030 | N12: =IF(ELC_EGP!O$32="","",ELC_EGP!O$32)+SUM($AA12:$AB12) -> 3310.277 | O12: =IF(ELC_EGP!P$32="","",ELC_EGP!P$32)+SUM($AA12:$AB12) -> 2990.277 | P12: =IF(ELC_EGP!Q$32="","",ELC_EGP!Q$32)+SUM($AA12:$AB12) -> 2950.277 | Q12: =IF(ELC_EGP!R$32="","",ELC_EGP!R$32) -> 93 | R12: =IF(ELC_EGP!S$32="","",ELC_EGP!S$32) -> 86.55 | S12: =IF(ELC_EGP!T$32="","",ELC_EGP!T$32) -> 84.75 | T12: =IF(ELC_EGP!U$32="","",ELC_EGP!U$32) -> 84.75 | U12: =IF(ELC_EGP!V$32="","",ELC_EGP!V$32) -> 84.75 | V12: =IF(ELC_EGP!W$32="","",ELC_EGP!W$32)+SUM($AC12:$AD12) -> 0.85167111 | W12: =IF(ELC_EGP!X$32="","",ELC_EGP!X$32)+SUM($AC12:$AD12) -> 0.83877111 | X12: =IF(ELC_EGP!Y$32="","",ELC_EGP!Y$32)+SUM($AC12:$AD12) -> 0.83517111 | Y12: =IF(ELC_EGP!Z$32="","",ELC_EGP!Z$32)+SUM($AC12:$AD12) -> 0.83517111 | Z12: =IF(ELC_EGP!AA$32="","",ELC_EGP!AA$32)+SUM($AC12:$AD12) -> 0.83517111 | AA12: =496.855906144888*(131.215852099895/100) -> 651.95371 | AB12: =90.1745105753192*(131.215852099895/100) -> 118.32325 | AC12: =0.416318676166623*(131.215852099895/100) -> 0.5462761 | AD12: =0.0909913043412747*(131.215852099895/100) -> 0.11939502 | AE12: =IF(ELC_EGP!AB$32="","",ELC_EGP!AB$32) -> 35 | AF12: =IF(ELC_EGP!AE$32="","",ELC_EGP!AE$32) -> 31.536 | AG12: =IF(ELC_EGP!AF$32="","",ELC_EGP!AF$32) -> 0.9 | AH12: =IF(ELC_EGP!AG$32="","",ELC_EGP!AG$32) | AI12: =IF(ELC_EGP!AH$32="","",ELC_EGP!AH$32) | AJ12: =IF(ELC_EGP!AI$32="","",ELC_EGP!AI$32) | AK12: =IF(ELC_EGP!AJ$32="","",ELC_EGP!AJ$32) | AO12: ELE | AP12: =B12 -> P-TH-IGCC-COA-CCS06-MP2 | AQ12: =C12 -> New Power Plant - IGCC coal CCS pre-combustion_Moneypoint Spanish Point | AR12: PJ | AS12: GW | AT12: DAYNITE | BG12: IGCC coal CCS pre-combustion_Moneypoint Spanish Point
B13: P-TH-CCGT-GAS-CCS04-Cork1 | C13: ="New Power Plant - "&BG13 -> New Power Plant - CCGT advanced CCS post combustion_Cork Kinsale | D13: PWRGAS | E13: ="ELCC, "&$AY$9 -> ELCC, PWRCO2S | F13: =IF(ELC_EGP!G$28="","",ELC_EGP!G$28) -> 0.5 | G13: =IF(ELC_EGP!H$28="","",ELC_EGP!H$28) -> 0.52 | H13: =IF(ELC_EGP!I$28="","",ELC_EGP!I$28) -> 0.55 | I13: =IF(ELC_EGP!J$28="","",ELC_EGP!J$28) -> 0.55 | J13: =IF(ELC_EGP!K$28="","",ELC_EGP!K$28) -> 0.55 | K13: =IF(ELC_EGP!L$28="","",ELC_EGP!L$28) -> 2030 | N13: =IF(ELC_EGP!O$28="","",ELC_EGP!O$28)+SUM($AA13:$AB13) -> 1491.5259 | O13: =IF(ELC_EGP!P$28="","",ELC_EGP!P$28)+SUM($AA13:$AB13) -> 1411.5259 | P13: =IF(ELC_EGP!Q$28="","",ELC_EGP!Q$28)+SUM($AA13:$AB13) -> 1381.5259 | Q13: =IF(ELC_EGP!R$28="","",ELC_EGP!R$28) -> 37.5 | R13: =IF(ELC_EGP!S$28="","",ELC_EGP!S$28) -> 37.5 | S13: =IF(ELC_EGP!T$28="","",ELC_EGP!T$28) -> 37.5 | T13: =IF(ELC_EGP!U$28="","",ELC_EGP!U$28) -> 37.5 | U13: =IF(ELC_EGP!V$28="","",ELC_EGP!V$28) -> 37.5 | V13: =IF(ELC_EGP!W$28="","",ELC_EGP!W$28)+SUM($AC13:$AD13) -> 0.24714746 | W13: =IF(ELC_EGP!X$28="","",ELC_EGP!X$28)+SUM($AC13:$AD13) -> 0.24714746 | X13: =IF(ELC_EGP!Y$28="","",ELC_EGP!Y$28)+SUM($AC13:$AD13) -> 0.24714746 | Y13: =IF(ELC_EGP!Z$28="","",ELC_EGP!Z$28)+SUM($AC13:$AD13) -> 0.24714746 | Z13: =IF(ELC_EGP!AA$28="","",ELC_EGP!AA$28)+SUM($AC13:$AD13) -> 0.24714746 | AA13: =51.846136548894*(131.215852099895/100) -> 68.03035 | AB13: =25.5270389168779*(131.215852099895/100) -> 33.495522 | AC13: =0.0932556484566934*(131.215852099895/100) -> 0.12236619 | AD13: =0.0493699999964453*(131.215852099895/100) -> 0.064781266 | AE13: =IF(ELC_EGP!AB$28="","",ELC_EGP!AB$28) -> 30 | AF13: =IF(ELC_EGP!AE$28="","",ELC_EGP!AE$28) -> 31.536 | AG13: =IF(ELC_EGP!AF$28="","",ELC_EGP!AF$28) -> 0.9 | AH13: =IF(ELC_EGP!AG$28="","",ELC_EGP!AG$28) | AI13: =IF(ELC_EGP!AH$28="","",ELC_EGP!AH$28) | AJ13: =IF(ELC_EGP!AI$28="","",ELC_EGP!AI$28) | AK13: =IF(ELC_EGP!AJ$28="","",ELC_EGP!AJ$28) | AO13: ELE | AP13: =B13 -> P-TH-CCGT-GAS-CCS04-Cork1 | AQ13: =C13 -> New Power Plant - CCGT advanced CCS post combustion_Cork Kinsale | AR13: PJ | AS13: GW | AT13: DAYNITE | BG13: CCGT advanced CCS post combustion_Cork Kinsale
B14: P-TH-CCGT-GAS-CCS04-Cork2 | C14: ="New Power Plant - "&BG14 -> New Power Plant - CCGT advanced CCS post combustion_Cork Spanish Point | D14: PWRGAS | E14: ="ELCC, "&$AY$9 -> ELCC, PWRCO2S | F14: =IF(ELC_EGP!G$28="","",ELC_EGP!G$28) -> 0.5 | G14: =IF(ELC_EGP!H$28="","",ELC_EGP!H$28) -> 0.52 | H14: =IF(ELC_EGP!I$28="","",ELC_EGP!I$28) -> 0.55 | I14: =IF(ELC_EGP!J$28="","",ELC_EGP!J$28) -> 0.55 | J14: =IF(ELC_EGP!K$28="","",ELC_EGP!K$28) -> 0.55 | K14: =IF(ELC_EGP!L$28="","",ELC_EGP!L$28) -> 2030 | N14: =IF(ELC_EGP!O$28="","",ELC_EGP!O$28)+SUM($AA14:$AB14) -> 2499.5522 | O14: =IF(ELC_EGP!P$28="","",ELC_EGP!P$28)+SUM($AA14:$AB14) -> 2419.5522 | P14: =IF(ELC_EGP!Q$28="","",ELC_EGP!Q$28)+SUM($AA14:$AB14) -> 2389.5522 | Q14: =IF(ELC_EGP!R$28="","",ELC_EGP!R$28) -> 37.5 | R14: =IF(ELC_EGP!S$28="","",ELC_EGP!S$28) -> 37.5 | S14: =IF(ELC_EGP!T$28="","",ELC_EGP!T$28) -> 37.5 | T14: =IF(ELC_EGP!U$28="","",ELC_EGP!U$28) -> 37.5 | U14: =IF(ELC_EGP!V$28="","",ELC_EGP!V$28) -> 37.5 | V14: =IF(ELC_EGP!W$28="","",ELC_EGP!W$28)+SUM($AC14:$AD14) -> 0.76539312 | W14: =IF(ELC_EGP!X$28="","",ELC_EGP!X$28)+SUM($AC14:$AD14) -> 0.76539312 | X14: =IF(ELC_EGP!Y$28="","",ELC_EGP!Y$28)+SUM($AC14:$AD14) -> 0.76539312 | Y14: =IF(ELC_EGP!Z$28="","",ELC_EGP!Z$28)+SUM($AC14:$AD14) -> 0.76539312 | Z14: =IF(ELC_EGP!AA$28="","",ELC_EGP!AA$28)+SUM($AC14:$AD14) -> 0.76539312 | AA14: =794.539013969699*(131.215852099895/100) -> 1042.5611 | AB14: =51.0540778337558*(131.215852099895/100) -> 66.991043 | AC14: =0.446590938720387*(131.215852099895/100) -> 0.58599811 | AD14: =0.0909913043412747*(131.215852099895/100) -> 0.11939502 | AE14: =IF(ELC_EGP!AB$28="","",ELC_EGP!AB$28) -> 30 | AF14: =IF(ELC_EGP!AE$28="","",ELC_EGP!AE$28) -> 31.536 | AG14: =IF(ELC_EGP!AF$28="","",ELC_EGP!AF$28) -> 0.9 | AH14: =IF(ELC_EGP!AG$28="","",ELC_EGP!AG$28) | AI14: =IF(ELC_EGP!AH$28="","",ELC_EGP!AH$28) | AJ14: =IF(ELC_EGP!AI$28="","",ELC_EGP!AI$28) | AK14: =IF(ELC_EGP!AJ$28="","",ELC_EGP!AJ$28) | AO14: ELE | AP14: =B14 -> P-TH-CCGT-GAS-CCS04-Cork2 | AQ14: =C14 -> New Power Plant - CCGT advanced CCS post combustion_Cork Spanish Point | AR14: PJ | AS14: GW | AT14: DAYNITE | BG14: CCGT advanced CCS post combustion_Cork Spanish Point
B15: P-TH-IGCC-PEA-CCS05-Offaly1 | C15: ="New Power Plant - "&BG15 -> New Power Plant - IGCC peat CCS pre combustion_Offaly Kinsale | D15: PWRPEA | E15: ="ELCC, "&$AY$9 -> ELCC, PWRCO2S | F15: =IF(ELC_EGP!G$32="","",ELC_EGP!G$32) -> 0.35 | G15: =IF(ELC_EGP!H$32="","",ELC_EGP!H$32) -> 0.37 | H15: =IF(ELC_EGP!I$32="","",ELC_EGP!I$32) -> 0.4 | I15: =IF(ELC_EGP!J$32="","",ELC_EGP!J$32) -> 0.41 | J15: =IF(ELC_EGP!K$32="","",ELC_EGP!K$32) -> 0.44 | K15: =IF(ELC_EGP!L$32="","",ELC_EGP!L$32) -> 2030 | L15: =IF(ELC_EGP!M$35="","",ELC_EGP!M$35)+SUM($AA15:$AB15) -> 3473.817 | M15: =IF(ELC_EGP!N$35="","",ELC_EGP!N$35)+SUM($AA15:$AB15) -> 3133.817 | N15: =IF(ELC_EGP!O$35="","",ELC_EGP!O$35)+SUM($AA15:$AB15) -> 2843.817 | O15: =IF(ELC_EGP!P$35="","",ELC_EGP!P$35)+SUM($AA15:$AB15) -> 2573.817 | P15: =IF(ELC_EGP!Q$35="","",ELC_EGP!Q$35)+SUM($AA15:$AB15) -> 2343.817 | Q15: =IF(ELC_EGP!R$32="","",ELC_EGP!R$32) -> 93 | R15: =IF(ELC_EGP!S$32="","",ELC_EGP!S$32) -> 86.55 | S15: =IF(ELC_EGP!T$32="","",ELC_EGP!T$32) -> 84.75 | T15: =IF(ELC_EGP!U$32="","",ELC_EGP!U$32) -> 84.75 | U15: =IF(ELC_EGP!V$32="","",ELC_EGP!V$32) -> 84.75 | V15: =IF(ELC_EGP!W$35="","",ELC_EGP!W$35)+SUM($AC15:$AD15) -> 0.96521309 | W15: =IF(ELC_EGP!X$35="","",ELC_EGP!X$35)+SUM($AC15:$AD15) -> 0.95229309 | X15: =IF(ELC_EGP!Y$35="","",ELC_EGP!Y$35)+SUM($AC15:$AD15) -> 0.94127309 | Y15: =IF(ELC_EGP!Z$35="","",ELC_EGP!Z$35)+SUM($AC15:$AD15) -> 0.93101309 | Z15: =IF(ELC_EGP!AA$35="","",ELC_EGP!AA$35)+SUM($AC15:$AD15) -> 0.92227309 | AA15: =301.406974763073*(131.215852099895/100) -> 395.49373 | AB15: =90.1745105753192*(131.215852099895/100) -> 118.32325 | AC15: =0.558879176973221*(131.215852099895/100) -> 0.73333807 | AD15: =0.0909913043412747*(131.215852099895/100) -> 0.11939502 | AE15: =IF(ELC_EGP!AB$32="","",ELC_EGP!AB$32) -> 35 | AF15: =IF(ELC_EGP!AE$32="","",ELC_EGP!AE$32) -> 31.536 | AG15: =IF(ELC_EGP!AF$32="","",ELC_EGP!AF$32) -> 0.9 | AH15: =IF(ELC_EGP!AG$32="","",ELC_EGP!AG$32) | AI15: =IF(ELC_EGP!AH$32="","",ELC_EGP!AH$32) | AJ15: =IF(ELC_EGP!AI$32="","",ELC_EGP!AI$32) | AK15: =IF(ELC_EGP!AJ$32="","",ELC_EGP!AJ$32) | AO15: ELE | AP15: =B15 -> P-TH-IGCC-PEA-CCS05-Offaly1 | AQ15: =C15 -> New Power Plant - IGCC peat CCS pre combustion_Offaly Kinsale | AR15: PJ | AS15: GW | AT15: DAYNITE | BG15: IGCC peat CCS pre combustion_Offaly Kinsale
B16: P-TH-IGCC-PEA-CCS05-Offaly2 | C16: ="New Power Plant - "&BG16 -> New Power Plant - IGCC peat CCS pre combustion_Offaly East Irish Sea | D16: PWRPEA | E16: ="ELCC, "&$AY$9 -> ELCC, PWRCO2S | F16: =IF(ELC_EGP!G$32="","",ELC_EGP!G$32) -> 0.35 | G16: =IF(ELC_EGP!H$32="","",ELC_EGP!H$32) -> 0.37 | H16: =IF(ELC_EGP!I$32="","",ELC_EGP!I$32) -> 0.4 | I16: =IF(ELC_EGP!J$32="","",ELC_EGP!J$32) -> 0.41 | J16: =IF(ELC_EGP!K$32="","",ELC_EGP!K$32) -> 0.44 | K16: =IF(ELC_EGP!L$32="","",ELC_EGP!L$32) -> 2030 | L16: =IF(ELC_EGP!M$35="","",ELC_EGP!M$35)+SUM($AA16:$AB16) -> 3625.7907 | M16: =IF(ELC_EGP!N$35="","",ELC_EGP!N$35)+SUM($AA16:$AB16) -> 3285.7907 | N16: =IF(ELC_EGP!O$35="","",ELC_EGP!O$35)+SUM($AA16:$AB16) -> 2995.7907 | O16: =IF(ELC_EGP!P$35="","",ELC_EGP!P$35)+SUM($AA16:$AB16) -> 2725.7907 | P16: =IF(ELC_EGP!Q$35="","",ELC_EGP!Q$35)+SUM($AA16:$AB16) -> 2495.7907 | Q16: =IF(ELC_EGP!R$32="","",ELC_EGP!R$32) -> 93 | R16: =IF(ELC_EGP!S$32="","",ELC_EGP!S$32) -> 86.55 | S16: =IF(ELC_EGP!T$32="","",ELC_EGP!T$32) -> 84.75 | T16: =IF(ELC_EGP!U$32="","",ELC_EGP!U$32) -> 84.75 | U16: =IF(ELC_EGP!V$32="","",ELC_EGP!V$32) -> 84.75 | V16: =IF(ELC_EGP!W$35="","",ELC_EGP!W$35)+SUM($AC16:$AD16) -> 0.86936419 | W16: =IF(ELC_EGP!X$35="","",ELC_EGP!X$35)+SUM($AC16:$AD16) -> 0.85644419 | X16: =IF(ELC_EGP!Y$35="","",ELC_EGP!Y$35)+SUM($AC16:$AD16) -> 0.84542419 | Y16: =IF(ELC_EGP!Z$35="","",ELC_EGP!Z$35)+SUM($AC16:$AD16) -> 0.83516419 | Z16: =IF(ELC_EGP!AA$35="","",ELC_EGP!AA$35)+SUM($AC16:$AD16) -> 0.82642419 | AA16: =417.22661515867*(131.215852099895/100) -> 547.46746 | AB16: =90.1745105753192*(131.215852099895/100) -> 118.32325 | AC16: =0.485832436774261*(131.215852099895/100) -> 0.63748917 | AD16: =0.0909913043412747*(131.215852099895/100) -> 0.11939502 | AE16: =IF(ELC_EGP!AB$32="","",ELC_EGP!AB$32) -> 35 | AF16: =IF(ELC_EGP!AE$32="","",ELC_EGP!AE$32) -> 31.536 | AG16: =IF(ELC_EGP!AF$32="","",ELC_EGP!AF$32) -> 0.9 | AH16: =IF(ELC_EGP!AG$32="","",ELC_EGP!AG$32) | AI16: =IF(ELC_EGP!AH$32="","",ELC_EGP!AH$32) | AJ16: =IF(ELC_EGP!AI$32="","",ELC_EGP!AI$32) | AK16: =IF(ELC_EGP!AJ$32="","",ELC_EGP!AJ$32) | AO16: ELE | AP16: =B16 -> P-TH-IGCC-PEA-CCS05-Offaly2 | AQ16: =C16 -> New Power Plant - IGCC peat CCS pre combustion_Offaly East Irish Sea | AR16: PJ | AS16: GW | AT16: DAYNITE | BG16: IGCC peat CCS pre combustion_Offaly East Irish Sea
B17: P-TH-IGCC-PEA-CCS05-Offaly3 | C17: ="New Power Plant - "&BG17 -> New Power Plant - IGCC peat CCS pre combustion_Offaly Central Irish Sea | D17: PWRPEA | E17: ="ELCC, "&$AY$9 -> ELCC, PWRCO2S | F17: =IF(ELC_EGP!G$32="","",ELC_EGP!G$32) -> 0.35 | G17: =IF(ELC_EGP!H$32="","",ELC_EGP!H$32) -> 0.37 | H17: =IF(ELC_EGP!I$32="","",ELC_EGP!I$32) -> 0.4 | I17: =IF(ELC_EGP!J$32="","",ELC_EGP!J$32) -> 0.41 | J17: =IF(ELC_EGP!K$32="","",ELC_EGP!K$32) -> 0.44 | K17: =IF(ELC_EGP!L$32="","",ELC_EGP!L$32) -> 2030 | L17: =IF(ELC_EGP!M$35="","",ELC_EGP!M$35)+SUM($AA17:$AB17) -> 3532.6197 | M17: =IF(ELC_EGP!N$35="","",ELC_EGP!N$35)+SUM($AA17:$AB17) -> 3192.6197 | N17: =IF(ELC_EGP!O$35="","",ELC_EGP!O$35)+SUM($AA17:$AB17) -> 2902.6197 | O17: =IF(ELC_EGP!P$35="","",ELC_EGP!P$35)+SUM($AA17:$AB17) -> 2632.6197 | P17: =IF(ELC_EGP!Q$35="","",ELC_EGP!Q$35)+SUM($AA17:$AB17) -> 2402.6197 | Q17: =IF(ELC_EGP!R$32="","",ELC_EGP!R$32) -> 93 | R17: =IF(ELC_EGP!S$32="","",ELC_EGP!S$32) -> 86.55 | S17: =IF(ELC_EGP!T$32="","",ELC_EGP!T$32) -> 84.75 | T17: =IF(ELC_EGP!U$32="","",ELC_EGP!U$32) -> 84.75 | U17: =IF(ELC_EGP!V$32="","",ELC_EGP!V$32) -> 84.75 | V17: =IF(ELC_EGP!W$35="","",ELC_EGP!W$35)+SUM($AC17:$AD17) -> 0.79418858 | W17: =IF(ELC_EGP!X$35="","",ELC_EGP!X$35)+SUM($AC17:$AD17) -> 0.78126858 | X17: =IF(ELC_EGP!Y$35="","",ELC_EGP!Y$35)+SUM($AC17:$AD17) -> 0.77024858 | Y17: =IF(ELC_EGP!Z$35="","",ELC_EGP!Z$35)+SUM($AC17:$AD17) -> 0.75998858 | Z17: =IF(ELC_EGP!AA$35="","",ELC_EGP!AA$35)+SUM($AC17:$AD17) -> 0.75124858 | AA17: =346.220733549765*(131.215852099895/100) -> 454.29649 | AB17: =90.1745105753192*(131.215852099895/100) -> 118.32325 | AC17: =0.4285408758339*(131.215852099895/100) -> 0.56231356 | AD17: =0.0909913043412747*(131.215852099895/100) -> 0.11939502 | AE17: =IF(ELC_EGP!AB$32="","",ELC_EGP!AB$32) -> 35 | AF17: =IF(ELC_EGP!AE$32="","",ELC_EGP!AE$32) -> 31.536 | AG17: =IF(ELC_EGP!AF$32="","",ELC_EGP!AF$32) -> 0.9 | AH17: =IF(ELC_EGP!AG$32="","",ELC_EGP!AG$32) | AI17: =IF(ELC_EGP!AH$32="","",ELC_EGP!AH$32) | AJ17: =IF(ELC_EGP!AI$32="","",ELC_EGP!AI$32) | AK17: =IF(ELC_EGP!AJ$32="","",ELC_EGP!AJ$32) | AO17: ELE | AP17: =B17 -> P-TH-IGCC-PEA-CCS05-Offaly3 | AQ17: =C17 -> New Power Plant - IGCC peat CCS pre combustion_Offaly Central Irish Sea | AR17: PJ | AS17: GW | AT17: DAYNITE | BG17: IGCC peat CCS pre combustion_Offaly Central Irish Sea
B18: P-TH-CCGT-GAS-CCS04-Dublin1 | C18: ="New Power Plant - "&BG18 -> New Power Plant - CCGT advanced CCS post combustion_Dublin East Irish Sea | D18: PWRGAS | E18: ="ELCC, "&$AY$9 -> ELCC, PWRCO2S | F18: =IF(ELC_EGP!G$28="","",ELC_EGP!G$28) -> 0.5 | G18: =IF(ELC_EGP!H$28="","",ELC_EGP!H$28) -> 0.52 | H18: =IF(ELC_EGP!I$28="","",ELC_EGP!I$28) -> 0.55 | I18: =IF(ELC_EGP!J$28="","",ELC_EGP!J$28) -> 0.55 | J18: =IF(ELC_EGP!K$28="","",ELC_EGP!K$28) -> 0.55 | K18: =IF(ELC_EGP!L$28="","",ELC_EGP!L$28) -> 2030 | N18: =IF(ELC_EGP!O$28="","",ELC_EGP!O$28)+SUM($AA18:$AB18) -> 1748.6567 | O18: =IF(ELC_EGP!P$28="","",ELC_EGP!P$28)+SUM($AA18:$AB18) -> 1668.6567 | P18: =IF(ELC_EGP!Q$28="","",ELC_EGP!Q$28)+SUM($AA18:$AB18) -> 1638.6567 | Q18: =IF(ELC_EGP!R$28="","",ELC_EGP!R$28) -> 37.5 | R18: =IF(ELC_EGP!S$28="","",ELC_EGP!S$28) -> 37.5 | S18: =IF(ELC_EGP!T$28="","",ELC_EGP!T$28) -> 37.5 | T18: =IF(ELC_EGP!U$28="","",ELC_EGP!U$28) -> 37.5 | U18: =IF(ELC_EGP!V$28="","",ELC_EGP!V$28) -> 37.5 | V18: =IF(ELC_EGP!W$28="","",ELC_EGP!W$28)+SUM($AC18:$AD18) -> 0.24714746 | W18: =IF(ELC_EGP!X$28="","",ELC_EGP!X$28)+SUM($AC18:$AD18) -> 0.24714746 | X18: =IF(ELC_EGP!Y$28="","",ELC_EGP!Y$28)+SUM($AC18:$AD18) -> 0.24714746 | Y18: =IF(ELC_EGP!Z$28="","",ELC_EGP!Z$28)+SUM($AC18:$AD18) -> 0.24714746 | Z18: =IF(ELC_EGP!AA$28="","",ELC_EGP!AA$28)+SUM($AC18:$AD18) -> 0.24714746 | AA18: =222.27928155831*(131.215852099895/100) -> 291.66565 | AB18: =51.0540778337558*(131.215852099895/100) -> 66.991043 | AC18: =0.0932556484566934*(131.215852099895/100) -> 0.12236619 | AD18: =0.0493699999964453*(131.215852099895/100) -> 0.064781266 | AE18: =IF(ELC_EGP!AB$28="","",ELC_EGP!AB$28) -> 30 | AF18: =IF(ELC_EGP!AE$28="","",ELC_EGP!AE$28) -> 31.536 | AG18: =IF(ELC_EGP!AF$28="","",ELC_EGP!AF$28) -> 0.9 | AH18: =IF(ELC_EGP!AG$28="","",ELC_EGP!AG$28) | AI18: =IF(ELC_EGP!AH$28="","",ELC_EGP!AH$28) | AJ18: =IF(ELC_EGP!AI$28="","",ELC_EGP!AI$28) | AK18: =IF(ELC_EGP!AJ$28="","",ELC_EGP!AJ$28) | AO18: ELE | AP18: =B18 -> P-TH-CCGT-GAS-CCS04-Dublin1 | AQ18: =C18 -> New Power Plant - CCGT advanced CCS post combustion_Dublin East Irish Sea | AR18: PJ | AS18: GW | AT18: DAYNITE | BG18: CCGT advanced CCS post combustion_Dublin East Irish Sea
B19: P-TH-CCGT-GAS-CCS04-Dublin2 | C19: ="New Power Plant - "&BG19 -> New Power Plant - CCGT advanced CCS post combustion_Dublin Central Irish Sea | D19: PWRGAS | E19: ="ELCC, "&$AY$9 -> ELCC, PWRCO2S | F19: =IF(ELC_EGP!G$28="","",ELC_EGP!G$28) -> 0.5 | G19: =IF(ELC_EGP!H$28="","",ELC_EGP!H$28) -> 0.52 | H19: =IF(ELC_EGP!I$28="","",ELC_EGP!I$28) -> 0.55 | I19: =IF(ELC_EGP!J$28="","",ELC_EGP!J$28) -> 0.55 | J19: =IF(ELC_EGP!K$28="","",ELC_EGP!K$28) -> 0.55 | K19: =IF(ELC_EGP!L$28="","",ELC_EGP!L$28) -> 2030 | N19: =IF(ELC_EGP!O$28="","",ELC_EGP!O$28)+SUM($AA19:$AB19) -> 1651.4348 | O19: =IF(ELC_EGP!P$28="","",ELC_EGP!P$28)+SUM($AA19:$AB19) -> 1571.4348 | P19: =IF(ELC_EGP!Q$28="","",ELC_EGP!Q$28)+SUM($AA19:$AB19) -> 1541.4348 | Q19: =IF(ELC_EGP!R$28="","",ELC_EGP!R$28) -> 37.5 | R19: =IF(ELC_EGP!S$28="","",ELC_EGP!S$28) -> 37.5 | S19: =IF(ELC_EGP!T$28="","",ELC_EGP!T$28) -> 37.5 | T19: =IF(ELC_EGP!U$28="","",ELC_EGP!U$28) -> 37.5 | U19: =IF(ELC_EGP!V$28="","",ELC_EGP!V$28) -> 37.5 | V19: =IF(ELC_EGP!W$28="","",ELC_EGP!W$28)+SUM($AC19:$AD19) -> 0.20635873 | W19: =IF(ELC_EGP!X$28="","",ELC_EGP!X$28)+SUM($AC19:$AD19) -> 0.20635873 | X19: =IF(ELC_EGP!Y$28="","",ELC_EGP!Y$28)+SUM($AC19:$AD19) -> 0.20635873 | Y19: =IF(ELC_EGP!Z$28="","",ELC_EGP!Z$28)+SUM($AC19:$AD19) -> 0.20635873 | Z19: =IF(ELC_EGP!AA$28="","",ELC_EGP!AA$28)+SUM($AC19:$AD19) -> 0.20635873 | AA19: =148.18618770554*(131.215852099895/100) -> 194.44377 | AB19: =51.0540778337558*(131.215852099895/100) -> 66.991043 | AC19: =0.0621704323044623*(131.215852099895/100) -> 0.081577463 | AD19: =0.0493699999964453*(131.215852099895/100) -> 0.064781266 | AE19: =IF(ELC_EGP!AB$28="","",ELC_EGP!AB$28) -> 30 | AF19: =IF(ELC_EGP!AE$28="","",ELC_EGP!AE$28) -> 31.536 | AG19: =IF(ELC_EGP!AF$28="","",ELC_EGP!AF$28) -> 0.9 | AH19: =IF(ELC_EGP!AG$28="","",ELC_EGP!AG$28) | AI19: =IF(ELC_EGP!AH$28="","",ELC_EGP!AH$28) | AJ19: =IF(ELC_EGP!AI$28="","",ELC_EGP!AI$28) | AK19: =IF(ELC_EGP!AJ$28="","",ELC_EGP!AJ$28) | AO19: ELE | AP19: =B19 -> P-TH-CCGT-GAS-CCS04-Dublin2 | AQ19: =C19 -> New Power Plant - CCGT advanced CCS post combustion_Dublin Central Irish Sea | AR19: PJ | AS19: GW | AT19: DAYNITE | BG19: CCGT advanced CCS post combustion_Dublin Central Irish Sea
B20: P-TH-SC-COA-CCS04-Kilroot1 | C20: ="New Power Plant - "&BG20 -> New Power Plant - Pulverised coal supercritical CCS post-combustion_Kilroot Portpatrick | D20: PWRCOA | E20: ="ELCC, "&$AY$9 -> ELCC, PWRCO2S | F20: =IF(ELC_EGP!G$29="","",ELC_EGP!G$29) -> 0.34 | G20: =IF(ELC_EGP!H$29="","",ELC_EGP!H$29) -> 0.35 | H20: =IF(ELC_EGP!I$29="","",ELC_EGP!I$29) -> 0.35 | I20: =IF(ELC_EGP!J$29="","",ELC_EGP!J$29) -> 0.38 | J20: =IF(ELC_EGP!K$29="","",ELC_EGP!K$29) -> 0.38 | K20: =IF(ELC_EGP!L$29="","",ELC_EGP!L$29) -> 2030 | N20: =IF(ELC_EGP!O$29="","",ELC_EGP!O$29)+SUM($AA20:$AB20) -> 2982.5512 | O20: =IF(ELC_EGP!P$29="","",ELC_EGP!P$29)+SUM($AA20:$AB20) -> 2832.5512 | P20: =IF(ELC_EGP!Q$29="","",ELC_EGP!Q$29)+SUM($AA20:$AB20) -> 2812.5512 | Q20: =IF(ELC_EGP!R$29="","",ELC_EGP!R$29) -> 75 | R20: =IF(ELC_EGP!S$29="","",ELC_EGP!S$29) -> 67.5 | S20: =IF(ELC_EGP!T$29="","",ELC_EGP!T$29) -> 63.75 | T20: =IF(ELC_EGP!U$29="","",ELC_EGP!U$29) -> 63.75 | U20: =IF(ELC_EGP!V$29="","",ELC_EGP!V$29) -> 63.75 | V20: =IF(ELC_EGP!W$29="","",ELC_EGP!W$29)+SUM($AC20:$AD20) -> 0.38462916 | W20: =IF(ELC_EGP!X$29="","",ELC_EGP!X$29)+SUM($AC20:$AD20) -> 0.36812916 | X20: =IF(ELC_EGP!Y$29="","",ELC_EGP!Y$29)+SUM($AC20:$AD20) -> 0.35987916 | Y20: =IF(ELC_EGP!Z$29="","",ELC_EGP!Z$29)+SUM($AC20:$AD20) -> 0.35987916 | Z20: =IF(ELC_EGP!AA$29="","",ELC_EGP!AA$29)+SUM($AC20:$AD20) -> 0.35987916 | AA20: =94.6745088118728*(131.215852099895/100) -> 124.22796 | AB20: =90.1745105753192*(131.215852099895/100) -> 118.32325 | AC20: =0.0763887479204813*(131.215852099895/100) -> 0.10023415 | AD20: =0.0909913043412747*(131.215852099895/100) -> 0.11939502 | AE20: =IF(ELC_EGP!AB$29="","",ELC_EGP!AB$29) -> 40 | AF20: =IF(ELC_EGP!AE$29="","",ELC_EGP!AE$29) -> 31.536 | AG20: =IF(ELC_EGP!AF$29="","",ELC_EGP!AF$29) -> 0.9 | AH20: =IF(ELC_EGP!AG$29="","",ELC_EGP!AG$29) | AI20: =IF(ELC_EGP!AH$29="","",ELC_EGP!AH$29) | AJ20: =IF(ELC_EGP!AI$29="","",ELC_EGP!AI$29) | AK20: =IF(ELC_EGP!AJ$29="","",ELC_EGP!AJ$29) | AO20: ELE | AP20: =B20 -> P-TH-SC-COA-CCS04-Kilroot1 | AQ20: =C20 -> New Power Plant - Pulverised coal supercritical CCS post-combustion_Kilroot Portpatrick | AR20: PJ | AS20: GW | AT20: DAYNITE | BG20: Pulverised coal supercritical CCS post-combustion_Kilroot Portpatrick
E24: ~FI_T | AA24: =131.215852099895/100 -> 1.3121585 | AB24: -> | AC24: 2000-2012 CPI
B25: TechName | C25: Comm-IN | D25: Comm-Out | E25: Year | F25: START | G25: Life | H25: AF | I25: CAP2ACT | J25: NCAP_DRATE | K25: EFF | L25: INVCOST | M25: FIXOM | N25: VAROM | AA25: (source Eurostat)
B26: P-RNW-ST-BIO-CCS05 | C26: PWRBIO | D26: ELCC | E26: 2018 | F26: 2019 | G26: 20 | H26: 0.61 | I26: 31.536 | J26: 0.082 | K26: 0.34 | L26: 3373 | M26: 118 | R26: Source: JRC-EU-TIMES model documentation 2013 (p. 87 Biomass with carbon sequestration)
E27: 2020 | J27: 0.09 | K27: 0.34 | L27: 3373 | M27: 118
E28: 2030 | J28: 0.09 | K28: 0.35 | L28: 2652 | M28: 93
E29: 2050 | J29: 0.09 | K29: 0.36 | L29: 2321 | M29: 81
B32: ~FI_Process
B33: Sets | C33: TechName | D33: TechDesc | E33: Tact | F33: Tcap | G33: Tslvl | H33: PrimaryCG | I33: Vintage
B34: ELE | C34: P-RNW-ST-BIO-CCS05 | D34: Steam Turbine Biomass WOO with CO2seq | E34: PJ | F34: GW | G34: DAYNITE

Sheet Win_ON_Cost_Data
A1: fid | B1: Merged_ID | C1: Parcel | D1: COUNTY - 1 | E1: COUNTY - 2 | F1: Station ID | G1: name | H1: operator | I1: voltage | J1: voltage_pr | K1: voltage_te | L1: Distance | M1: Round Up Distance | N1: Area_km_2_ | O1: Class | P1: Area With Packing Density Applied(km2) | Q1: Rationalised Output Per Parcel (MW) | R1: Rationalised Output Per Parcel (MW) | S1: Cost (€) | T1: PS | U1: Cost Per MW | V1: Watt per Euro
A2: 1 | B2: 1 | C2: CL1-001 | D2: KERRY | E2: KERRY | F2: SS-636 | G2: Garranebane 38kV Substation | H2: ESB Networks | I2: 38000 | J2: 38000 | K2: 20000 | L2: 15.861 | M2: 16 | N2: 0.122 | O2: 1 | P2: 0.122 | Q2: 3.45 | R2: 3.45 | S2: 1703340 | T2: 1 | U2: 493721.74 | V2: 2.0254324
A3: 2 | B3: 2 | C3: CL1-002 | D3: KERRY | E3: KERRY | F3: SS-636 | G3: Garranebane 38kV Substation | H3: ESB Networks | I3: 38000 | J3: 38000 | K3: 20000 | L3: 5.42 | M3: 6 | N3: 0.263 | O3: 1 | P3: 0.263 | Q3: 3.45 | R3: 3.45 | S3: 769410 | T3: 4 | U3: 223017.39 | V3: 4.4839552
A4: 3 | B4: 3 | C4: CL1-003 | D4: GALWAY | E4: GALWAY | F4: SS-106 | G4: Clifden 38kV Substation | H4: ESB Networks | I4: 38000 | J4: 38000 | K4: low | L4: 11.691 | M4: 12 | N4: 0.133 | O4: 1 | P4: 0.133 | Q4: 3.45 | R4: 3.45 | S4: 1492540 | T4: 1 | U4: 432620.29 | V4: 2.3114958
A5: 4 | B5: 4 | C5: CL1-004 | D5: DONEGAL | E5: DONEGAL | F5: SS-250 | G5: Kilcar 38kV Substation | H5: ESB Networks | I5: 38000 | J5: 38000 | K5: 10000 | L5: 13.24 | M5: 14 | N5: 0.133 | O5: 1 | P5: 0.133 | Q5: 3.45 | R5: 3.45 | S5: 1597940 | T5: 1 | U5: 463171.01 | V5: 2.1590298
A6: 5 | B6: 5 | C6: CL1-005 | D6: DONEGAL | E6: DONEGAL | F6: SS-138 | G6: Creeslough 38kV Substation | H6: ESB Networks | I6: 38000 | J6: 38000 | K6: low | L6: 9.962 | M6: 10 | N6: 0.157 | O6: 1 | P6: 0.157 | Q6: 3.45 | R6: 3.45 | S6: 1387140 | T6: 1 | U6: 402069.57 | V6: 2.4871318
A7: 6 | B7: 6 | C7: CL1-006 | D7: DONEGAL | E7: DONEGAL | F7: SS-119 | G7: Drumlough Hill (1) 38kV Substation | H7: ESB Networks | I7: 38000 | J7: low | K7: 38000 | L7: 10.639 | M7: 11 | N7: 0.093 | O7: 1 | P7: 0.093 | Q7: 3.45 | R7: 3.45 | S7: 1439840 | T7: 1 | U7: 417344.93 | V7: 2.3960996
A8: 7 | B8: 7 | C8: CL1-007 | D8: CLARE | E8: CLARE | F8: SS-708 | H8: EirGrid | I8: 110000 | J8: medium | K8: 110000 | L8: 1.526 | M8: 2 | N8: 0.126 | O8: 1 | P8: 0.126 | Q8: 3.45 | R8: 3.45 | S8: 1340080 | T8: 11 | U8: 388428.99 | V8: 2.5744732
A9: 8 | B9: 8 | C9: CL1-008 | D9: DUBLIN | E9: DUBLIN | F9: SS-014 | G9: Ballyboden 38kV Substation | H9: ESB Networks | I9: 38000 | J9: 38000 | K9: 10000 | L9: 6.009 | M9: 7 | N9: 0.28 | O9: 1 | P9: 0.28 | Q9: 3.45 | R9: 3.45 | S9: 839680 | T9: 4 | U9: 243385.51 | V9: 4.1087081
A10: 9 | B10: 9 | C10: CL1-009 | D10: DUBLIN | E10: DUBLIN | F10: SS-014 | G10: Ballyboden 38kV Substation | H10: ESB Networks | I10: 38000 | J10: 38000 | K10: 10000 | L10: 5.282 | M10: 6 | N10: 0.178 | O10: 1 | P10: 0.178 | Q10: 3.45 | R10: 3.45 | S10: 769410 | T10: 4 | U10: 223017.39 | V10: 4.4839552
A11: 10 | B11: 10 | C11: CL1-010 | D11: WICKLOW | E11: WICKLOW | F11: SS-010 | G11: Fassaroe 110kV Substation | H11: EirGrid | I11: 110000 | J11: 110000 | K11: 38000 | L11: 4.695 | M11: 5 | N11: 0.2 | O11: 1 | P11: 0.2 | Q11: 3.45 | R11: 3.45 | S11: 1679970 | T11: 7 | U11: 486947.83 | V11: 2.0536081
A12: 11 | B12: 11 | C12: CL1-011 | D12: WICKLOW | E12: WICKLOW | F12: SS-010 | G12: Fassaroe 110kV Substation | H12: EirGrid | I12: 110000 | J12: 110000 | K12: 38000 | L12: 5.608 | M12: 6 | N12: 0.116 | O12: 1 | P12: 0.116 | Q12: 3.45 | R12: 3.45 | S12: 1732670 | T12: 7 | U12: 502223.19 | V12: 1.9911466
A13: 12 | B13: 12 | C13: CL1-012 | D13: WICKLOW | E13: WICKLOW | F13: SS-597 | G13: Kilmartin 38kV Substation | H13: ESB Networks | I13: 38000 | J13: 38000 | K13: low | L13: 5.924 | M13: 6 | N13: 0.134 | O13: 1 | P13: 0.134 | Q13: 3.45 | R13: 3.45 | S13: 769410 | T13: 4 | U13: 223017.39 | V13: 4.4839552
A14: 13 | B14: 13 | C14: CL1-013 | D14: CORK | E14: CORK | F14: SS-253 | G14: Ballydehob 38kV Substation | H14: ESB Networks | I14: 38000 | J14: 38000 | K14: low | L14: 8.843 | M14: 9 | N14: 0.139 | O14: 1 | P14: 0.139 | Q14: 3.45 | R14: 3.45 | S14: 1334440 | T14: 1 | U14: 386794.2 | V14: 2.5853542
A15: 14 | B15: 14 | C15: CL1-014 | D15: WICKLOW | E15: WICKLOW | F15: SS-037 | G15: Ballybeg 110kV Substation | H15: EirGrid | I15: 110000 | J15: 110000 | K15: 38000 | L15: 4.542 | M15: 5 | N15: 0.154 | O15: 1 | P15: 0.154 | Q15: 3.45 | R15: 3.45 | S15: 1679970 | T15: 7 | U15: 486947.83 | V15: 2.0536081
A16: 15 | B16: 15 | C16: CL1-015 | D16: KERRY | E16: KERRY | F16: SS-635 | G16: Dingle 38kV Substation | H16: ESB Networks | I16: 38000 | J16: 38000 | K16: 20000 | L16: 11.995 | M16: 12 | N16: 0.155 | O16: 1 | P16: 0.155 | Q16: 3.45 | R16: 3.45 | S16: 1492540 | T16: 1 | U16: 432620.29 | V16: 2.3114958
A17: 16 | B17: 16 | C17: CL1-016 | D17: CORK | E17: CORK | F17: SS-273 | G17: Castletownbere 38kV Substation | H17: ESB Networks | I17: 38000 | J17: 38000 | K17: 20000 | L17: 11.179 | M17: 12 | N17: 0.101 | O17: 1 | P17: 0.101 | Q17: 3.45 | R17: 3.45 | S17: 1492540 | T17: 1 | U17: 432620.29 | V17: 2.3114958
A18: 17 | B18: 17 | C18: CL1-017 | D18: DONEGAL | E18: DONEGAL | F18: SS-610 | G18: Milford (North) 38kV Substation | H18: ESB Networks | I18: 38000 | J18: 38000 | K18: low | L18: 14.864 | M18: 15 | N18: 0.149 | O18: 1 | P18: 0.149 | Q18: 3.45 | R18: 3.45 | S18: 1650640 | T18: 1 | U18: 478446.38 | V18: 2.0900984
A19: 18 | B19: 18 | C19: CL1-018 | D19: DONEGAL | E19: DONEGAL | F19: SS-117 | G19: Crockahenny 38kV Substation | H19: ESB Networks | I19: 38000 | J19: low | K19: 38000 | L19: 2.217 | M19: 3 | N19: 0.259 | O19: 1 | P19: 0.259 | Q19: 3.45 | R19: 3.45 | S19: 558600 | T19: 4 | U19: 161913.04 | V19: 6.1761547
A20: 19 | B20: 19 | C20: CL1-019 | D20: MAYO | E20: MAYO | F20: SS-642 | G20: Achill 38kV Substation | H20: ESB Networks | I20: 38000 | J20: 38000 | K20: 20000 | L20: 7.887 | M20: 8 | N20: 0.337 | O20: 1 | P20: 0.337 | Q20: 3.45 | R20: 3.45 | S20: 909950 | T20: 4 | U20: 263753.62 | V20: 3.7914171
A21: 20 | B21: 20 | C21: CL1-020 | D21: DONEGAL | E21: DONEGAL | F21: SS-123 | G21: Derrybeg 38kV Substation | H21: ESB Networks | I21: 38000 | J21: 38000 | K21: 10000 | L21: 8.548 | M21: 9 | N21: 0.523 | O21: 1 | P21: 0.523 | Q21: 3.45 | R21: 3.45 | S21: 1334440 | T21: 1 | U21: 386794.2 | V21: 2.5853542
A22: 21 | B22: 21 | C22: CL1-021 | D22: KERRY | E22: KERRY | F22: SS-636 | G22: Garranebane 38kV Substation | H22: ESB Networks | I22: 38000 | J22: 38000 | K22: 20000 | L22: 13.635 | M22: 14 | N22: 0.289 | O22: 1 | P22: 0.289 | Q22: 3.45 | R22: 3.45 | S22: 1597940 | T22: 1 | U22: 463171.01 | V22: 2.1590298
A23: 22 | B23: 22 | C23: CL1-022 | D23: WICKLOW | E23: WICKLOW | F23: SS-209 | G23: Blessington 38kV Substation | H23: ESB Networks | I23: 38000 | J23: 38000 | K23: 20000 | L23: 7.06 | M23: 8 | N23: 0.325 | O23: 1 | P23: 0.325 | Q23: 3.45 | R23: 3.45 | S23: 909950 | T23: 4 | U23: 263753.62 | V23: 3.7914171
A24: 23 | B24: 23 | C24: CL1-023 | D24: DONEGAL | E24: DONEGAL | F24: SS-117 | G24: Crockahenny 38kV Substation | H24: ESB Networks | I24: 38000 | J24: low | K24: 38000 | L24: 4.876 | M24: 5 | N24: 0.614 | O24: 1 | P24: 0.4605 | Q24: 3.45 | R24: 3.45 | S24: 699140 | T24: 4 | U24: 202649.28 | V24: 4.934634
A25: 24 | B25: 24 | C25: CL1-024 | D25: DONEGAL | E25: DONEGAL | F25: SS-617 | G25: Mulreavy 110kV Substation | H25: EirGrid | I25: 110000 | J25: 33000 | K25: 110000 | L25: 12.664 | M25: 13 | N25: 0.209 | O25: 1 | P25: 0.209 | Q25: 3.45 | R25: 3.45 | S25: 2101570 | T25: 7 | U25: 609150.72 | V25: 1.6416298
A26: 25 | B26: 25 | C26: CL1-025 | D26: CAVAN | E26: CAVAN | F26: SS-110 | G26: Corraclassy 110kV Substation | H26: EirGrid | I26: 110000 | L26: 10.905 | M26: 11 | N26: 0.786 | O26: 1 | P26: 0.5895 | Q26: 3.45 | R26: 3.45 | S26: 1996170 | T26: 7 | U26: 578600 | V26: 1.7283097
A27: 26 | B27: 26 | C27: CL1-026 | D27: LOUTH | E27: LOUTH | F27: SS-650 | G27: Ballymascanlan 38kV Substation | H27: ESB Networks | I27: 38000 | J27: 38000 | K27: low | L27: 4.994 | M27: 5 | N27: 0.211 | O27: 1 | P27: 0.211 | Q27: 3.45 | R27: 3.45 | S27: 699140 | T27: 4 | U27: 202649.28 | V27: 4.934634
A28: 27 | B28: 27 | C28: CL1-027 | D28: CORK | E28: CORK | F28: SS-362 | G28: Glengarriff 38kV Substation | H28: ESB Networks | I28: 38000 | J28: 38000 | K28: 20000 | L28: 12.641 | M28: 13 | N28: 0.281 | O28: 1 | P28: 0.281 | Q28: 3.45 | R28: 3.45 | S28: 1545240 | T28: 1 | U28: 447895.65 | V28: 2.2326629
A29: 28 | B29: 28 | C29: CL1-028 | D29: KERRY | E29: KERRY | F29: SS-362 | G29: Glengarriff 38kV Substation | H29: ESB Networks | I29: 38000 | J29: 38000 | K29: 20000 | L29: 12.848 | M29: 13 | N29: 0.134 | O29: 1 | P29: 0.134 | Q29: 3.45 | R29: 3.45 | S29: 1545240 | T29: 1 | U29: 447895.65 | V29: 2.2326629
A30: 29 | B30: 29 | C30: CL1-029 | D30: CORK | E30: CORK | F30: SS-273 | G30: Castletownbere 38kV Substation | H30: ESB Networks | I30: 38000 | J30: 38000 | K30: 20000 | L30: 12.044 | M30: 13 | N30: 0.17 | O30: 1 | P30: 0.17 | Q30: 3.45 | R30: 3.45 | S30: 1545240 | T30: 1 | U30: 447895.65 | V30: 2.2326629
A31: 30 | B31: 30 | C31: CL1-030 | D31: KERRY | E31: KERRY | F31: SS-337 | G31: Knockaneden 38kV Substation | H31: ESB Networks | I31: 38000 | J31: low | K31: 38000 | L31: 13.637 | M31: 14 | N31: 0.496 | O31: 1 | P31: 0.496 | Q31: 3.45 | R31: 3.45 | S31: 1597940 | T31: 1 | U31: 463171.01 | V31: 2.1590298
A32: 31 | B32: 31 | C32: CL1-031 | D32: KERRY | E32: KERRY | F32: SS-151 | G32: Kenmare 38kV Substation | H32: ESB Networks | I32: 38000 | J32: 38000 | K32: low | L32: 12.786 | M32: 13 | N32: 0.351 | O32: 1 | P32: 0.351 | Q32: 3.45 | R32: 3.45 | S32: 1545240 | T32: 1 | U32: 447895.65 | V32: 2.2326629
A33: 32 | B33: 32 | C33: CL1-032 | D33: KERRY | E33: KERRY | F33: SS-151 | G33: Kenmare 38kV Substation | H33: ESB Networks | I33: 38000 | J33: 38000 | K33: low | L33: 14.48 | M33: 15 | N33: 0.438 | O33: 1 | P33: 0.438 | Q33: 3.45 | R33: 3.45 | S33: 1650640 | T33: 1 | U33: 478446.38 | V33: 2.0900984
A34: 33 | B34: 33 | C34: CL1-033 | D34: KERRY | E34: KERRY | F34: SS-321 | G34: Milltown 38kV Substation | H34: ESB Networks | I34: 38000 | J34: 38000 | K34: 20000 | L34: 11.713 | M34: 12 | N34: 0.121 | O34: 1 | P34: 0.121 | Q34: 3.45 | R34: 3.45 | S34: 1492540 | T34: 1 | U34: 432620.29 | V34: 2.3114958
A35: 34 | B35: 34 | C35: CL1-034 | D35: KERRY | E35: KERRY | F35: SS-387 | G35: Coolcorcoran 38kV Substation | H35: ESB Networks | I35: 38000 | J35: 38000 | K35: low | L35: 11.301 | M35: 12 | N35: 0.237 | O35: 1 | P35: 0.237 | Q35: 3.45 | R35: 3.45 | S35: 1492540 | T35: 1 | U35: 432620.29 | V35: 2.3114958
A36: 35 | B36: 35 | C36: CL1-035 | D36: KERRY | E36: KERRY | F36: SS-151 | G36: Kenmare 38kV Substation | H36: ESB Networks | I36: 38000 | J36: 38000 | K36: low | L36: 15.65 | M36: 16 | N36: 0.262 | O36: 1 | P36: 0.262 | Q36: 3.45 | R36: 3.45 | S36: 1703340 | T36: 1 | U36: 493721.74 | V36: 2.0254324
A37: 36 | B37: 36 | C37: CL1-036 | D37: KERRY | E37: KERRY | F37: SS-636 | G37: Garranebane 38kV Substation | H37: ESB Networks | I37: 38000 | J37: 38000 | K37: 20000 | L37: 4.091 | M37: 5 | N37: 0.567 | O37: 1 | P37: 0.567 | Q37: 3.45 | R37: 3.45 | S37: 699140 | T37: 4 | U37: 202649.28 | V37: 4.934634
A38: 37 | B38: 37 | C38: CL1-037 | D38: KERRY | E38: KERRY | F38: SS-337 | G38: Knockaneden 38kV Substation | H38: ESB Networks | I38: 38000 | J38: low | K38: 38000 | L38: 2.79 | M38: 3 | N38: 0.399 | O38: 1 | P38: 0.399 | Q38: 3.45 | R38: 3.45 | S38: 558600 | T38: 4 | U38: 161913.04 | V38: 6.1761547
A39: 38 | B39: 38 | C39: CL1-038 | D39: KERRY | E39: KERRY | F39: SS-337 | G39: Knockaneden 38kV Substation | H39: ESB Networks | I39: 38000 | J39: low | K39: 38000 | L39: 14.268 | M39: 15 | N39: 0.109 | O39: 1 | P39: 0.109 | Q39: 3.45 | R39: 3.45 | S39: 1650640 | T39: 1 | U39: 478446.38 | V39: 2.0900984
A40: 39 | B40: 39 | C40: CL1-039 | D40: KERRY | E40: KERRY | F40: SS-337 | G40: Knockaneden 38kV Substation | H40: ESB Networks | I40: 38000 | J40: low | K40: 38000 | L40: 9.745 | M40: 10 | N40: 0.123 | O40: 1 | P40: 0.123 | Q40: 3.45 | R40: 3.45 | S40: 1387140 | T40: 1 | U40: 402069.57 | V40: 2.4871318
A41: 40 | B41: 40 | C41: CL1-040 | D41: KERRY | E41: KERRY | F41: SS-337 | G41: Knockaneden 38kV Substation | H41: ESB Networks | I41: 38000 | J41: low | K41: 38000 | L41: 9.612 | M41: 10 | N41: 0.099 | O41: 1 | P41: 0.099 | Q41: 3.45 | R41: 3.45 | S41: 1387140 | T41: 1 | U41: 402069.57 | V41: 2.4871318
A42: 41 | B42: 41 | C42: CL1-041 | D42: KERRY | E42: KERRY | F42: SS-337 | G42: Knockaneden 38kV Substation | H42: ESB Networks | I42: 38000 | J42: low | K42: 38000 | L42: 15.118 | M42: 16 | N42: 0.109 | O42: 1 | P42: 0.109 | Q42: 3.45 | R42: 3.45 | S42: 1703340 | T42: 1 | U42: 493721.74 | V42: 2.0254324
A43: 42 | B43: 42 | C43: CL1-042 | D43: CORK | E43: CORK | F43: SS-362 | G43: Glengarriff 38kV Substation | H43: ESB Networks | I43: 38000 | J43: 38000 | K43: 20000 | L43: 1.996 | M43: 2 | N43: 0.14 | O43: 1 | P43: 0.14 | Q43: 3.45 | R43: 3.45 | S43: 488330 | T43: 4 | U43: 141544.93 | V43: 7.0648946
A44: 43 | B44: 43 | C44: CL1-043 | D44: CORK | E44: CORK | F44: SS-362 | G44: Glengarriff 38kV Substation | H44: ESB Networks | I44: 38000 | J44: 38000 | K44: 20000 | L44: 2.393 | M44: 3 | N44: 0.093 | O44: 1 | P44: 0.093 | Q44: 3.45 | R44: 3.45 | S44: 558600 | T44: 4 | U44: 161913.04 | V44: 6.1761547
A45: 44 | B45: 44 | C45: CL1-044 | D45: CORK | E45: KERRY | F45: SS-362 | G45: Glengarriff 38kV Substation | H45: ESB Networks | I45: 38000 | J45: 38000 | K45: 20000 | L45: 4.316 | M45: 5 | N45: 0.219 | O45: 1 | P45: 0.219 | Q45: 3.45 | R45: 3.45 | S45: 699140 | T45: 4 | U45: 202649.28 | V45: 4.934634
A46: 45 | B46: 45 | C46: CL1-045 | D46: KERRY | E46: KERRY | F46: SS-637 | G46: Kilgarvan 38kV Substation | H46: ESB Networks | I46: 38000 | J46: 38000 | K46: 20000 | L46: 4.375 | M46: 5 | N46: 0.163 | O46: 1 | P46: 0.163 | Q46: 3.45 | R46: 3.45 | S46: 699140 | T46: 4 | U46: 202649.28 | V46: 4.934634
A47: 46 | B47: 46 | C47: CL1-046 | D47: KERRY | E47: KERRY | F47: SS-637 | G47: Kilgarvan 38kV Substation | H47: ESB Networks | I47: 38000 | J47: 38000 | K47: 20000 | L47: 5.589 | M47: 6 | N47: 0.256 | O47: 1 | P47: 0.256 | Q47: 3.45 | R47: 3.45 | S47: 769410 | T47: 4 | U47: 223017.39 | V47: 4.4839552
A48: 47 | B48: 47 | C48: CL1-047 | D48: KERRY | E48: KERRY | F48: SS-635 | G48: Dingle 38kV Substation | H48: ESB Networks | I48: 38000 | J48: 38000 | K48: 20000 | L48: 10.077 | M48: 11 | N48: 0.349 | O48: 1 | P48: 0.349 | Q48: 3.45 | R48: 3.45 | S48: 1439840 | T48: 1 | U48: 417344.93 | V48: 2.3960996
A49: 48 | B49: 48 | C49: CL1-048 | D49: KERRY | E49: KERRY | F49: SS-634 | G49: Inch 38kV Substation | H49: ESB Networks | I49: 38000 | J49: 38000 | K49: 20000 | L49: 7.851 | M49: 8 | N49: 0.591 | O49: 1 | P49: 0.591 | Q49: 3.45 | R49: 3.45 | S49: 909950 | T49: 4 | U49: 263753.62 | V49: 3.7914171
A50: 49 | B50: 49 | C50: CL1-049 | D50: KERRY | E50: KERRY | F50: SS-140 | G50: Ballyard 38kV Substation | H50: ESB Networks | I50: 38000 | J50: 38000 | K50: 10000 | L50: 4.771 | M50: 5 | N50: 0.381 | O50: 1 | P50: 0.381 | Q50: 3.45 | R50: 3.45 | S50: 699140 | T50: 4 | U50: 202649.28 | V50: 4.934634
A51: 50 | B51: 50 | C51: CL1-050 | D51: CLARE | E51: CLARE | F51: SS-595 | G51: Kilkee 38kV Substation | H51: ESB Networks | I51: 38000 | J51: 38000 | K51: low | L51: 23.476 | M51: 24 | N51: 0.195 | O51: 1 | P51: 0.195 | Q51: 3.45 | R51: 3.45 | S51: 2124940 | T51: 1 | U51: 615924.64 | V51: 1.6235753
A52: 51 | B52: 51 | C52: CL1-051 | D52: CLARE | E52: CLARE | F52: SS-134 | G52: Ennistymon 38kV Substation | H52: ESB Networks | I52: 38000 | J52: 38000 | K52: low | L52: 15.891 | M52: 16 | N52: 0.111 | O52: 1 | P52: 0.111 | Q52: 3.45 | R52: 3.45 | S52: 1703340 | T52: 1 | U52: 493721.74 | V52: 2.0254324
A53: 52 | B53: 52 | C53: CL1-052 | D53: GALWAY | E53: GALWAY | F53: SS-105 | G53: Garroman 38kV Substation | H53: ESB Networks | I53: 38000 | J53: 38000 | K53: low | L53: 15.806 | M53: 16 | N53: 0.437 | O53: 1 | P53: 0.437 | Q53: 3.45 | R53: 3.45 | S53: 1703340 | T53: 1 | U53: 493721.74 | V53: 2.0254324
A54: 53 | B54: 53 | C54: CL1-053 | D54: GALWAY | E54: GALWAY | F54: SS-106 | G54: Clifden 38kV Substation | H54: ESB Networks | I54: 38000 | J54: 38000 | K54: low | L54: 11.451 | M54: 12 | N54: 0.189 | O54: 1 | P54: 0.189 | Q54: 3.45 | R54: 3.45 | S54: 1492540 | T54: 1 | U54: 432620.29 | V54: 2.3114958
A55: 54 | B55: 54 | C55: CL1-054 | D55: GALWAY | E55: GALWAY | F55: SS-106 | G55: Clifden 38kV Substation | H55: ESB Networks | I55: 38000 | J55: 38000 | K55: low | L55: 5.715 | M55: 6 | N55: 0.331 | O55: 1 | P55: 0.331 | Q55: 3.45 | R55: 3.45 | S55: 769410 | T55: 4 | U55: 223017.39 | V55: 4.4839552
A56: 55 | B56: 55 | C56: CL1-055 | D56: GALWAY | E56: GALWAY | F56: SS-105 | G56: Garroman 38kV Substation | H56: ESB Networks | I56: 38000 | J56: 38000 | K56: low | L56: 4.746 | M56: 5 | N56: 0.316 | O56: 1 | P56: 0.316 | Q56: 3.45 | R56: 3.45 | S56: 699140 | T56: 4 | U56: 202649.28 | V56: 4.934634
A57: 56 | B57: 56 | C57: CL1-056 | D57: GALWAY | E57: GALWAY | F57: SS-105 | G57: Garroman 38kV Substation | H57: ESB Networks | I57: 38000 | J57: 38000 | K57: low | L57: 14.998 | M57: 15 | N57: 0.394 | O57: 1 | P57: 0.394 | Q57: 3.45 | R57: 3.45 | S57: 1650640 | T57: 1 | U57: 478446.38 | V57: 2.0900984
A58: 57 | B58: 57 | C58: CL1-057 | D58: MAYO | E58: MAYO | F58: SS-461 | G58: Westport 38kV Substation | H58: ESB Networks | I58: 38000 | J58: 38000 | K58: 20000 | L58: 15.493 | M58: 16 | N58: 0.104 | O58: 1 | P58: 0.104 | Q58: 3.45 | R58: 3.45 | S58: 1703340 | T58: 1 | U58: 493721.74 | V58: 2.0254324
A59: 58 | B59: 58 | C59: CL1-058 | D59: GALWAY | E59: GALWAY | F59: SS-638 | G59: Oughterard 38kV Substation | H59: ESB Networks | I59: 38000 | J59: 38000 | K59: 10000 | L59: 12.648 | M59: 13 | N59: 0.377 | O59: 1 | P59: 0.377 | Q59: 3.45 | R59: 3.45 | S59: 1545240 | T59: 1 | U59: 447895.65 | V59: 2.2326629
A60: 59 | B60: 59 | C60: CL1-059 | D60: GALWAY | E60: GALWAY | F60: SS-638 | G60: Oughterard 38kV Substation | H60: ESB Networks | I60: 38000 | J60: 38000 | K60: 10000 | L60: 8.696 | M60: 9 | N60: 0.246 | O60: 1 | P60: 0.246 | Q60: 3.45 | R60: 3.45 | S60: 1334440 | T60: 1 | U60: 386794.2 | V60: 2.5853542
A61: 60 | B61: 60 | C61: CL1-060 | D61: MAYO | E61: MAYO | F61: SS-073 | G61: Carrowbeg 110kV Substation | H61: EirGrid | I61: 110000 | J61: 110000 | K61: 38000 | L61: 23.516 | M61: 24 | N61: 0.218 | O61: 1 | P61: 0.218 | Q61: 3.45 | R61: 3.45 | S61: 2681270 | T61: 7 | U61: 777179.71 | V61: 1.2867037
A62: 61 | B62: 61 | C62: CL1-061 | D62: MAYO | E62: MAYO | F62: SS-073 | G62: Carrowbeg 110kV Substation | H62: EirGrid | I62: 110000 | J62: 110000 | K62: 38000 | L62: 23.133 | M62: 24 | N62: 0.191 | O62: 1 | P62: 0.191 | Q62: 3.45 | R62: 3.45 | S62: 2681270 | T62: 7 | U62: 777179.71 | V62: 1.2867037
A63: 62 | B63: 62 | C63: CL1-062 | D63: MAYO | E63: MAYO | F63: SS-073 | G63: Carrowbeg 110kV Substation | H63: EirGrid | I63: 110000 | J63: 110000 | K63: 38000 | L63: 20.874 | M63: 21 | N63: 0.106 | O63: 1 | P63: 0.106 | Q63: 3.45 | R63: 3.45 | S63: 2523170 | T63: 7 | U63: 731353.62 | V63: 1.3673276
A64: 63 | B64: 63 | C64: CL1-063 | D64: GALWAY | E64: GALWAY | F64: SS-105 | G64: Garroman 38kV Substation | H64: ESB Networks | I64: 38000 | J64: 38000 | K64: low | L64: 3.98 | M64: 4 | N64: 0.279 | O64: 1 | P64: 0.279 | Q64: 3.45 | R64: 3.45 | S64: 628870 | T64: 4 | U64: 182281.16 | V64: 5.4860305
A65: 64 | B65: 64 | C65: CL1-064 | D65: GALWAY | E65: GALWAY | F65: SS-105 | G65: Garroman 38kV Substation | H65: ESB Networks | I65: 38000 | J65: 38000 | K65: low | L65: 11.894 | M65: 12 | N65: 0.276 | O65: 1 | P65: 0.276 | Q65: 3.45 | R65: 3.45 | S65: 1492540 | T65: 1 | U65: 432620.29 | V65: 2.3114958
A66: 65 | B66: 65 | C66: CL1-065 | D66: MAYO | E66: MAYO | F66: SS-317 | G66: Newport 38kV Substation | H66: ESB Networks | I66: 38000 | J66: 38000 | K66: 20000 | L66: 11.804 | M66: 12 | N66: 0.167 | O66: 1 | P66: 0.167 | Q66: 3.45 | R66: 3.45 | S66: 1492540 | T66: 1 | U66: 432620.29 | V66: 2.3114958
A67: 66 | B67: 66 | C67: CL1-066 | D67: MAYO | E67: MAYO | F67: SS-133 | G67: Bellacorrick 110kV Substation | H67: EirGrid | I67: 110000 | J67: 110000 | K67: 38000 | L67: 10.284 | M67: 11 | N67: 0.094 | O67: 1 | P67: 0.094 | Q67: 3.45 | R67: 3.45 | S67: 1996170 | T67: 7 | U67: 578600 | V67: 1.7283097
A68: 67 | B68: 67 | C68: CL1-067 | D68: MAYO | E68: MAYO | F68: SS-419 | G68: Bangor 38kV Substation | H68: ESB Networks | I68: 38000 | J68: 38000 | K68: low | L68: 5.543 | M68: 6 | N68: 0.698 | O68: 1 | P68: 0.5235 | Q68: 3.45 | R68: 3.45 | S68: 769410 | T68: 4 | U68: 223017.39 | V68: 4.4839552
A69: 68 | B69: 68 | C69: CL1-068 | D69: MAYO | E69: MAYO | F69: SS-419 | G69: Bangor 38kV Substation | H69: ESB Networks | I69: 38000 | J69: 38000 | K69: low | L69: 14.459 | M69: 15 | N69: 0.288 | O69: 1 | P69: 0.288 | Q69: 3.45 | R69: 3.45 | S69: 1650640 | T69: 1 | U69: 478446.38 | V69: 2.0900984
A70: 69 | B70: 69 | C70: CL1-069 | D70: MAYO | E70: MAYO | F70: SS-419 | G70: Bangor 38kV Substation | H70: ESB Networks | I70: 38000 | J70: 38000 | K70: low | L70: 15.611 | M70: 16 | N70: 0.148 | O70: 1 | P70: 0.148 | Q70: 3.45 | R70: 3.45 | S70: 1703340 | T70: 1 | U70: 493721.74 | V70: 2.0254324
A71: 70 | B71: 70 | C71: CL1-070 | D71: MAYO | E71: MAYO | F71: SS-419 | G71: Bangor 38kV Substation | H71: ESB Networks | I71: 38000 | J71: 38000 | K71: low | L71: 15.467 | M71: 16 | N71: 0.187 | O71: 1 | P71: 0.187 | Q71: 3.45 | R71: 3.45 | S71: 1703340 | T71: 1 | U71: 493721.74 | V71: 2.0254324
A72: 71 | B72: 71 | C72: CL1-071 | D72: MAYO | E72: MAYO | F72: SS-419 | G72: Bangor 38kV Substation | H72: ESB Networks | I72: 38000 | J72: 38000 | K72: low | L72: 16.38 | M72: 17 | N72: 0.131 | O72: 1 | P72: 0.131 | Q72: 3.45 | R72: 3.45 | S72: 1756040 | T72: 1 | U72: 508997.1 | V72: 1.9646477
A73: 72 | B73: 72 | C73: CL1-072 | D73: MAYO | E73: MAYO | F73: SS-419 | G73: Bangor 38kV Substation | H73: ESB Networks | I73: 38000 | J73: 38000 | K73: low | L73: 1.724 | M73: 2 | N73: 0.688 | O73: 1 | P73: 0.516 | Q73: 3.45 | R73: 3.45 | S73: 488330 | T73: 4 | U73: 141544.93 | V73: 7.0648946
A74: 73 | B74: 73 | C74: CL1-073 | D74: MAYO | E74: MAYO | F74: SS-234 | G74: Crossmolina 38kV Substation | H74: ESB Networks | I74: 38000 | J74: 38000 | K74: low | L74: 13.238 | M74: 14 | N74: 0.596 | O74: 1 | P74: 0.447 | Q74: 3.45 | R74: 3.45 | S74: 1597940 | T74: 1 | U74: 463171.01 | V74: 2.1590298
A75: 74 | B75: 74 | C75: CL1-074 | D75: MAYO | E75: MAYO | F75: SS-133 | G75: Bellacorrick 110kV Substation | H75: EirGrid | I75: 110000 | J75: 110000 | K75: 38000 | L75: 13.919 | M75: 14 | N75: 0.619 | O75: 1 | P75: 0.46425 | Q75: 3.45 | R75: 3.45 | S75: 2154270 | T75: 7 | U75: 624426.09 | V75: 1.6014706
A76: 75 | B76: 75 | C76: CL1-075 | D76: MAYO | E76: MAYO | F76: SS-710 | G76: Tawnaghmore 110kV Substation | H76: EirGrid | I76: 110000 | J76: low | K76: 110000 | L76: 14.333 | M76: 15 | N76: 0.103 | O76: 1 | P76: 0.103 | Q76: 3.45 | R76: 3.45 | S76: 2206970 | T76: 7 | U76: 639701.45 | V76: 1.5632292
A77: 76 | B77: 76 | C77: CL1-076 | D77: MAYO | E77: MAYO | F77: SS-710 | G77: Tawnaghmore 110kV Substation | H77: EirGrid | I77: 110000 | J77: low | K77: 110000 | L77: 16.962 | M77: 17 | N77: 0.325 | O77: 1 | P77: 0.325 | Q77: 3.45 | R77: 3.45 | S77: 2312370 | T77: 7 | U77: 670252.17 | V77: 1.4919758
A78: 77 | B78: 77 | C78: CL1-077 | D78: MAYO | E78: MAYO | F78: SS-419 | G78: Bangor 38kV Substation | H78: ESB Networks | I78: 38000 | J78: 38000 | K78: low | L78: 7.99 | M78: 8 | N78: 0.129 | O78: 1 | P78: 0.129 | Q78: 3.45 | R78: 3.45 | S78: 909950 | T78: 4 | U78: 263753.62 | V78: 3.7914171
A79: 78 | B79: 78 | C79: CL1-078 | D79: SLIGO | E79: SLIGO | F79: SS-075 | G79: Cunghill 110kV Substation | H79: EirGrid | I79: 110000 | J79: 110000 | K79: medium | L79: 11.375 | M79: 12 | N79: 0.246 | O79: 1 | P79: 0.246 | Q79: 3.45 | R79: 3.45 | S79: 2048870 | T79: 7 | U79: 593875.36 | V79: 1.683855
A80: 79 | B80: 79 | C80: CL1-079 | D80: SLIGO | E80: SLIGO | F80: SS-075 | G80: Cunghill 110kV Substation | H80: EirGrid | I80: 110000 | J80: 110000 | K80: medium | L80: 11.206 | M80: 12 | N80: 0.242 | O80: 1 | P80: 0.242 | Q80: 3.45 | R80: 3.45 | S80: 2048870 | T80: 7 | U80: 593875.36 | V80: 1.683855
A81: 80 | B81: 80 | C81: CL1-080 | D81: SLIGO | E81: LEITRIM | F81: SS-042 | G81: Ballytivnan 38kV Substation | H81: ESB Networks | I81: 38000 | J81: 38000 | K81: 10000 | L81: 10.22 | M81: 11 | N81: 0.206 | O81: 1 | P81: 0.206 | Q81: 3.45 | R81: 3.45 | S81: 1439840 | T81: 1 | U81: 417344.93 | V81: 2.3960996
A82: 81 | B82: 81 | C82: CL1-081 | D82: SLIGO | E82: SLIGO | F82: SS-042 | G82: Ballytivnan 38kV Substation | H82: ESB Networks | I82: 38000 | J82: 38000 | K82: 10000 | L82: 8.688 | M82: 9 | N82: 0.249 | O82: 1 | P82: 0.249 | Q82: 3.45 | R82: 3.45 | S82: 1334440 | T82: 1 | U82: 386794.2 | V82: 2.5853542
A83: 82 | B83: 82 | C83: CL1-082 | D83: SLIGO | E83: SLIGO | F83: SS-042 | G83: Ballytivnan 38kV Substation | H83: ESB Networks | I83: 38000 | J83: 38000 | K83: 10000 | L83: 8.236 | M83: 9 | N83: 0.132 | O83: 1 | P83: 0.132 | Q83: 3.45 | R83: 3.45 | S83: 1334440 | T83: 1 | U83: 386794.2 | V83: 2.5853542
A84: 83 | B84: 83 | C84: CL1-083 | D84: DONEGAL | E84: DONEGAL | F84: SS-250 | G84: Kilcar 38kV Substation | H84: ESB Networks | I84: 38000 | J84: 38000 | K84: 10000 | L84: 4.929 | M84: 5 | N84: 0.527 | O84: 1 | P84: 0.527 | Q84: 3.45 | R84: 3.45 | S84: 699140 | T84: 4 | U84: 202649.28 | V84: 4.934634
A85: 84 | B85: 84 | C85: CL1-084 | D85: DONEGAL | E85: DONEGAL | F85: SS-250 | G85: Kilcar 38kV Substation | H85: ESB Networks | I85: 38000 | J85: 38000 | K85: 10000 | L85: 13.065 | M85: 14 | N85: 0.101 | O85: 1 | P85: 0.101 | Q85: 3.45 | R85: 3.45 | S85: 1597940 | T85: 1 | U85: 463171.01 | V85: 2.1590298
A86: 85 | B86: 85 | C86: CL1-085 | D86: DONEGAL | E86: DONEGAL | F86: SS-090 | G86: Corkermore 38kV Substation | H86: ESB Networks | I86: 38000 | J86: low | K86: 38000 | L86: 9.143 | M86: 10 | N86: 0.599 | O86: 1 | P86: 0.44925 | Q86: 3.45 | R86: 3.45 | S86: 1387140 | T86: 1 | U86: 402069.57 | V86: 2.4871318
A87: 86 | B87: 86 | C87: CL1-086 | D87: DONEGAL | E87: DONEGAL | F87: SS-250 | G87: Kilcar 38kV Substation | H87: ESB Networks | I87: 38000 | J87: 38000 | K87: 10000 | L87: 11.022 | M87: 12 | N87: 0.205 | O87: 1 | P87: 0.205 | Q87: 3.45 | R87: 3.45 | S87: 1492540 | T87: 1 | U87: 432620.29 | V87: 2.3114958
A88: 87 | B88: 87 | C88: CL1-087 | D88: DONEGAL | E88: DONEGAL | F88: SS-250 | G88: Kilcar 38kV Substation | H88: ESB Networks | I88: 38000 | J88: 38000 | K88: 10000 | L88: 3.316 | M88: 4 | N88: 0.442 | O88: 1 | P88: 0.442 | Q88: 3.45 | R88: 3.45 | S88: 628870 | T88: 4 | U88: 182281.16 | V88: 5.4860305
A89: 88 | B89: 88 | C89: CL1-088 | D89: DONEGAL | E89: DONEGAL | F89: SS-250 | G89: Kilcar 38kV Substation | H89: ESB Networks | I89: 38000 | J89: 38000 | K89: 10000 | L89: 2.243 | M89: 3 | N89: 0.097 | O89: 1 | P89: 0.097 | Q89: 3.45 | R89: 3.45 | S89: 558600 | T89: 4 | U89: 161913.04 | V89: 6.1761547
A90: 89 | B90: 89 | C90: CL1-089 | D90: DONEGAL | E90: DONEGAL | F90: SS-252 | G90: Killybegs 38kV Substation | H90: ESB Networks | I90: 38000 | J90: 38000 | K90: 10000 | L90: 4.306 | M90: 5 | N90: 0.197 | O90: 1 | P90: 0.197 | Q90: 3.45 | R90: 3.45 | S90: 699140 | T90: 4 | U90: 202649.28 | V90: 4.934634
A91: 90 | B91: 90 | C91: CL1-090 | D91: DONEGAL | E91: DONEGAL | F91: SS-684 | G91: Tievebrack 110kV Substation | H91: EirGrid | I91: 110000 | J91: 110000 | K91: 38000 | L91: 3.787 | M91: 4 | N91: 0.318 | O91: 1 | P91: 0.318 | Q91: 3.45 | R91: 3.45 | S91: 1627270 | T91: 7 | U91: 471672.46 | V91: 2.1201153
A92: 91 | B92: 91 | C92: CL1-091 | D92: DONEGAL | E92: DONEGAL | F92: SS-684 | G92: Tievebrack 110kV Substation | H92: EirGrid | I92: 110000 | J92: 110000 | K92: 38000 | L92: 3.504 | M92: 4 | N92: 0.395 | O92: 1 | P92: 0.395 | Q92: 3.45 | R92: 3.45 | S92: 1627270 | T92: 7 | U92: 471672.46 | V92: 2.1201153
A93: 92 | B93: 92 | C93: CL1-092 | D93: DONEGAL | E93: DONEGAL | F93: SS-123 | G93: Derrybeg 38kV Substation | H93: ESB Networks | I93: 38000 | J93: 38000 | K93: 10000 | L93: 10.189 | M93: 11 | N93: 0.286 | O93: 1 | P93: 0.286 | Q93: 3.45 | R93: 3.45 | S93: 1439840 | T93: 1 | U93: 417344.93 | V93: 2.3960996
A94: 93 | B94: 93 | C94: CL1-093 | D94: DONEGAL | E94: DONEGAL | F94: SS-119 | G94: Drumlough Hill (1) 38kV Substation | H94: ESB Networks | I94: 38000 | J94: low | K94: 38000 | L94: 1.583 | M94: 2 | N94: 0.166 | O94: 1 | P94: 0.166 | Q94: 3.45 | R94: 3.45 | S94: 488330 | T94: 4 | U94: 141544.93 | V94: 7.0648946
A95: 94 | B95: 94 | C95: CL1-094 | D95: DONEGAL | E95: DONEGAL | F95: SS-239 | G95: Moville 38kV Substation | H95: ESB Networks | I95: 38000 | J95: 38000 | K95: 20000 | L95: 3.296 | M95: 4 | N95: 0.115 | O95: 1 | P95: 0.115 | Q95: 3.45 | R95: 3.45 | S95: 628870 | T95: 4 | U95: 182281.16 | V95: 5.4860305
A96: 95 | B96: 95 | C96: CL1-095 | D96: DONEGAL | E96: DONEGAL | F96: SS-689 | H96: ESB Networks | I96: 38000 | L96: 5.174 | M96: 6 | N96: 0.108 | O96: 1 | P96: 0.108 | Q96: 3.45 | R96: 3.45 | S96: 769410 | T96: 4 | U96: 223017.39 | V96: 4.4839552
A97: 96 | B97: 96 | C97: CL1-096 | D97: MAYO | E97: MAYO | F97: SS-642 | G97: Achill 38kV Substation | H97: ESB Networks | I97: 38000 | J97: 38000 | K97: 20000 | L97: 10.713 | M97: 11 | N97: 0.108 | O97: 1 | P97: 0.108 | Q97: 3.45 | R97: 3.45 | S97: 1439840 | T97: 1 | U97: 417344.93 | V97: 2.3960996
A98: 97 | B98: 97 | C98: CL1-097 | D98: CARLOW | E98: CARLOW | F98: SS-481 | G98: Castledockrell 110kV Substation | H98: EirGrid | I98: 110000 | J98: 20000 | K98: 110000 | L98: 10.637 | M98: 11 | N98: 0.364 | O98: 1 | P98: 0.364 | Q98: 3.45 | R98: 3.45 | S98: 1996170 | T98: 7 | U98: 578600 | V98: 1.7283097
A99: 98 | B99: 98 | C99: CL1-098 | D99: CARLOW | E99: WEXFORD | F99: SS-481 | G99: Castledockrell 110kV Substation | H99: EirGrid | I99: 110000 | J99: 20000 | K99: 110000 | L99: 9.874 | M99: 10 | N99: 0.328 | O99: 1 | P99: 0.328 | Q99: 3.45 | R99: 3.45 | S99: 1943470 | T99: 7 | U99: 563324.64 | V99: 1.7751753
A100: 99 | B100: 99 | C100: CL1-099 | D100: CARLOW | E100: CARLOW | F100: SS-494 | G100: Bunclody 38kV Substation | H100: ESB Networks | I100: 38000 | J100: 38000 | K100: 20000 | L100: 9.975 | M100: 10 | N100: 0.438 | O100: 1 | P100: 0.438 | Q100: 3.45 | R100: 3.45 | S100: 1387140 | T100: 1 | U100: 402069.57 | V100: 2.4871318
...

Sheet ETRI_Cost
B1: Tsiropoulos I, Tarvydas, D, Zucker, A, Cost development of low carbon energy technologies - Scenario-based cost trajectories to 2050, 2017 Edition, EUR 29034 EN, Publications Office of the European Union, Luxembourg, 2018, ISBN 978-92-79-77479-9, doi:10.2760/490059, JRC109894.
B2: Wind energy
B4: Input assumptions on learning rate method for onshore wind energy
D5: Unit | E5: 2015 | F5: 2020 | G5: 2025 | H5: 2030 | I5: 2035 | J5: 2040 | K5: 2045 | L5: 2050
B6: Global deployment | C6: Baseline | D6: GW | E6: 403.6677 | F6: 606.14927 | G6: 766.39753 | H6: 926.64579 | I6: 1073.6547 | J6: 1220.6637 | K6: 1370.5899 | L6: 1520.5162
C7: Diversified | D7: GW | E7: 403.6677 | F7: 785 | G7: 1222.5 | H7: 1660 | I7: 2043 | J7: 2426 | K7: 2731.5 | L7: 3037
C8: ProRES | D8: GW | E8: 403.6677 | F8: 783.88035 | G8: 1483.7708 | H8: 2183.6612 | I8: 2842.8862 | J8: 3502.1113 | K8: 3972.8269 | L8: 4443.5425
B9: Global capacity additions | C9: Baseline | D9: GW/year | E9: 45 | F9: 40 | G9: 38 | H9: 37 | I9: 57 | J9: 71 | K9: 65 | L9: 74
C10: Diversified | D10: GW/year | E10: 45 | F10: 76 | G10: 77 | H10: 109 | I10: 107 | J10: 115 | K10: 129 | L10: 147
C11: ProRES | D11: GW/year | E11: 45 | F11: 76 | G11: 133 | H11: 159 | I11: 165 | J11: 167 | K11: 185 | L11: 212
B12: Learning rate | C12: Reference | D12: % | E12: 0.05 | F12: 0.05 | G12: 0.05 | H12: 0.05 | I12: 0.05 | J12: 0.05 | K12: 0.05 | L12: 0.05
C13: High | D13: % | E13: 0.1 | F13: 0.1 | G13: 0.1 | H13: 0.1 | I13: 0.1 | J13: 0.1 | K13: 0.1 | L13: 0.1
C14: Low | D14: % | E14: 0.02 | F14: 0.02 | G14: 0.02 | H14: 0.02 | I14: 0.02 | J14: 0.02 | K14: 0.02 | L14: 0.02
B15: Lifetime | C15: - | D15: Years | E15: 25 | F15: 25 | G15: 25 | H15: 25 | I15: 25 | J15: 25 | K15: 25 | L15: 25
B17: Input assumptions on learning rate method for offshore wind energy
D18: Unit | E18: 2015 | F18: 2020 | G18: 2025 | H18: 2030 | I18: 2035 | J18: 2040 | K18: 2045 | L18: 2050
B19: Global deployment | C19: Baseline | D19: GW | E19: 11.6367 | F19: 29.848723 | G19: 38.287371 | H19: 46.726019 | I19: 60.041553 | J19: 73.357086 | K19: 90.638104 | L19: 107.91912
C20: Diversified | D20: GW | E20: 11.6367 | F20: 37.909091 | G20: 79.954545 | H20: 122 | I20: 194.5 | J20: 267 | K20: 352 | L20: 437
C21: ProRES | D21: GW | E21: 11.6367 | F21: 36.515154 | G21: 181.50429 | H21: 326.49342 | I21: 570.1989 | J21: 813.90439 | K21: 972.55366 | L21: 1131.2029
B22: Global capacity additions | C22: Baseline | D22: GW/year | E22: 2 | F22: 4 | G22: 2 | H22: 2 | I22: 3 | J22: 3 | K22: 5 | L22: 7
C23: Diversified | D23: GW/year | E23: 2 | F23: 5 | G23: 5 | H23: 12 | I23: 14 | J23: 15 | K23: 17 | L23: 24
C24: ProRES | D24: GW/year | E24: 2 | F24: 5 | G24: 21 | H24: 37 | I24: 49 | J24: 49 | K24: 44 | L24: 26
B25: Learning rate | C25: Reference | D25: % | E25: 0.11 | F25: 0.11 | G25: 0.08 | H25: 0.05 | I25: 0.05 | J25: 0.05 | K25: 0.05 | L25: 0.05
C26: High | D26: % | E26: 0.2 | F26: 0.2 | G26: 0.15 | H26: 0.1 | I26: 0.1 | J26: 0.1 | K26: 0.1 | L26: 0.1
C27: Low | D27: % | E27: 0.05 | F27: 0.05 | G27: 0.05 | H27: 0.02 | I27: 0.02 | J27: 0.02 | K27: 0.02 | L27: 0.02
B28: Lifetime | C28: - | D28: Years | E28: 30 | F28: 30 | G28: 30 | H28: 30 | I28: 30 | J28: 30 | K28: 30 | L28: 30
B31: Capital investment cost trajectories of onshore wind turbines (low specific capacity, high hub height)
D32: Unit | E32: 2015 | F32: 2020 | G32: 2030 | H32: 2040 | I32: 2050
B33: Capital investment costs | C33: Baseline | D33: EUR 2015/kW | E33: 1850 | F33: 1800 | G33: 1730 | H33: 1670 | I33: 1630
C34: Diversified | D34: EUR 2015/kW | E34: 1850 | F34: 1760 | G34: 1660 | H34: 1600 | I34: 1560
C35: ProRES | D35: EUR 2015/kW | E35: 1850 | F35: 1760 | G35: 1630 | H35: 1560 | I35: 1520
C36: Min | D36: EUR 2015/kW | E36: 1850 | F36: 1670 | G36: 1430 | H36: 1310 | I36: 1230
C37: Max | D37: EUR 2015/kW | E37: 1850 | F37: 1830 | G37: 1800 | H37: 1780 | I37: 1760
B38: O&M costs | C38: - | D38: %CAPEX | E38: 0.03 | F38: 0.03 | G38: 0.03 | H38: 0.03 | I38: 0.03
B41: Capital investment cost trajectories of onshore wind turbines (medium specific capacity, medium hub height)
D42: Unit | E42: 2015 | F42: 2020 | G42: 2030 | H42: 2040 | I42: 2050
B43: Capital investment costs | C43: Baseline | D43: EUR 2015/kW | E43: 1350 | F43: 1310 | G43: 1260 | H43: 1220 | I43: 1190
C44: Diversified | D44: EUR 2015/kW | E44: 1350 | F44: 1290 | G44: 1210 | H44: 1170 | I44: 1130
C45: ProRES | D45: EUR 2015/kW | E45: 1350 | F45: 1290 | G45: 1190 | H45: 1140 | I45: 1110
C46: Min | D46: EUR 2015/kW | E46: 1350 | F46: 1220 | G46: 1040 | H46: 960 | I46: 900
C47: Max | D47: EUR 2015/kW | E47: 1350 | F47: 1330 | G47: 1320 | H47: 1300 | I47: 1280
B48: O&M costs | C48: - | D48: %CAPEX | E48: 0.03 | F48: 0.03 | G48: 0.03 | H48: 0.03 | I48: 0.03
B51: Capital investment cost trajectories of onshore wind turbines (high specific capacity, low hub height)
D52: Unit | E52: 2015 | F52: 2020 | G52: 2030 | H52: 2040 | I52: 2050
B53: Capital investment costs | C53: Baseline | D53: EUR 2015/kW | E53: 1090 | F53: 1060 | G53: 1020 | H53: 980 | I53: 960
C54: Diversified | D54: EUR 2015/kW | E54: 1090 | F54: 1040 | G54: 980 | H54: 940 | I54: 920
C55: ProRES | D55: EUR 2015/kW | E55: 1090 | F55: 1040 | G55: 960 | H55: 920 | I55: 890
C56: Min | D56: EUR 2015/kW | E56: 1090 | F56: 990 | G56: 840 | H56: 770 | I56: 730
C57: Max | D57: EUR 2015/kW | E57: 1090 | F57: 1080 | G57: 1060 | H57: 1050 | I57: 1040
B58: O&M costs | C58: - | D58: %CAPEX | E58: 0.03 | F58: 0.03 | G58: 0.03 | H58: 0.03 | I58: 0.03
B60: Capital investment cost trajectories of offshore wind turbines (monopole, medium distance to shore)
D61: Unit | E61: 2015 | F61: 2020 | G61: 2030 | H61: 2040 | I61: 2050
B62: Capital investment costs | C62: Baseline | D62: EUR 2015/kW | E62: 3500 | F62: 2990 | G62: 2850 | H62: 2750 | I62: 2640
A63: P-RNW-WIN-OF02 | C63: Diversified | D63: EUR 2015/kW | E63: 3500 | F63: 2870 | G63: 2570 | H63: 2430 | I63: 2330
C64: ProRES | D64: EUR 2015/kW | E64: 3500 | F64: 2890 | G64: 2310 | H64: 2150 | I64: 2100
C65: Min | D65: EUR 2015/kW | E65: 3500 | F65: 2390 | G65: 1550 | H65: 1350 | I65: 1280
C66: Max | D66: EUR 2015/kW | E66: 3500 | F66: 3260 | G66: 3180 | H66: 3140 | I66: 3090
B67: O&M costs | C67: - | D67: %CAPEX | E67: 0.02 | F67: 0.02 | G67: 0.02 | H67: 0.02 | I67: 0.02
B70: Capital investment cost trajectories of offshore wind turbines (jacket, medium distance to shore)
D71: Unit | E71: 2015 | F71: 2020 | G71: 2030 | H71: 2040 | I71: 2050
B72: Capital investment costs | C72: Baseline | D72: EUR 2015/kW | E72: 3600 | F72: 3070 | G72: 2940 | H72: 2830 | I72: 2710
C73: Diversified | D73: EUR 2015/kW | E73: 3600 | F73: 2950 | G73: 2650 | H73: 2490 | I73: 2390
C74: ProRES | D74: EUR 2015/kW | E74: 3600 | F74: 2970 | G74: 2370 | H74: 2220 | I74: 2160
C75: Min | D75: EUR 2015/kW | E75: 3600 | F75: 2460 | G75: 1600 | H75: 1390 | I75: 1320
C76: Max | D76: EUR 2015/kW | E76: 3600 | F76: 3360 | G76: 3280 | H76: 3230 | I76: 3170
B77: O&M costs | C77: - | D77: %CAPEX | E77: 0.02 | F77: 0.02 | G77: 0.02 | H77: 0.02 | I77: 0.02
B80: Capital investment cost trajectories of offshore wind turbines (floating, long distance to shore)
D81: Unit | E81: 2015 | F81: 2020 | G81: 2030 | H81: 2040 | I81: 2050
B82: Capital investment costs | C82: Baseline | D82: EUR 2015/kW | E82: 5500 | F82: 4690 | G82: 4490 | H82: 4330 | I82: 4140
C83: Diversified | D83: EUR 2015/kW | E83: 5500 | F83: 4510 | G83: 4040 | H83: 3810 | I83: 3660
C84: ProRES | D84: EUR 2015/kW | E84: 5500 | F84: 4540 | G84: 3620 | H84: 3390 | I84: 3300
C85: Min | D85: EUR 2015/kW | E85: 5500 | F85: 3760 | G85: 2440 | H85: 2120 | I85: 2010
C86: Max | D86: EUR 2015/kW | E86: 5500 | F86: 5130 | G86: 5000 | H86: 4930 | I86: 4850
B87: O&M costs | C87: - | D87: %CAPEX | E87: 0.02 | F87: 0.02 | G87: 0.02 | H87: 0.02 | I87: 0.02
B89: Input assumptions on learning rate method for photovoltaics
D90: Unit | E90: 2015 | F90: 2020 | G90: 2025 | H90: 2030 | I90: 2035 | J90: 2040 | K90: 2045 | L90: 2050
B91: Global deployment | C91: Baseline | D91: GW | E91: 220 | F91: 424.27247 | G91: 533.59459 | H91: 642.9167 | I91: 833.73054 | J91: 1024.5444 | K91: 1244.4583 | L91: 1464.3722
C92: Diversified | D92: GW | E92: 220 | F92: 491.63636 | G92: 826.81818 | H92: 1162 | I92: 1851 | J92: 2540 | K92: 3482 | L92: 4424
C93: ProRES | D93: GW | E93: 220 | F93: 732.07457 | G93: 1785.3218 | H93: 2838.5691 | I93: 3913.0396 | J93: 4987.5101 | K93: 5866.1956 | L93: 6744.881
B94: Global capacity additions | C94: Baseline | D94: GW/year | E94: 36.24594 | F94: 40.827895 | G94: 23.435159 | H94: 21.196686 | I94: 25.577992 | J94: 93.871146 | K94: 91.576353 | L94: 60.65226
C95: Diversified | D95: GW/year | E95: 36.24594 | F95: 54.300673 | G95: 52.434247 | H95: 82.54148 | I95: 128.67766 | J95: 190.04594 | K95: 242.50067 | L95: 241.03425
C96: ProRES | D96: GW/year | E96: 36.24594 | F96: 102.38831 | G96: 174.43864 | H96: 247.76327 | I96: 232.68181 | J96: 240.23 | K96: 283.37477 | L96: 344.92636
B97: Learning rate | C97: Reference | D97: % | E97: 0.2 | F97: 0.2 | G97: 0.2 | H97: 0.2 | I97: 0.2 | J97: 0.2 | K97: 0.2 | L97: 0.2
C98: High | D98: % | E98: 0.23 | F98: 0.23 | G98: 0.23 | H98: 0.23 | I98: 0.23 | J98: 0.23 | K98: 0.23 | L98: 0.23
C99: Low | D99: % | E99: 0.1 | F99: 0.1 | G99: 0.1 | H99: 0.1 | I99: 0.1 | J99: 0.1 | K99: 0.1 | L99: 0.1
B100: Lifetime | C100: - | D100: Years | E100: 25 | F100: 25 | G100: 25 | H100: 25 | I100: 25 | J100: 25 | K100: 25 | L100: 25
B102: Capital investment cost trajectories of utility-scale photovoltaics with one-axis tracking
D103: Unit | E103: 2015 | F103: 2020 | G103: 2030 | H103: 2040 | I103: 2050
B104: Capital investment costs | C104: Baseline | D104: EUR 2015/kW | E104: 1120 | F104: 910 | G104: 790 | H104: 640 | I104: 550
A105: P-RNW-SOL-PV03 | C105: Diversified | D105: EUR 2015/kW | E105: 1120 | F105: 860 | G105: 650 | H105: 500 | I105: 410
C106: ProRES | D106: EUR 2015/kW | E106: 1120 | F106: 760 | G106: 490 | H106: 400 | I106: 350
C107: Min | D107: EUR 2015/kW | E107: 1120 | F107: 710 | G107: 430 | H107: 340 | I107: 280
C108: Max | D108: EUR 2015/kW | E108: 1120 | F108: 1010 | G108: 950 | H108: 860 | I108: 800
B109: O&M costs | C109: - | D109: %CAPEX | E109: 0.023 | F109: 0.023 | G109: 0.023 | H109: 0.023 | I109: 0.023
B112: Capital investment cost trajectories of utility-scale photovoltaics without tracking
D113: Unit | E113: 2015 | F113: 2020 | G113: 2030 | H113: 2040 | I113: 2050
B114: Capital investment costs | C114: Baseline | D114: EUR 2015/kW | E114: 1020 | F114: 830 | G114: 720 | H114: 580 | I114: 500
A115: P-RNW-SOL-PV02 | C115: Diversified | D115: EUR 2015/kW | E115: 1020 | F115: 790 | G115: 600 | H115: 450 | I115: 370
C116: ProRES | D116: EUR 2015/kW | E116: 1020 | F116: 690 | G116: 450 | H116: 370 | I116: 320
C117: Min | D117: EUR 2015/kW | E117: 1020 | F117: 650 | G117: 390 | H117: 310 | I117: 260
...
